Workbook

Sheet PROJEÇÃO 2025
A1: META ANUAL: R$5.000.000,00 | F1: META | H1: REALIZADO | I1: % REALIZADA | K1: META | M1: REALIZADO | N1: % REALIZADA | P1: META | R1: REALIZADO | S1: % REALIZADA
A2: MESES | B2: FATURAMENTO | C2: META | D2: % META | F2: META FATURAMENTO | G2: 250000 | H2: =JANEIRO!E65 -> 302600 | I2: =H2/G2 -> 1.2104 | K2: META FATURAMENTO | L2: 300000 | M2: =FEVEREIRO!E64 -> 390450 | N2: =M2/L2 -> 1.3015 | P2: META FATURAMENTO | Q2: 350000 | R2: ='MARÇO'!E69 -> 343280 | S2: =R2/Q2 -> 0.9808
A3: JANEIRO | B3: =JANEIRO!E65 -> 302600 | C3: =G2 -> 250000 | D3: =B3/C3 -> 1.2104 | F3: LIGAÇÃO | G3: 110 | H3: 14 | I3: =H3/G3 -> 0.12727273 | K3: LIGAÇÃO | L3: 110 | M3: 22 | N3: =M3/L3 -> 0.2 | P3: LIGAÇÃO | Q3: 110 | R3: 6 | S3: =R3/Q3 -> 0.054545455
A4: FEVEREIRO | B4: =FEVEREIRO!E64 -> 390450 | C4: =L2 -> 300000 | D4: =B4/C4 -> 1.3015 | F4: CARGAS | G4: 50 | H4: 32 | I4: =H4/G4 -> 0.64 | K4: CARGAS | L4: 50 | M4: 40 | N4: =M4/L4 -> 0.8 | P4: CARGAS | Q4: 50 | R4: 43 | S4: =R4/Q4 -> 0.86
A5: MARÇO | B5: ='MARÇO'!E69 -> 343280 | C5: =Q2 -> 350000 | D5: =B5/C5 -> 0.9808 | F5: COMISSÃO | G5: 12000 | H5: 10400 | I5: =H5/G5 -> 0.86666667 | K5: COMISSÃO | L5: 14000 | M5: 14500 | N5: =M5/L5 -> 1.0357143 | P5: COMISSÃO | Q5: 14000 | R5: 13420 | S5: =R5/Q5 -> 0.95857143
A6: ABRIL | B6: =ABRIL!E65 -> 339900 | C6: =G12 -> 300000 | D6: =B6/C6 -> 1.133 | F6: CLIENTES NOVOS | G6: 3 | H6: 1 | I6: =H6/G6 -> 0.33333333 | K6: CLIENTES NOVOS | L6: 3 | M6: 1 | N6: =M6/L6 -> 0.33333333 | P6: CLIENTES NOVOS | Q6: 3 | R6: 1 | S6: =R6/Q6 -> 0.33333333
A7: MAIO | B7: =MAIO!E61 -> 320880 | C7: =L12 -> 350000 | D7: =B7/C7 -> 0.9168 | F7: JANEIRO | K7: FEVEREIRO | P7: MARÇO
A8: JUNHO | B8: =JUNHO!E77 -> 416920 | C8: 350000 | D8: =B8/C8 -> 1.1912
A9: JULHO | B9: =JULHO!E76 -> 353400 | C9: =G22 -> 420000 | D9: =B9/C9 -> 0.84142857
A10: AGOSTO | B10: =AGOSTO!E71 -> 306620 | C10: =L22 -> 420000 | D10: =B10/C10 -> 0.73004762
A11: SETEMBRO | B11: =SETEMBRO!E79 -> 400120 | C11: =Q22 -> 420000 | D11: =B11/C11 -> 0.95266667 | F11: META | H11: REALIZADO | I11: % REALIZADA | K11: META | M11: REALIZADO | N11: % REALIZADA | P11: META | R11: REALIZADO | S11: % REALIZADA
A12: OUTUBRO | B12: =OUTUBRO!E87 -> 401623 | C12: 420000 | D12: =B12/C12 -> 0.95624524 | F12: META FATURAMENTO | G12: 300000 | H12: =ABRIL!E65 -> 339900 | I12: =H12/G12 -> 1.133 | K12: META FATURAMENTO | L12: 350000 | M12: 417190 | N12: =M12/L12 -> 1.1919714 | P12: META FATURAMENTO | Q12: 420000 | R12: 359000 | S12: =R12/Q12 -> 0.8547619
A13: NOVEMBRO | B13: =NOVEMBRO!E87 -> 341975 | C13: 420000 | D13: =B13/C13 -> 0.81422619 | F13: LIGAÇÃO | G13: 110 | H13: 44 | I13: =H13/G13 -> 0.4 | K13: LIGAÇÃO | L13: 110 | M13: 51 | N13: =M13/L13 -> 0.46363636 | P13: LIGAÇÃO | Q13: 110 | R13: 41 | S13: =R13/Q13 -> 0.37272727
A14: DEZEMBRO | B14: =DEZEMBRO!E87 -> 296575 | C14: 325000 | D14: =B14/C14 -> 0.91253846 | F14: CARGAS | G14: 50 | H14: 41 | I14: =H14/G14 -> 0.82 | K14: CARGAS | L14: 50 | M14: 58 | N14: =M14/L14 -> 1.16 | P14: CARGAS | Q14: 50 | R14: 55 | S14: =R14/Q14 -> 1.1
A15: TOTAL: | B15: =SUM(B3:B14) -> 4214343 | C15: =SUM(C3:C14) -> 4325000 | D15: =AVERAGE(D3:D14) -> 0.99507106 | F15: COMISSÃO | G15: 15000 | H15: 13118.32 | I15: =H15/G15 -> 0.87455467 | K15: COMISSÃO | L15: 15000 | M15: 15848.91 | N15: =M15/L15 -> 1.056594 | P15: COMISSÃO | Q15: 15000 | R15: 13095.95 | S15: =R15/Q15 -> 0.87306333
F16: CLIENTES NOVOS | G16: 3 | H16: 0 | I16: =H16/G16 -> 0 | K16: CLIENTES NOVOS | L16: 3 | M16: 1 | N16: =M16/L16 -> 0.33333333 | P16: CLIENTES NOVOS | Q16: 3 | R16: 0 | S16: =R16/Q16 -> 0
F17: ABRIL | K17: JUNHO | P17: JULHO
F21: META | H21: REALIZADO | I21: % REALIZADA | K21: META | M21: REALIZADO | N21: % REALIZADA | P21: META | R21: REALIZADO | S21: % REALIZADA
F22: META FATURAMENTO | G22: 420000 | H22: 310620 | I22: =H22/G22 -> 0.73957143 | K22: META FATURAMENTO | L22: 420000 | M22: 400220 | N22: =M22/L22 -> 0.95290476 | P22: META FATURAMENTO | Q22: 420000 | R22: =B12 -> 401623 | S22: =R22/Q22 -> 0.95624524
F23: LIGAÇÃO | G23: 110 | H23: 44 | I23: =H23/G23 -> 0.4 | K23: LIGAÇÃO | L23: 110 | M23: 24 | N23: =M23/L23 -> 0.21818182 | P23: LIGAÇÃO | Q23: 110 | R23: 14 | S23: =R23/Q23 -> 0.12727273
F24: CARGAS | G24: 50 | H24: 44 | I24: =H24/G24 -> 0.88 | K24: CARGAS | L24: 50 | M24: 61 | N24: =M24/L24 -> 1.22 | P24: CARGAS | Q24: 50 | R24: 60 | S24: =R24/Q24 -> 1.2
F25: COMISSÃO | G25: 15000 | H25: 9881.8 | I25: =H25/G25 -> 0.65878667 | K25: COMISSÃO | L25: 15000 | M25: 13605.51 | N25: =M25/L25 -> 0.907034 | P25: COMISSÃO | Q25: 15000 | R25: 13519.26 | S25: =R25/Q25 -> 0.901284
F26: CLIENTES NOVOS | G26: 3 | H26: 0 | I26: =H26/G26 -> 0 | K26: CLIENTES NOVOS | L26: 3 | M26: 2 | N26: =M26/L26 -> 0.66666667 | P26: CLIENTES NOVOS | Q26: 3 | R26: 0 | S26: =R26/Q26 -> 0
F27: AGOSTO | K27: SETEMBRO | P27: OUTUBRO
F31: META | H31: REALIZADO | I31: % REALIZADA | K31: META | M31: REALIZADO | N31: % REALIZADA
F32: META FATURAMENTO | G32: 420000 | H32: =B13 -> 341975 | I32: =H32/G32 -> 0.81422619 | K32: META FATURAMENTO | L32: 325000 | M32: =B14 -> 296575 | N32: =M32/L32 -> 0.91253846
F33: LIGAÇÃO | G33: 110 | H33: 15 | I33: =H33/G33 -> 0.13636364 | K33: LIGAÇÃO | L33: 180 | M33: 48 | N33: =M33/L33 -> 0.26666667
F34: CARGAS | G34: 50 | H34: 54 | I34: =H34/G34 -> 1.08 | K34: CARGAS | L34: 50 | M34: =DEZEMBRO!M134+DEZEMBRO!M135 -> 27 | N34: =M34/L34 -> 0.54
F35: COMISSÃO | G35: 15000 | H35: 13000 | I35: =H35/G35 -> 0.86666667 | K35: COMISSÃO | L35: 13000 | M35: =DEZEMBRO!F87 -> 12283.703 | N35: =M35/L35 -> 0.94490023
F36: CLIENTES NOVOS | G36: 3 | H36: 1 | I36: =H36/G36 -> 0.33333333 | K36: CLIENTES NOVOS | L36: 3 | M36: 1 | N36: =M36/L36 -> 0.33333333
F37: NOVEMBRO | K37: DEZEMBRO

Sheet FEEDBACK SEMANAL
A1: RELATÓRIO SEMANA (23/04 - 29/04)
A2: INDICADORES | B2: META | C2: RESULTADOS
A3: LIGAÇÕES / 5 | B3: 12 | C3: 12
A4: CARGAS / 5 | B4: 3 | C4: 2
A5: LEADS ADICIONADOS | B5: 10 | C5: 11
A7: PORCENTAGEM META | B7: 1 | C7: ='ABRIL - 2026'!G85 -> 0.86347826
A8: FATURAMENTO | B8: 460000 | C8: ='ABRIL - 2026'!E79 -> 397200
A10: LEADS DECLINADOS | B10: 5
A12: CLIENTE POTENCIAIS | C12: CLIENTE POTENCIAIS NOVOS
A13: VOESTALPINE | C13: DINOPLAST
A14: VIPAL | C14: BRASPLAST
A15: SULPRINT | C15: VIRTUS
A139: REGRA DE 3 - PORCENTUAL FATURAMENTO
A140: 22 | B140: 1
A141: 12 | B141: =A141*B140/A140 -> 0.54545455

Sheet PROJEÇÃO 2026
A1: META ANUAL: R$7.000.000,00 | G1: META | I1: REALIZADO | J1: % REALIZADA | L1: META | N1: REALIZADO | O1: % REALIZADA | Q1: META | S1: REALIZADO | T1: % REALIZADA
A2: MESES | B2: FATURAMENTO | C2: META PESSOAL | D2: META | E2: % META | G2: META FATURAMENTO | H2: ='JANEIRO - 2026'!G93 -> 325000 | I2: =B3 -> 355490 | J2: =I2/H2 -> 1.0938154 | L2: META FATURAMENTO | M2: 400000 | N2: =B4 -> 282310 | O2: =N2/M2 -> 0.705775 | Q2: META FATURAMENTO | R2: 350000 | S2: =B5 -> 450530 | T2: =S2/R2 -> 1.2872286
A3: JANEIRO | B3: ='JANEIRO - 2026'!G98 -> 355490 | C3: 420000 | D3: =H2 -> 325000 | E3: =B3/D3 -> 1.0938154 | G3: LIGAÇÃO | H3: 110 | I3: 38 | J3: =I3/H3 -> 0.34545455 | L3: LIGAÇÃO | M3: 110 | N3: 115 | O3: =N3/M3 -> 1.0454545 | Q3: LIGAÇÃO | R3: 110 | S3: ='MARÇO - 2026'!J151 -> 94 | T3: =S3/R3 -> 0.85454545
A4: FEVEREIRO | B4: ='FEVEREIRO - 2026'!G98 -> 282310 | C4: 420000 | D4: 400000 | E4: =B4/D4 -> 0.705775 | G4: CARGAS | H4: 50 | I4: ='JANEIRO - 2026'!T134+'JANEIRO - 2026'!T135 -> 62 | J4: =I4/H4 -> 1.24 | L4: CARGAS | M4: 50 | N4: ='FEVEREIRO - 2026'!M134+'FEVEREIRO - 2026'!M135 -> 65 | O4: =N4/M4 -> 1.3 | Q4: CARGAS | R4: 50 | S4: ='MARÇO - 2026'!M144+'MARÇO - 2026'!M145 -> 81 | T4: =S4/R4 -> 1.62
A5: MARÇO | B5: ='MARÇO - 2026'!G108 -> 450530 | C5: 420000 | D5: =R2 -> 350000 | E5: =B5/D5 -> 1.2872286 | G5: COMISSÃO | H5: 15000 | I5: ='JANEIRO - 2026'!F87 -> 13387.191 | J5: =I5/H5 -> 0.89247943 | L5: COMISSÃO | M5: 14000 | N5: ='FEVEREIRO - 2026'!F86 -> 11868.619 | O5: =N5/M5 -> 0.84775848 | Q5: COMISSÃO | R5: 14000 | S5: ='MARÇO - 2026'!F97 -> 15813.763 | T5: =S5/R5 -> 1.1295545
A6: ABRIL | B6: ='ABRIL - 2026'!E79 -> 397200 | C6: 420000 | D6: =H12 -> 460000 | E6: =B6/D6 -> 0.86347826 | G6: CLIENTES NOVOS | H6: 3 | I6: 1 | J6: =I6/H6 -> 0.33333333 | L6: CLIENTES NOVOS | M6: 3 | N6: 1 | O6: =N6/M6 -> 0.33333333 | Q6: CLIENTES NOVOS | R6: 3 | S6: 2 | T6: =S6/R6 -> 0.66666667
A7: MAIO | B7: ='MAIO - 2026'!E78 -> 380491 | C7: 420000 | D7: =M12 -> 450000 | E7: =B7/D7 -> 0.84553556 | G7: JANEIRO | L7: FEVEREIRO | Q7: MARÇO
A8: JUNHO | B8: ='JUNHO - 2026'!E79 -> 2910 | C8: 420000 | D8: =M12 -> 450000 | E8: =B8/D8 -> 0.0064666667
A9: JULHO | B9: ='JULHO - 2026'!E80 -> 0 | C9: 420000 | D9: =H22 -> 700000 | E9: =B9/D9 -> 0
A10: AGOSTO | B10: ='AGOSTO - 2026'!E80 -> 0 | C10: 420000 | D10: =M22 -> 700000 | E10: =B10/D10 -> 0
A11: SETEMBRO | B11: ='SETEMBRO - 2026'!E80 -> 0 | C11: 420000 | D11: =R22 -> 750000 | E11: =B11/D11 -> 0 | G11: META | I11: REALIZADO | J11: % REALIZADA | L11: META | N11: REALIZADO | O11: % REALIZADA | Q11: META | S11: REALIZADO | T11: % REALIZADA
A12: OUTUBRO | B12: ='OUTUBRO - 2026'!E80 -> 0 | C12: 420000 | D12: =R22 -> 750000 | E12: =B12/D12 -> 0 | G12: META FATURAMENTO | H12: 460000 | I12: ='ABRIL - 2026'!G89 -> 397200 | J12: =I12/H12 -> 0.86347826 | L12: META FATURAMENTO | M12: 450000 | N12: ='MAIO - 2026'!E78 -> 380491 | O12: =N12/M12 -> 0.84553556 | Q12: META FATURAMENTO | R12: 600000 | S12: ='JUNHO - 2026'!E79 -> 2910 | T12: =S12/R12 -> 0.00485
A13: NOVEMBRO | B13: ='NOVEMBRO - 2026'!E80 -> 0 | C13: 420000 | D13: =H32 -> 700000 | E13: =B13/D13 -> 0 | G13: LIGAÇÃO | H13: 110 | I13: 64 | J13: =I13/H13 -> 0.58181818 | L13: LIGAÇÃO | M13: 110 | N13: 144 | O13: =N13/M13 -> 1.3090909 | Q13: LIGAÇÃO | R13: 110 | S13: ='JUNHO - 2026'!J134 | T13: =S13/R13 -> 0
A14: DEZEMBRO | B14: ='DEZEMBRO - 2026'!E80 -> 0 | C14: 420000 | D14: =M32 -> 600000 | E14: =B14/D14 -> 0 | G14: CARGAS | H14: 50 | I14: 58 | J14: =I14/H14 -> 1.16 | L14: CARGAS | M14: 50 | N14: ='MAIO - 2026'!N126+'MAIO - 2026'!N127 -> 60 | O14: =N14/M14 -> 1.2 | Q14: CARGAS | R14: 50 | S14: ='JUNHO - 2026'!K133 -> 39 | T14: =S14/R14 -> 0.78
A15: TOTAL: | B15: =SUM(B3:B14) -> 1868931 | C15: =SUM(C3:C14) -> 5040000 | D15: =SUM(D3:D14) -> 6635000 | E15: =AVERAGE(E3:E14) -> 0.40019162 | G15: COMISSÃO | H15: 17000 | I15: ='ABRIL - 2026'!F79 -> 10532.041 | J15: =I15/H15 -> 0.61953183 | L15: COMISSÃO | M15: 20000 | N15: ='MAIO - 2026'!F78 -> 16250.473 | O15: =N15/M15 -> 0.81252365 | Q15: COMISSÃO | R15: 25000 | S15: ='JUNHO - 2026'!F79 -> 131.7 | T15: =S15/R15 -> 0.005268
G16: CLIENTES NOVOS | H16: 3 | I16: 2 | J16: =I16/H16 -> 0.66666667 | L16: CLIENTES NOVOS | M16: 3 | N16: 0 | O16: =N16/M16 -> 0 | Q16: CLIENTES NOVOS | R16: 3 | S16: 0 | T16: =S16/R16 -> 0
G17: ABRIL | L17: MAIO | Q17: JUNHO
A19: META | C19: REALIZADO | D19: % REALIZADA
A20: META FATURAMENTO | B20: 325000 | C20: =279475+9900 -> 289375 | D20: =C20/B20 -> 0.89038462
A21: LIGAÇÃO | B21: 110 | C21: 75 | D21: =C21/B21 -> 0.68181818 | G21: META | I21: REALIZADO | J21: % REALIZADA | L21: META | N21: REALIZADO | O21: % REALIZADA | Q21: META | S21: REALIZADO | T21: % REALIZADA
A22: CARGAS | B22: 50 | C22: 49 | D22: =C22/B22 -> 0.98 | G22: META FATURAMENTO | H22: 700000 | I22: ='JULHO - 2026'!E80 -> 0 | J22: =I22/H22 -> 0 | L22: META FATURAMENTO | M22: 700000 | N22: ='AGOSTO - 2026'!E80 -> 0 | O22: =N22/M22 -> 0 | Q22: META FATURAMENTO | R22: 750000 | S22: ='SETEMBRO - 2026'!E80 -> 0 | T22: =S22/R22 -> 0
A23: COMISSÃO | B23: 15000 | C23: 12044.11 | D23: =C23/B23 -> 0.80294067 | G23: LIGAÇÃO | H23: 110 | I23: ='JULHO - 2026'!J134 -> 0 | J23: =I23/H23 -> 0 | L23: LIGAÇÃO | M23: 110 | N23: ='AGOSTO - 2026'!J134 -> 0 | O23: =N23/M23 -> 0 | Q23: LIGAÇÃO | R23: 110 | S23: ='SETEMBRO - 2026'!J134 -> 0 | T23: =S23/R23 -> 0
A24: CLIENTES NOVOS | B24: 3 | C24: 0 | D24: =C24/B24 -> 0 | G24: CARGAS | H24: 50 | I24: ='JULHO - 2026'!M127+'JULHO - 2026'!M128 -> 0 | J24: =I24/H24 -> 0 | L24: CARGAS | M24: 50 | N24: ='AGOSTO - 2026'!M127+'AGOSTO - 2026'!M128 -> 0 | O24: =N24/M24 -> 0 | Q24: CARGAS | R24: 50 | S24: ='SETEMBRO - 2026'!M127+'SETEMBRO - 2026'!M128 -> 0 | T24: =S24/R24 -> 0
A25: DEZEMBRO - 2025 - PARÂMETRO | G25: COMISSÃO | H25: 30000 | I25: ='JULHO - 2026'!F80 -> 0 | J25: =I25/H25 -> 0 | L25: COMISSÃO | M25: 35000 | N25: ='AGOSTO - 2026'!F80 -> 0 | O25: =N25/M25 -> 0 | Q25: COMISSÃO | R25: 38000 | S25: ='SETEMBRO - 2026'!F80 -> 0 | T25: =S25/R25 -> 0
G26: CLIENTES NOVOS | H26: 3 | I26: 0 | J26: =I26/H26 -> 0 | L26: CLIENTES NOVOS | M26: 3 | N26: 0 | O26: =N26/M26 -> 0 | Q26: CLIENTES NOVOS | R26: 3 | S26: 0 | T26: =S26/R26 -> 0
G27: JULHO | L27: AGOSTO | Q27: SETEMBRO
G31: META | I31: REALIZADO | J31: % REALIZADA | L31: META | N31: REALIZADO | O31: % REALIZADA | Q31: META | S31: REALIZADO | T31: % REALIZADA
G32: META FATURAMENTO | H32: 700000 | I32: ='OUTUBRO - 2026'!E80 -> 0 | J32: =I32/H32 -> 0 | L32: META FATURAMENTO | M32: 600000 | N32: ='NOVEMBRO - 2026'!E80 -> 0 | O32: =N32/M32 -> 0 | Q32: META FATURAMENTO | R32: 600000 | S32: ='DEZEMBRO - 2026'!E80 -> 0 | T32: =S32/R32 -> 0
G33: LIGAÇÃO | H33: 110 | I33: ='OUTUBRO - 2026'!J134 -> 0 | J33: =I33/H33 -> 0 | L33: LIGAÇÃO | M33: 180 | N33: ='NOVEMBRO - 2026'!J134 -> 0 | O33: =N33/M33 -> 0 | Q33: LIGAÇÃO | R33: 180 | S33: ='DEZEMBRO - 2026'!J134 -> 0 | T33: =S33/R33 -> 0
G34: CARGAS | H34: 50 | I34: ='OUTUBRO - 2026'!M127+'OUTUBRO - 2026'!M128 -> 0 | J34: =I34/H34 -> 0 | L34: CARGAS | M34: 50 | N34: ='NOVEMBRO - 2026'!M127+'NOVEMBRO - 2026'!M128 -> 0 | O34: =N34/M34 -> 0 | Q34: CARGAS | R34: 50 | S34: ='DEZEMBRO - 2026'!M127+'DEZEMBRO - 2026'!M128 -> 0 | T34: =S34/R34 -> 0
G35: COMISSÃO | H35: 350000 | I35: ='OUTUBRO - 2026'!F80 -> 0 | J35: =I35/H35 -> 0 | L35: COMISSÃO | M35: 35000 | N35: ='NOVEMBRO - 2026'!F80 -> 0 | O35: =N35/M35 -> 0 | Q35: COMISSÃO | R35: 35000 | S35: ='DEZEMBRO - 2026'!F80 -> 0 | T35: =S35/R35 -> 0
G36: CLIENTES NOVOS | H36: 3 | I36: 0 | J36: =I36/H36 -> 0 | L36: CLIENTES NOVOS | M36: 3 | N36: 1 | O36: =N36/M36 -> 0.33333333 | Q36: CLIENTES NOVOS | R36: 3 | S36: 1 | T36: =S36/R36 -> 0.33333333
G37: OUTUBRO | L37: NOVEMBRO | Q37: DEZEMBRO

Sheet JANEIRO - 2026
A1: GODI TRANSPORTES - UNINDO PROPÓSITOS
A3: DATA | B3: CTE | C3: MANIFESTO | D3: ORIGEM | E3: ESTADO | F3: DESTINO | G3: ESTADO | H3: CLIENTE | I3: PAGAMENTO | J3: CONFERENCIA | K3: MOTORISTA | L3: TELEFONE | M3: VALOR MOTORISTA | N3: VALOR EMPRESA | O3: NF | P3: SEGURO | Q3: SEGURO | R3: ICMS | S3: ICMS | T3: C.O | V3: CO | W3: IMPOSTO | X3: IMPOSTO | Y3: BOLETO | Z3: DIA PAG | AA3: TOTAL TAXAS | AB3: VALOR IMPOSTO | AC3: % | AD3: COMISSÕES | AE3: BOLETOS | AF3: LUCRO | AG3: RENTABIL | AH3: FRETE LIQ | AI3: MOVA | AJ3: ADQ TAB | AK3: VALOR
A4: 46024 | B4: 28238 - 28237 | D4: SÃO LEOPOLDO | E4: RS | F4: CAXIAS DO SUL | G4: RS | H4: CYA RUBBER | I4: FINALIZADO | J4: SIM | K4: PEDRO PAULO DOS SANTOS | M4: 1760 | N4: 2980 | O4: 250000 | P4: 0.0003 | Q4: =O4*P4 -> 75 | R4: 0 | S4: =R4*N4 -> 0 | T4: 0.035 | U4: 1 | V4: =T4*N4 -> 104.3 | W4: 0.065 | X4: =N4*W4 -> 193.7 | Y4: =Z4*0.00133 -> 0.01995 | Z4: 15 | AA4: =R4+T4+W4+Y4 -> 0.11995 | AB4: =N4*AA4+AK4 -> 382.781 | AC4: 0.13 | AD4: =(N4-M4)*AC4 -> 158.6 | AE4: =17.5 -> 17.5 | AF4: =N4-M4-Q4-AB4-AD4-AE4 -> 586.119 | AG4: =AF4/N4 -> 0.19668423 | AH4: =N4-AB4-AI4 -> 2537.768 | AI4: =Y4*N4 -> 59.451 | AJ4: 0.0085 | AK4: =AJ4*N4 -> 25.33
A5: 46024 | B5: 6398-6399 | D5: GUARULHOS | E5: SP | F5: SOROCABA | G5: SP | H5: CYA RUBBER | I5: FINALIZADO | J5: SIM | K5: ALAN OLIVEIRADA SILVA | M5: 2060 | N5: 1250 | O5: 50000 | P5: 0.0003 | Q5: =O5*P5 -> 15 | R5: 0.12 | S5: =R5*N5 -> 150 | T5: 0 | U5: 1 | V5: =T5*N5 -> 0 | W5: 0.065 | X5: =N5*W5 -> 81.25 | Y5: =Z5*0.00133 -> 0.01995 | Z5: 15 | AA5: =R5+T5+W5+Y5 -> 0.20495 | AB5: =N5*AA5+AK5 -> 266.8125 | AC5: 0 | AD5: =(N5-M5)*AC5 -> 0 | AE5: =17.5 -> 17.5 | AF5: =N5-M5-Q5-AB5-AD5-AE5 -> -1109.3125 | AG5: =AF5/N5 -> -0.88745 | AH5: =N5-AB5-AI5 -> 958.25 | AI5: =Y5*N5 -> 24.9375 | AJ5: 0.0085 | AK5: =AJ5*N5 -> 10.625
A6: 46027 | B6: 6426 | D6: GUARULHOS | E6: SP | F6: ITAQUAQUECETUBA | G6: SP | H6: CYA RUBBER | I6: FINALIZADO | J6: SIM | K6: RODRIGO DA SILVA | M6: 860 | N6: 1620 | O6: 80000 | P6: 0.0003 | Q6: =O6*P6 -> 24 | R6: 0.12 | S6: =R6*N6 -> 194.4 | T6: 0 | U6: 1 | V6: =T6*N6 -> 0 | W6: 0.065 | X6: =N6*W6 -> 105.3 | Y6: =Z6*0.00133 -> 0.01995 | Z6: 15 | AA6: =R6+T6+W6+Y6 -> 0.20495 | AB6: =N6*AA6+AK6 -> 345.789 | AC6: 0.13 | AD6: =(N6-M6)*AC6 -> 98.8 | AE6: =17.5 -> 17.5 | AF6: =N6-M6-Q6-AB6-AD6-AE6 -> 273.911 | AG6: =AF6/N6 -> 0.16908086 | AH6: =N6-AB6-AI6 -> 1241.892 | AI6: =Y6*N6 -> 32.319 | AJ6: 0.0085 | AK6: =AJ6*N6 -> 13.77
A7: 46028 | B7: 6427 6428 6429 | D7: GUARULHOS | E7: SP | F7: SÃO BERNARDO DO CAMPO | G7: SP | H7: CYA RUBBER | I7: FINALIZADO | J7: SIM | K7: THIAGO RODRIGUES | M7: 1160 | N7: 2390 | O7: 100000 | P7: 0.0003 | Q7: =O7*P7 -> 30 | R7: 0.12 | S7: =R7*N7 -> 286.8 | T7: 0 | U7: 1 | V7: =T7*N7 -> 0 | W7: 0.065 | X7: =N7*W7 -> 155.35 | Y7: =Z7*0.00133 -> 0.01995 | Z7: 15 | AA7: =R7+T7+W7+Y7 -> 0.20495 | AB7: =N7*AA7+AK7 -> 510.1455 | AC7: 0.13 | AD7: =(N7-M7)*AC7 -> 159.9 | AE7: =17.5 -> 17.5 | AF7: =N7-M7-Q7-AB7-AD7-AE7 -> 512.4545 | AG7: =AF7/N7 -> 0.21441611 | AH7: =N7-AB7-AI7 -> 1832.174 | AI7: =Y7*N7 -> 47.6805 | AJ7: 0.0085 | AK7: =AJ7*N7 -> 20.315
A8: 46028 | B8: 6449 6450 | D8: GUARULHOS | E8: SP | F8: GUARULHOS | G8: SP | H8: CYA RUBBER | I8: FINALIZADO | J8: SIM | K8: THIAGO RODRIGUES | M8: 810 | N8: 1490 | O8: 80000 | P8: 0.0003 | Q8: =O8*P8 -> 24 | R8: 0.12 | S8: =R8*N8 -> 178.8 | T8: 0 | U8: 1 | V8: =T8*N8 -> 0 | W8: 0.065 | X8: =N8*W8 -> 96.85 | Y8: =Z8*0.00133 -> 0.01995 | Z8: 15 | AA8: =R8+T8+W8+Y8 -> 0.20495 | AB8: =N8*AA8+AK8 -> 318.0405 | AC8: 0.13 | AD8: =(N8-M8)*AC8 -> 88.4 | AE8: =17.5 -> 17.5 | AF8: =N8-M8-Q8-AB8-AD8-AE8 -> 232.0595 | AG8: =AF8/N8 -> 0.15574463 | AH8: =N8-AB8-AI8 -> 1142.234 | AI8: =Y8*N8 -> 29.7255 | AJ8: 0.0085 | AK8: =AJ8*N8 -> 12.665
A9: 46030 | B9: 6480 6481 6482 | D9: GUARULHOS | E9: SP | F9: SALTO | G9: SP | H9: CYA RUBBER | I9: FINALIZADO | J9: SIM | K9: DAVISON DOS SANTOS | M9: 1460 | N9: 2300 | O9: 50000 | P9: 0.0003 | Q9: =O9*P9 -> 15 | R9: 0.12 | S9: =R9*N9 -> 276 | T9: 0 | U9: 1 | V9: =T9*N9 -> 0 | W9: 0.065 | X9: =N9*W9 -> 149.5 | Y9: =Z9*0.00133 -> 0.01995 | Z9: 15 | AA9: =R9+T9+W9+Y9 -> 0.20495 | AB9: =N9*AA9+AK9 -> 490.935 | AC9: 0.06 | AD9: =(N9-M9)*AC9 -> 50.4 | AE9: =17.5 -> 17.5 | AF9: =N9-M9-Q9-AB9-AD9-AE9 -> 266.165 | AG9: =AF9/N9 -> 0.11572391 | AH9: =N9-AB9-AI9 -> 1763.18 | AI9: =Y9*N9 -> 45.885 | AJ9: 0.0085 | AK9: =AJ9*N9 -> 19.55
A10: 46031 | B10: 6514 | D10: GUARULHOS | E10: SP | F10: SÃO PAULO | G10: SP | H10: CYA RUBBER | I10: FINALIZADO | J10: SIM | K10: DAVISON DOS SANTOS | M10: 810 | N10: 1490 | O10: 50000 | P10: 0.0003 | Q10: =O10*P10 -> 15 | R10: 0.12 | S10: =R10*N10 -> 178.8 | T10: 0 | U10: 1 | V10: =T10*N10 -> 0 | W10: 0.065 | X10: =N10*W10 -> 96.85 | Y10: =Z10*0.00133 -> 0.01995 | Z10: 15 | AA10: =R10+T10+W10+Y10 -> 0.20495 | AB10: =N10*AA10+AK10 -> 318.0405 | AC10: 0.13 | AD10: =(N10-M10)*AC10 -> 88.4 | AE10: =17.5 -> 17.5 | AF10: =N10-M10-Q10-AB10-AD10-AE10 -> 241.0595 | AG10: =AF10/N10 -> 0.1617849 | AH10: =N10-AB10-AI10 -> 1142.234 | AI10: =Y10*N10 -> 29.7255 | AJ10: 0.0085 | AK10: =AJ10*N10 -> 12.665
A11: 46031 | B11: 6528 - 6543 - 6544 | D11: BETIM | E11: MG | F11: MARABA | G11: PA | H11: UNIFORT | I11: FINALIZADO | J11: SIM | K11: LEONARDO SOARES | M11: 18060 | N11: 27900 | O11: 100000 | P11: 0.0003 | Q11: =O11*P11 -> 30 | R11: 0.03 | S11: =R11*N11 -> 837 | T11: 0.035 | U11: 1 | V11: =T11*N11 -> 976.5 | W11: 0.065 | X11: =N11*W11 -> 1813.5 | Y11: =Z11*0.00133 -> 0.01995 | Z11: 15 | AA11: =R11+T11+W11+Y11 -> 0.14995 | AB11: =N11*AA11+AK11 -> 4420.755 | AC11: 0.1 | AD11: =(N11-M11)*AC11 -> 984 | AE11: =17.5 -> 17.5 | AF11: =N11-M11-Q11-AB11-AD11-AE11 -> 4387.745 | AG11: =AF11/N11 -> 0.15726685 | AH11: =N11-AB11-AI11 -> 22922.64 | AI11: =Y11*N11 -> 556.605 | AJ11: 0.0085 | AK11: =AJ11*N11 -> 237.15
A12: 46033 | B12: 6550 6551 6552 6553 | D12: GOIANIA | E12: GO | F12: IMPERATRIZ | G12: MA | H12: UNIFORT | I12: FINALIZADO | J12: SIM | K12: CIRINEU KOHLBECK | M12: 7760 | N12: 12900 | O12: 80000 | P12: 0.0003 | Q12: =O12*P12 -> 24 | R12: 0.03 | S12: =R12*N12 -> 387 | T12: 0.035 | U12: 1 | V12: =T12*N12 -> 451.5 | W12: 0.065 | X12: =N12*W12 -> 838.5 | Y12: =Z12*0.00133 -> 0.01995 | Z12: 15 | AA12: =R12+T12+W12+Y12 -> 0.14995 | AB12: =N12*AA12+AK12 -> 2044.005 | AC12: 0.1 | AD12: =(N12-M12)*AC12 -> 514 | AE12: =17.5 -> 17.5 | AF12: =N12-M12-Q12-AB12-AD12-AE12 -> 2540.495 | AG12: =AF12/N12 -> 0.1969376 | AH12: =N12-AB12-AI12 -> 10598.64 | AI12: =Y12*N12 -> 257.355 | AJ12: 0.0085 | AK12: =AJ12*N12 -> 109.65
A13: 46033 | B13: 6546 6547 6548 6549 | D13: GOIANIA | E13: GO | F13: VARZEA GRANDE | G13: MT | H13: UNIFORT | I13: FINALIZADO | J13: SIM | K13: KENDERSON LUCAS | M13: 5060 | N13: 8200 | O13: 80000 | P13: 0.0003 | Q13: =O13*P13 -> 24 | R13: 0.03 | S13: =R13*N13 -> 246 | T13: 0.035 | U13: 1 | V13: =T13*N13 -> 287 | W13: 0.065 | X13: =N13*W13 -> 533 | Y13: =Z13*0.00133 -> 0.01995 | Z13: 15 | AA13: =R13+T13+W13+Y13 -> 0.14995 | AB13: =N13*AA13+AK13 -> 1299.29 | AC13: 0.1 | AD13: =(N13-M13)*AC13 -> 314 | AE13: =17.5 -> 17.5 | AF13: =N13-M13-Q13-AB13-AD13-AE13 -> 1485.21 | AG13: =AF13/N13 -> 0.18112317 | AH13: =N13-AB13-AI13 -> 6737.12 | AI13: =Y13*N13 -> 163.59 | AJ13: 0.0085 | AK13: =AJ13*N13 -> 69.7
A14: 46034 | B14: 6556 | D14: GUARULHOS | E14: SP | F14: ITAQUAQUECETUBA | G14: SP | H14: CYA RUBBER | I14: FINALIZADO | J14: SIM | K14: JURANDY VIEIRA PAIVA | M14: 710 | N14: 1190 | O14: 50000 | P14: 0.0003 | Q14: =O14*P14 -> 15 | R14: 0.12 | S14: =R14*N14 -> 142.8 | T14: 0 | U14: 1 | V14: =T14*N14 -> 0 | W14: 0.065 | X14: =N14*W14 -> 77.35 | Y14: =Z14*0.00133 -> 0.01995 | Z14: 15 | AA14: =R14+T14+W14+Y14 -> 0.20495 | AB14: =N14*AA14+AK14 -> 254.0055 | AC14: 0.07 | AD14: =(N14-M14)*AC14 -> 33.6 | AE14: =17.5 -> 17.5 | AF14: =N14-M14-Q14-AB14-AD14-AE14 -> 159.8945 | AG14: =AF14/N14 -> 0.13436513 | AH14: =N14-AB14-AI14 -> 912.254 | AI14: =Y14*N14 -> 23.7405 | AJ14: 0.0085 | AK14: =AJ14*N14 -> 10.115
A15: 46034 | B15: 6557 | D15: GUARULHOS | E15: SP | F15: DIADEMA | G15: SP | H15: CYA RUBBER | I15: FINALIZADO | J15: SIM | K15: TADEU CRISTOVAO DA SILVA | M15: 710 | N15: 1250 | O15: 50000 | P15: 0.0003 | Q15: =O15*P15 -> 15 | R15: 0.12 | S15: =R15*N15 -> 150 | T15: 0 | U15: 1 | V15: =T15*N15 -> 0 | W15: 0.065 | X15: =N15*W15 -> 81.25 | Y15: =Z15*0.00133 -> 0.01995 | Z15: 15 | AA15: =R15+T15+W15+Y15 -> 0.20495 | AB15: =N15*AA15+AK15 -> 266.8125 | AC15: 0.09 | AD15: =(N15-M15)*AC15 -> 48.6 | AE15: =17.5 -> 17.5 | AF15: =N15-M15-Q15-AB15-AD15-AE15 -> 192.0875 | AG15: =AF15/N15 -> 0.15367 | AH15: =N15-AB15-AI15 -> 958.25 | AI15: =Y15*N15 -> 24.9375 | AJ15: 0.0085 | AK15: =AJ15*N15 -> 10.625
A16: 46035 | B16: 6598 | D16: GUARULHOS | E16: SP | F16: GUARULHOS | G16: SP | H16: CYA RUBBER | I16: FINALIZADO | J16: SIM | K16: TADEU CRISTOVAO DA SILVA | M16: 660 | N16: 1250 | O16: 50000 | P16: 0.0003 | Q16: =O16*P16 -> 15 | R16: 0.12 | S16: =R16*N16 -> 150 | T16: 0 | U16: 1 | V16: =T16*N16 -> 0 | W16: 0.065 | X16: =N16*W16 -> 81.25 | Y16: =Z16*0.00133 -> 0.01995 | Z16: 15 | AA16: =R16+T16+W16+Y16 -> 0.20495 | AB16: =N16*AA16+AK16 -> 266.8125 | AC16: 0.13 | AD16: =(N16-M16)*AC16 -> 76.7 | AE16: =17.5 -> 17.5 | AF16: =N16-M16-Q16-AB16-AD16-AE16 -> 213.9875 | AG16: =AF16/N16 -> 0.17119 | AH16: =N16-AB16-AI16 -> 958.25 | AI16: =Y16*N16 -> 24.9375 | AJ16: 0.0085 | AK16: =AJ16*N16 -> 10.625
A17: 46035 | B17: 28340 | D17: ITAJAI | E17: SC | F17: BETIM | G17: MG | H17: UNIFORT | I17: FINALIZADO | J17: SIM | K17: ADILSON VASQUES | M17: 9360 | N17: 12900 | O17: 580000 | P17: 0.0003 | Q17: =O17*P17 -> 174 | R17: 0.056 | S17: =R17*N17 -> 722.4 | T17: 0.035 | U17: 1 | V17: =T17*N17 -> 451.5 | W17: 0.065 | X17: =N17*W17 -> 838.5 | Y17: =Z17*0.00133 -> 0.01995 | Z17: 15 | AA17: =R17+T17+W17+Y17 -> 0.17595 | AB17: =N17*AA17+AK17 -> 2379.405 | AC17: 0 | AD17: 300 | AE17: =17.5 -> 17.5 | AF17: =N17-M17-Q17-AB17-AD17-AE17 -> 669.095 | AG17: =AF17/N17 -> 0.051867829 | AH17: =N17-AB17-AI17 -> 10263.24 | AI17: =Y17*N17 -> 257.355 | AJ17: 0.0085 | AK17: =AJ17*N17 -> 109.65
A18: 46035 | B18: 6624 | D18: ROCA SALES | E18: RS | F18: SÃO LEOPOLDO | G18: RS | H18: QUISVI | I18: FINALIZADO | J18: SIM | K18: CHRISTIANO AFFONSO RITT | M18: 1260 | N18: 2450 | O18: 100000 | P18: 0.0003 | Q18: =O18*P18 -> 30 | R18: 0 | S18: =R18*N18 -> 0 | T18: 0.035 | U18: 1 | V18: =T18*N18 -> 85.75 | W18: 0.065 | X18: =N18*W18 -> 159.25 | Y18: =Z18*0.00133 -> 0.01995 | Z18: 15 | AA18: =R18+T18+W18+Y18 -> 0.11995 | AB18: =N18*AA18+AK18 -> 314.7025 | AC18: 0.13 | AD18: =(N18-M18)*AC18 -> 154.7 | AE18: =17.5 -> 17.5 | AF18: =N18-M18-Q18-AB18-AD18-AE18 -> 673.0975 | AG18: =AF18/N18 -> 0.27473367 | AH18: =N18-AB18-AI18 -> 2086.42 | AI18: =Y18*N18 -> 48.8775 | AJ18: 0.0085 | AK18: =AJ18*N18 -> 20.825
A19: 46036 | B19: 28351 | D19: CRAVINHOS | E19: SP | F19: DIADEMA | G19: SP | H19: TERMOPLAST | I19: FINALIZADO | J19: SIM | K19: GUILHERME LEANDRO | M19: 2260 | N19: 3200 | O19: 50000 | P19: 0.0003 | Q19: =O19*P19 -> 15 | R19: 0.12 | S19: =R19*N19 -> 384 | T19: 0 | U19: 1 | V19: =T19*N19 -> 0 | W19: 0.065 | X19: =N19*W19 -> 208 | Y19: =Z19*0.00133 -> 0.01995 | Z19: 15 | AA19: =R19+T19+W19+Y19 -> 0.20495 | AB19: =N19*AA19+AK19 -> 683.04 | AC19: 0.01 | AD19: 200 | AE19: =17.5 -> 17.5 | AF19: =N19-M19-Q19-AB19-AD19-AE19 -> 24.46 | AG19: =AF19/N19 -> 0.00764375 | AH19: =N19-AB19-AI19 -> 2453.12 | AI19: =Y19*N19 -> 63.84 | AJ19: 0.0085 | AK19: =AJ19*N19 -> 27.2
A20: 46036 | B20: 6665-6666-6667- 6668 -6669-6670 | D20: GOIANIA | E20: GO | F20: MARABA | G20: PA | H20: UNIFORT | I20: FINALIZADO | J20: SIM | K20: WILSON PEREIRA DIAS | M20: 7060 | N20: 13900 | O20: 100000 | P20: 0.0003 | Q20: =O20*P20 -> 30 | R20: 0.03 | S20: =R20*N20 -> 417 | T20: 0.035 | U20: 1 | V20: =T20*N20 -> 486.5 | W20: 0.065 | X20: =N20*W20 -> 903.5 | Y20: =Z20*0.00133 -> 0.01995 | Z20: 15 | AA20: =R20+T20+W20+Y20 -> 0.14995 | AB20: =N20*AA20+AK20 -> 2202.455 | AC20: 0.1 | AD20: =(N20-M20)*AC20 -> 684 | AE20: =17.5 -> 17.5 | AF20: =N20-M20-Q20-AB20-AD20-AE20 -> 3906.045 | AG20: =AF20/N20 -> 0.28101043 | AH20: =N20-AB20-AI20 -> 11420.24 | AI20: =Y20*N20 -> 277.305 | AJ20: 0.0085 | AK20: =AJ20*N20 -> 118.15
A21: 46036 | B21: 6674 - 6675 - 6676 - 6677 - 6684 | D21: GOIANIA | E21: GO | F21: VARZEA GRANDE | G21: MT | H21: UNIFORT | I21: FINALIZADO | J21: SIM | K21: FERNANDO CARDOSO | M21: 4560 | N21: 8200 | O21: 100000 | P21: 0.0003 | Q21: =O21*P21 -> 30 | R21: 0.03 | S21: =R21*N21 -> 246 | T21: 0.035 | U21: 1 | V21: =T21*N21 -> 287 | W21: 0.065 | X21: =N21*W21 -> 533 | Y21: =Z21*0.00133 -> 0.01995 | Z21: 15 | AA21: =R21+T21+W21+Y21 -> 0.14995 | AB21: =N21*AA21+AK21 -> 1299.29 | AC21: 0.1 | AD21: =(N21-M21)*AC21 -> 364 | AE21: =17.5 -> 17.5 | AF21: =N21-M21-Q21-AB21-AD21-AE21 -> 1929.21 | AG21: =AF21/N21 -> 0.23526951 | AH21: =N21-AB21-AI21 -> 6737.12 | AI21: =Y21*N21 -> 163.59 | AJ21: 0.0085 | AK21: =AJ21*N21 -> 69.7
A22: 46036 | B22: 6662 - 6660 | D22: VARZEA GRANDE | E22: MT | F22: VILHENA | G22: RO | H22: UNIFORT | I22: FINALIZADO | J22: SIM | K22: FABIANO RODRIGUES | M22: 2660 | N22: 4200 | O22: 17000 | P22: 0.0003 | Q22: =O22*P22 -> 5.1 | R22: 0.03 | S22: =R22*N22 -> 126 | T22: 0.035 | U22: 1 | V22: =T22*N22 -> 147 | W22: 0.065 | X22: =N22*W22 -> 273 | Y22: =Z22*0.00133 -> 0.01995 | Z22: 15 | AA22: =R22+T22+W22+Y22 -> 0.14995 | AB22: =N22*AA22+AK22 -> 665.49 | AC22: 0.1 | AD22: =(N22-M22)*AC22 -> 154 | AE22: =17.5 -> 17.5 | AF22: =N22-M22-Q22-AB22-AD22-AE22 -> 697.91 | AG22: =AF22/N22 -> 0.16616905 | AH22: =N22-AB22-AI22 -> 3450.72 | AI22: =Y22*N22 -> 83.79 | AJ22: 0.0085 | AK22: =AJ22*N22 -> 35.7
A23: 46038 | B23: 6750 | D23: GUARULHOS | E23: SP | F23: ITAQUAQUECETUBA | G23: SP | H23: CYA RUBBER | I23: FINALIZADO | J23: SIM | K23: EDI LAZARO | M23: 810 | N23: 1620 | O23: 50000 | P23: 0.0003 | Q23: =O23*P23 -> 15 | R23: 0.12 | S23: =R23*N23 -> 194.4 | T23: 0 | U23: 1 | V23: =T23*N23 -> 0 | W23: 0.065 | X23: =N23*W23 -> 105.3 | Y23: =Z23*0.00133 -> 0.01995 | Z23: 15 | AA23: =R23+T23+W23+Y23 -> 0.20495 | AB23: =N23*AA23+AK23 -> 345.789 | AC23: 0.13 | AD23: =(N23-M23)*AC23 -> 105.3 | AE23: =17.5 -> 17.5 | AF23: =N23-M23-Q23-AB23-AD23-AE23 -> 326.411 | AG23: =AF23/N23 -> 0.20148827 | AH23: =N23-AB23-AI23 -> 1241.892 | AI23: =Y23*N23 -> 32.319 | AJ23: 0.0085 | AK23: =AJ23*N23 -> 13.77
A24: 46038 | B24: 6748 | D24: GUARULHOS | E24: SP | F24: ITAQUAQUECETUBA | G24: SP | H24: CYA RUBBER | I24: FINALIZADO | J24: SIM | K24: EDI LAZARO | M24: 710 | N24: 1350 | O24: 50000 | P24: 0.0003 | Q24: =O24*P24 -> 15 | R24: 0.12 | S24: =R24*N24 -> 162 | T24: 0 | U24: 1 | V24: =T24*N24 -> 0 | W24: 0.065 | X24: =N24*W24 -> 87.75 | Y24: =Z24*0.00133 -> 0.01995 | Z24: 15 | AA24: =R24+T24+W24+Y24 -> 0.20495 | AB24: =N24*AA24+AK24 -> 288.1575 | AC24: 0.13 | AD24: =(N24-M24)*AC24 -> 83.2 | AE24: =17.5 -> 17.5 | AF24: =N24-M24-Q24-AB24-AD24-AE24 -> 236.1425 | AG24: =AF24/N24 -> 0.17492037 | AH24: =N24-AB24-AI24 -> 1034.91 | AI24: =Y24*N24 -> 26.9325 | AJ24: 0.0085 | AK24: =AJ24*N24 -> 11.475
A25: 46039 | B25: 6812 - 6813 - 6814 - 6815 - 6816 - 6817 | D25: GOIANIA | E25: GO | F25: MARABA | G25: PA | H25: UNIFORT | I25: FINALIZADO | J25: SIM | K25: HEULLER DUARTE | M25: 6500 | N25: 10900 | O25: 150000 | P25: 0.0003 | Q25: =O25*P25 -> 45 | R25: 0.03 | S25: =R25*N25 -> 327 | T25: 0.035 | U25: 1 | V25: =T25*N25 -> 381.5 | W25: 0.065 | X25: =N25*W25 -> 708.5 | Y25: =Z25*0.00133 -> 0.01995 | Z25: 15 | AA25: =R25+T25+W25+Y25 -> 0.14995 | AB25: =N25*AA25+AK25 -> 1727.105 | AC25: 0.1 | AD25: =(N25-M25)*AC25 -> 440 | AE25: =17.5 -> 17.5 | AF25: =N25-M25-Q25-AB25-AD25-AE25 -> 2170.395 | AG25: =AF25/N25 -> 0.19911881 | AH25: =N25-AB25-AI25 -> 8955.44 | AI25: =Y25*N25 -> 217.455 | AJ25: 0.0085 | AK25: =AJ25*N25 -> 92.65
A26: 46039 | B26: 6818-6819-6820-6821 | D26: GOIANIA | E26: GO | F26: VARZEA GRANDE | G26: MT | H26: UNIFORT | I26: FINALIZADO | J26: SIM | K26: PATRICK DE LIMA LOPES | M26: 4560 | N26: 7900 | O26: 100000 | P26: 0.0003 | Q26: =O26*P26 -> 30 | R26: 0.03 | S26: =R26*N26 -> 237 | T26: 0.035 | U26: 1 | V26: =T26*N26 -> 276.5 | W26: 0.065 | X26: =N26*W26 -> 513.5 | Y26: =Z26*0.00133 -> 0.01995 | Z26: 15 | AA26: =R26+T26+W26+Y26 -> 0.14995 | AB26: =N26*AA26+AK26 -> 1251.755 | AC26: 0.1 | AD26: =(N26-M26)*AC26 -> 334 | AE26: =17.5 -> 17.5 | AF26: =N26-M26-Q26-AB26-AD26-AE26 -> 1706.745 | AG26: =AF26/N26 -> 0.21604367 | AH26: =N26-AB26-AI26 -> 6490.64 | AI26: =Y26*N26 -> 157.605 | AJ26: 0.0085 | AK26: =AJ26*N26 -> 67.15
A27: 46041 | B27: 6829 | D27: GUARULHOS | E27: SP | F27: SÃO JOSÉ DOS CAMPOS | G27: SP | H27: CYA RUBBER | I27: FINALIZADO | J27: SIM | K27: AGNALDO | M27: 760 | N27: 1630 | O27: 50000 | P27: 0.0003 | Q27: =O27*P27 -> 15 | R27: 0.12 | S27: =R27*N27 -> 195.6 | T27: 0 | U27: 1 | V27: =T27*N27 -> 0 | W27: 0.065 | X27: =N27*W27 -> 105.95 | Y27: =Z27*0.00133 -> 0.01995 | Z27: 15 | AA27: =R27+T27+W27+Y27 -> 0.20495 | AB27: =N27*AA27+AK27 -> 347.9235 | AC27: 0.13 | AD27: =(N27-M27)*AC27 -> 113.1 | AE27: =17.5 -> 17.5 | AF27: =N27-M27-Q27-AB27-AD27-AE27 -> 376.4765 | AG27: =AF27/N27 -> 0.23096718 | AH27: =N27-AB27-AI27 -> 1249.558 | AI27: =Y27*N27 -> 32.5185 | AJ27: 0.0085 | AK27: =AJ27*N27 -> 13.855
A28: 46042 | B28: 6890 | D28: ARAQUARI | E28: SC | F28: SANTAREM | G28: PA | H28: ARTESHOW | I28: FINALIZADO | J28: SIM | K28: UBIRATAN MENDES | M28: 9660 | N28: 11000 | O28: 100000 | P28: 0.0003 | Q28: =O28*P28 -> 30 | R28: 0.056 | S28: =R28*N28 -> 616 | T28: 0.035 | U28: 1 | V28: =T28*N28 -> 385 | W28: 0.065 | X28: =N28*W28 -> 715 | Y28: =Z28*0.00133 -> 0 | Z28: 0 | AA28: =R28+T28+W28+Y28 -> 0.156 | AB28: =N28*AA28+AK28 -> 1809.5 | AC28: 0 | AD28: =(N28-M28)*AC28 -> 0 | AE28: =17.5 -> 17.5 | AF28: =N28-M28-Q28-AB28-AD28-AE28 -> -517 | AG28: =AF28/N28 -> -0.047 | AH28: =N28-AB28-AI28 -> 9190.5 | AI28: =Y28*N28 -> 0 | AJ28: 0.0085 | AK28: =AJ28*N28 -> 93.5
A29: 46042 | B29: 6888 | D29: GUARULHOS | E29: SP | F29: SAO PAULO | G29: SP | H29: CYA RUBBER | I29: FINALIZADO | J29: SIM | K29: AILTON GOMES | M29: 760 | N29: 1490 | O29: 80000 | R29: 0.12 | T29: 0 | U29: 1 | V29: =T29*N29 -> 0 | W29: 0.065 | X29: =N29*W29 -> 96.85 | Y29: =Z29*0.00133 -> 0.01995 | Z29: 15 | AA29: =R29+T29+W29+Y29 -> 0.20495 | AB29: =N29*AA29+AK29 -> 318.0405 | AC29: 0.13 | AD29: =(N29-M29)*AC29 -> 94.9 | AE29: =17.5 -> 17.5 | AF29: =N29-M29-Q29-AB29-AD29-AE29 -> 299.5595 | AG29: =AF29/N29 -> 0.20104664 | AH29: =N29-AB29-AI29 -> 1142.234 | AI29: =Y29*N29 -> 29.7255 | AJ29: 0.0085 | AK29: =AJ29*N29 -> 12.665
A30: 46042 | B30: 6884 | D30: GUARULHOS | E30: SP | F30: COTIA | G30: SP | H30: CYA RUBBER | I30: FINALIZADO | J30: SIM | K30: FRANCISCO JOSE | M30: 710 | N30: 1300 | O30: 50000 | R30: 0.12 | T30: 0 | U30: 1 | V30: =T30*N30 -> 0 | W30: 0.065 | X30: =N30*W30 -> 84.5 | Y30: =Z30*0.00133 -> 0.01995 | Z30: 15 | AA30: =R30+T30+W30+Y30 -> 0.20495 | AB30: =N30*AA30+AK30 -> 277.485 | AC30: 0.13 | AD30: =(N30-M30)*AC30 -> 76.7 | AE30: =17.5 -> 17.5 | AF30: =N30-M30-Q30-AB30-AD30-AE30 -> 218.315 | AG30: =AF30/N30 -> 0.16793462 | AH30: =N30-AB30-AI30 -> 996.58 | AI30: =Y30*N30 -> 25.935 | AJ30: 0.0085 | AK30: =AJ30*N30 -> 11.05
A31: 46042 | B31: 6909 | D31: ITAJAI | E31: SC | F31: GUARULHOS | G31: SP | H31: CYA RUBBER | I31: FINALIZADO | J31: SIM | K31: RAFAEL DA SILVA | M31: 3810 | N31: 5900 | O31: 50000 | P31: 0.0003 | Q31: =O31*P31 -> 15 | R31: 0.12 | T31: 0 | U31: 1 | V31: =T31*N31 -> 0 | W31: 0.065 | X31: =N31*W31 -> 383.5 | Y31: =Z31*0.00133 -> 0.01995 | Z31: 15 | AA31: =R31+T31+W31+Y31 -> 0.20495 | AB31: =N31*AA31+AK31 -> 1259.355 | AC31: 0.06 | AD31: =(N31-M31)*AC31 -> 125.4 | AE31: =17.5 -> 17.5 | AF31: =N31-M31-Q31-AB31-AD31-AE31 -> 672.745 | AG31: =AF31/N31 -> 0.11402458 | AH31: =N31-AB31-AI31 -> 4522.94 | AI31: =Y31*N31 -> 117.705 | AJ31: 0.0085 | AK31: =AJ31*N31 -> 50.15
A32: 46043 | B32: 6948 - 6949 - 6950 - 6951 - 6952 - 6953 | D32: GOIANIA | E32: GO | F32: MARABA | G32: MA | H32: UNIFORT | I32: FINALIZADO | J32: SIM | K32: CRISTIANO DAS NEVES | M32: 6560 | N32: 12900 | O32: 80000 | P32: 0.0003 | Q32: =O32*P32 -> 24 | R32: 0.03 | S32: =R32*N32 -> 387 | T32: 0.035 | U32: 1 | V32: =T32*N32 -> 451.5 | W32: 0.065 | X32: =N32*W32 -> 838.5 | Y32: =Z32*0.00133 -> 0.01995 | Z32: 15 | AA32: =R32+T32+W32+Y32 -> 0.14995 | AB32: =N32*AA32+AK32 -> 2044.005 | AC32: 0.1 | AD32: =(N32-M32)*AC32 -> 634 | AE32: =17.5 -> 17.5 | AF32: =N32-M32-Q32-AB32-AD32-AE32 -> 3620.495 | AG32: =AF32/N32 -> 0.28065853 | AH32: =N32-AB32-AI32 -> 10598.64 | AI32: =Y32*N32 -> 257.355 | AJ32: 0.0085 | AK32: =AJ32*N32 -> 109.65
A33: 46043 | B33: 6944 - 6945 - 6946 - 6947 | D33: GOIANIA | E33: GO | F33: VARZEA GRANDE | G33: MT | H33: UNIFORT | I33: FINALIZADO | J33: SIM | K33: JOAO WALGNEI | M33: 4560 | N33: 7900 | O33: 80000 | P33: 0.0003 | Q33: =O33*P33 -> 24 | R33: 0.03 | S33: =R33*N33 -> 237 | T33: 0.035 | U33: 1 | V33: =T33*N33 -> 276.5 | W33: 0.065 | X33: =N33*W33 -> 513.5 | Y33: =Z33*0.00133 -> 0.01995 | Z33: 15 | AA33: =R33+T33+W33+Y33 -> 0.14995 | AB33: =N33*AA33+AK33 -> 1251.755 | AC33: 0.1 | AD33: =(N33-M33)*AC33 -> 334 | AE33: =17.5 -> 17.5 | AF33: =N33-M33-Q33-AB33-AD33-AE33 -> 1712.745 | AG33: =AF33/N33 -> 0.21680316 | AH33: =N33-AB33-AI33 -> 6490.64 | AI33: =Y33*N33 -> 157.605 | AJ33: 0.0085 | AK33: =AJ33*N33 -> 67.15
A34: 46043 | B34: 28435 | D34: ITAJAI | E34: SC | F34: BETIM | G34: MG | H34: UNIFORT | I34: FINALIZADO | J34: SIM | K34: FERNANDO EMANOEL | M34: 9560 | N34: 12900 | O34: 350000 | P34: 0.0003 | Q34: =O34*P34 -> 105 | R34: 0.056 | S34: =R34*N34 -> 722.4 | T34: 0.035 | U34: 1 | V34: =T34*N34 -> 451.5 | W34: 0.065 | X34: =N34*W34 -> 838.5 | Y34: =Z34*0.00133 -> 0.01995 | Z34: 15 | AA34: =R34+T34+W34+Y34 -> 0.17595 | AB34: =N34*AA34+AK34 -> 2379.405 | AC34: 0 | AD34: 300 | AE34: =17.5 -> 17.5 | AF34: =N34-M34-Q34-AB34-AD34-AE34 -> 538.095 | AG34: =AF34/N34 -> 0.041712791 | AH34: =N34-AB34-AI34 -> 10263.24 | AI34: =Y34*N34 -> 257.355 | AJ34: 0.0085 | AK34: =AJ34*N34 -> 109.65
A35: 46043 | B35: 6965 | D35: ITAJAI | E35: SC | F35: BETIM | G35: MG | H35: UNIFORT | I35: FINALIZADO | J35: SIM | K35: CRODOALDO FURTADO | M35: 8250 | N35: 13900 | O35: 350000 | P35: 0.0003 | Q35: =O35*P35 -> 105 | R35: 0.056 | S35: =R35*N35 -> 778.4 | T35: 0.035 | U35: 1 | V35: =T35*N35 -> 486.5 | W35: 0.065 | X35: =N35*W35 -> 903.5 | Y35: =Z35*0.00133 -> 0.01995 | Z35: 15 | AA35: =R35+T35+W35+Y35 -> 0.17595 | AB35: =N35*AA35+AK35 -> 2563.855 | AC35: 0.1 | AD35: =(N35-M35)*AC35 -> 565 | AE35: =17.5 -> 17.5 | AF35: =N35-M35-Q35-AB35-AD35-AE35 -> 2398.645 | AG35: =AF35/N35 -> 0.17256439 | AH35: =N35-AB35-AI35 -> 11058.84 | AI35: =Y35*N35 -> 277.305 | AJ35: 0.0085 | AK35: =AJ35*N35 -> 118.15
A36: 46043 | B36: 6914 | D36: GUARULHOS | E36: SP | F36: SALTO | G36: SP | H36: CYA RUBBER | I36: FINALIZADO | J36: SIM | K36: ANDERSON BARBOSA | M36: 1330 | N36: 2100 | O36: 100000 | P36: 0.0003 | Q36: =O36*P36 -> 30 | R36: 0.12 | S36: =R36*N36 -> 252 | T36: 0 | U36: 1 | V36: =T36*N36 -> 0 | W36: 0.065 | X36: =N36*W36 -> 136.5 | Y36: =Z36*0.00133 -> 0.01995 | Z36: 15 | AA36: =R36+T36+W36+Y36 -> 0.20495 | AB36: =N36*AA36+AK36 -> 448.245 | AC36: 0.05 | AD36: =(N36-M36)*AC36 -> 38.5 | AE36: =17.5 -> 17.5 | AF36: =N36-M36-Q36-AB36-AD36-AE36 -> 235.755 | AG36: =AF36/N36 -> 0.11226429 | AH36: =N36-AB36-AI36 -> 1609.86 | AI36: =Y36*N36 -> 41.895 | AJ36: 0.0085 | AK36: =AJ36*N36 -> 17.85
A37: 46043 | B37: 6961 | D37: GUARULHOS | E37: SP | F37: COTIA | G37: SP | H37: CYA RUBBER | I37: FINALIZADO | J37: SIM | K37: MARCELO ANTONIO | M37: 510 | N37: 720 | O37: 20000 | P37: 0.0003 | Q37: =O37*P37 -> 6 | R37: 0.12 | S37: =R37*N37 -> 86.4 | T37: 0 | U37: 1 | V37: =T37*N37 -> 0 | W37: 0.065 | X37: =N37*W37 -> 46.8 | Y37: =Z37*0.00133 -> 0.01995 | Z37: 15 | AA37: =R37+T37+W37+Y37 -> 0.20495 | AB37: =N37*AA37+AK37 -> 153.684 | AC37: 0 | AD37: =(N37-M37)*AC37 -> 0 | AE37: =17.5 -> 17.5 | AF37: =N37-M37-Q37-AB37-AD37-AE37 -> 32.816 | AG37: =AF37/N37 -> 0.045577778 | AH37: =N37-AB37-AI37 -> 551.952 | AI37: =Y37*N37 -> 14.364 | AJ37: 0.0085 | AK37: =AJ37*N37 -> 6.12
A38: 46044 | B38: 6998 - 6999 | D38: GUARULHOS | E38: SP | F38: ITAQUAQUECETUBA | G38: SP | H38: CYA RUBBER | I38: FINALIZADO | J38: SIM | K38: NATAN SANTOS | M38: 860 | N38: 1400 | O38: 50000 | P38: 0.0003 | Q38: =O38*P38 -> 15 | R38: 0.12 | S38: =R38*N38 -> 168 | T38: 0 | U38: 1 | V38: =T38*N38 -> 0 | W38: 0.065 | X38: =N38*W38 -> 91 | Y38: =Z38*0.00133 -> 0.01995 | Z38: 15 | AA38: =R38+T38+W38+Y38 -> 0.20495 | AB38: =N38*AA38+AK38 -> 298.83 | AC38: 0.07 | AD38: =(N38-M38)*AC38 -> 37.8 | AE38: =17.5 -> 17.5 | AF38: =N38-M38-Q38-AB38-AD38-AE38 -> 170.87 | AG38: =AF38/N38 -> 0.12205 | AH38: =N38-AB38-AI38 -> 1073.24 | AI38: =Y38*N38 -> 27.93 | AJ38: 0.0085 | AK38: =AJ38*N38 -> 11.9
A39: 46044 | B39: 7003 | D39: GUARULHOS | E39: SP | F39: GUARULHOS | G39: SP | H39: CYA RUBBER | I39: FINALIZADO | J39: SIM | K39: HUGO SANTIAGO | M39: 460 | N39: 800 | O39: 50000 | P39: 0.0003 | Q39: =O39*P39 -> 15 | R39: 0.12 | S39: =R39*N39 -> 96 | T39: 0 | U39: 1 | V39: =T39*N39 -> 0 | W39: 0.065 | X39: =N39*W39 -> 52 | Y39: =Z39*0.00133 -> 0.01995 | Z39: 15 | AA39: =R39+T39+W39+Y39 -> 0.20495 | AB39: =N39*AA39+AK39 -> 170.76 | AC39: 0.07 | AD39: =(N39-M39)*AC39 -> 23.8 | AE39: =17.5 -> 17.5 | AF39: =N39-M39-Q39-AB39-AD39-AE39 -> 112.94 | AG39: =AF39/N39 -> 0.141175 | AH39: =N39-AB39-AI39 -> 613.28 | AI39: =Y39*N39 -> 15.96 | AJ39: 0.0085 | AK39: =AJ39*N39 -> 6.8
A40: 46045 | B40: 7898 | D40: GUARULHOS | E40: SP | F40: DIADEMA | G40: SP | H40: CYA RUBBER | I40: FINALIZADO | J40: SIM | K40: THIAGO RODRIGUES | M40: 1100 | N40: 800 | O40: 50000 | P40: 0.0003 | Q40: =O40*P40 -> 15 | R40: 0.12 | S40: =R40*N40 -> 96 | T40: 0 | U40: 1 | V40: =T40*N40 -> 0 | W40: 0.065 | X40: =N40*W40 -> 52 | Y40: =Z40*0.00133 -> 0.01995 | Z40: 15 | AA40: =R40+T40+W40+Y40 -> 0.20495 | AB40: =N40*AA40+AK40 -> 170.76 | AC40: 0.07 | AD40: =(N40-M40)*AC40 -> -21 | AE40: =17.5 -> 17.5 | AF40: =N40-M40-Q40-AB40-AD40-AE40 -> -482.26 | AG40: =AF40/N40 -> -0.602825 | AH40: =N40-AB40-AI40 -> 613.28 | AI40: =Y40*N40 -> 15.96 | AJ40: 0.0085 | AK40: =AJ40*N40 -> 6.8
A41: 46045 | B41: 28493 28492 | D41: ITAJAI | E41: SC | F41: BETIM | G41: MG | H41: UNIFORT | I41: FINALIZADO | J41: SIM | K41: ALEXANDRE HENRIQUE | M41: 7760 | N41: 9800 | O41: 20000 | P41: 0.0003 | Q41: =O41*P41 -> 6 | R41: 0.03 | S41: =R41*N41 -> 294 | T41: 0.035 | U41: 1 | V41: =T41*N41 -> 343 | W41: 0.065 | X41: =N41*W41 -> 637 | Y41: =Z41*0.00133 -> 0.01995 | Z41: 15 | AA41: =R41+T41+W41+Y41 -> 0.14995 | AB41: =N41*AA41+AK41 -> 1552.81 | AC41: 0 | AD41: 300 | AE41: =17.5 -> 17.5 | AF41: =N41-M41-Q41-AB41-AD41-AE41 -> 163.69 | AG41: =AF41/N41 -> 0.016703061 | AH41: =N41-AB41-AI41 -> 8051.68 | AI41: =Y41*N41 -> 195.51 | AJ41: 0.0085 | AK41: =AJ41*N41 -> 83.3
A42: 46045 | B42: 7899 | D42: GUARULHOS | E42: SP | F42: SAO CAETANO DO SUL | G42: SP | H42: CYA RUBBER | I42: FINALIZADO | J42: SIM | K42: TIAGO GONÇALVES | M42: 410 | N42: 650 | O42: 20000 | P42: 0.0003 | Q42: =O42*P42 -> 6 | R42: 0.12 | S42: =R42*N42 -> 78 | T42: 0 | U42: 1 | V42: =T42*N42 -> 0 | W42: 0.065 | X42: =N42*W42 -> 42.25 | Y42: =Z42*0.00133 -> 0.01995 | Z42: 15 | AA42: =R42+T42+W42+Y42 -> 0.20495 | AB42: =N42*AA42+AK42 -> 138.7425 | AC42: 0.03 | AD42: =(N42-M42)*AC42 -> 7.2 | AE42: =17.5 -> 17.5 | AF42: =N42-M42-Q42-AB42-AD42-AE42 -> 70.5575 | AG42: =AF42/N42 -> 0.10855 | AH42: =N42-AB42-AI42 -> 498.29 | AI42: =Y42*N42 -> 12.9675 | AJ42: 0.0085 | AK42: =AJ42*N42 -> 5.525
A43: 46046 | B43: 28501 - 28502 - 28503 - 28504 - 28505 - 28506 - 28507 | D43: BETIM | E43: MG | F43: VITORIA DA CONQUISTA | G43: BA | H43: UNIFORT | I43: FINALIZADO | J43: SIM | K43: FERNANDO EMANOEL | M43: 7560 | N43: 11900 | O43: 100000 | P43: 0.0003 | Q43: =O43*P43 -> 30 | R43: 0.03 | S43: =R43*N43 -> 357 | T43: 0.035 | U43: 1 | V43: =T43*N43 -> 416.5 | W43: 0.065 | X43: =N43*W43 -> 773.5 | Y43: =Z43*0.00133 -> 0.01995 | Z43: 15 | AA43: =R43+T43+W43+Y43 -> 0.14995 | AB43: =N43*AA43+AK43 -> 1885.555 | AC43: 0.1 | AD43: =(N43-M43)*AC43 -> 434 | AE43: =17.5 -> 17.5 | AF43: =N43-M43-Q43-AB43-AD43-AE43 -> 1972.945 | AG43: =AF43/N43 -> 0.1657937 | AH43: =N43-AB43-AI43 -> 9777.04 | AI43: =Y43*N43 -> 237.405 | AJ43: 0.0085 | AK43: =AJ43*N43 -> 101.15
A44: 46046 | B44: 7943 - 7944 - 7945 - 7946 - 7947 - 7948 | D44: BETIM | E44: MG | F44: GOIANIA | G44: GO | H44: UNIFORT | I44: FINALIZADO | J44: SIM | K44: LEANDRO ALMEIDA | M44: 6710 | N44: 12800 | O44: 100000 | P44: 0.0003 | Q44: =O44*P44 -> 30 | R44: 0.03 | S44: =R44*N44 -> 384 | T44: 0.035 | U44: 1 | V44: =T44*N44 -> 448 | W44: 0.065 | X44: =N44*W44 -> 832 | Y44: =Z44*0.00133 -> 0.01995 | Z44: 15 | AA44: =R44+T44+W44+Y44 -> 0.14995 | AB44: =N44*AA44+AK44 -> 2028.16 | AC44: 0.1 | AD44: =(N44-M44)*AC44 -> 609 | AE44: =17.5 -> 17.5 | AF44: =N44-M44-Q44-AB44-AD44-AE44 -> 3405.34 | AG44: =AF44/N44 -> 0.26604219 | AH44: =N44-AB44-AI44 -> 10516.48 | AI44: =Y44*N44 -> 255.36 | AJ44: 0.0085 | AK44: =AJ44*N44 -> 108.8
A45: 46047 | B45: 7949 - 7950 | D45: IMPERATRIZ | E45: MA | F45: TERESINA | G45: PI | H45: UNIFORT | I45: FINALIZADO | J45: SIM | K45: AECIO VIEIRA | M45: 2360 | N45: 4600 | O45: 50000 | P45: 0.0003 | Q45: =O45*P45 -> 15 | R45: 0.03 | S45: =R45*N45 -> 138 | T45: 0.035 | U45: 1 | V45: =T45*N45 -> 161 | W45: 0.065 | X45: =N45*W45 -> 299 | Y45: =Z45*0.00133 -> 0.01995 | Z45: 15 | AA45: =R45+T45+W45+Y45 -> 0.14995 | AB45: =N45*AA45+AK45 -> 728.87 | AC45: 0.1 | AD45: =(N45-M45)*AC45 -> 224 | AE45: =17.5 -> 17.5 | AF45: =N45-M45-Q45-AB45-AD45-AE45 -> 1254.63 | AG45: =AF45/N45 -> 0.27274565 | AH45: =N45-AB45-AI45 -> 3779.36 | AI45: =Y45*N45 -> 91.77 | AJ45: 0.0085 | AK45: =AJ45*N45 -> 39.1
A46: 46048 | B46: 7963 - 7964 | D46: GUARULHOS | E46: SP | F46: ITAQUAQUECETUBA | G46: SP | H46: CYA RUBBER | I46: FINALIZADO | J46: SIM | K46: THIAGO RODRIGUES | M46: 960 | N46: 2540 | O46: 50000 | P46: 0.0003 | Q46: =O46*P46 -> 15 | R46: 0.12 | S46: =R46*N46 -> 304.8 | T46: 0 | U46: 1 | V46: =T46*N46 -> 0 | W46: 0.065 | X46: =N46*W46 -> 165.1 | Y46: =Z46*0.00133 -> 0.01995 | Z46: 15 | AA46: =R46+T46+W46+Y46 -> 0.20495 | AB46: =N46*AA46+AK46 -> 542.163 | AC46: 0.13 | AD46: =(N46-M46)*AC46 -> 205.4 | AE46: =17.5 -> 17.5 | AF46: =N46-M46-Q46-AB46-AD46-AE46 -> 799.937 | AG46: =AF46/N46 -> 0.31493583 | AH46: =N46-AB46-AI46 -> 1947.164 | AI46: =Y46*N46 -> 50.673 | AJ46: 0.0085 | AK46: =AJ46*N46 -> 21.59
A47: 46048 | B47: 7956 | D47: GUARULHOS | E47: SP | F47: DIADEMA | G47: SP | H47: CYA RUBBER | I47: FINALIZADO | J47: SIM | K47: EMERSON CUSTODIO | M47: 660 | N47: 860 | O47: 20000 | P47: 0.0003 | Q47: =O47*P47 -> 6 | R47: 0.12 | S47: =R47*N47 -> 103.2 | T47: 0 | U47: 1 | V47: =T47*N47 -> 0 | W47: 0.065 | X47: =N47*W47 -> 55.9 | Y47: =Z47*0.00133 -> 0.01995 | Z47: 15 | AA47: =R47+T47+W47+Y47 -> 0.20495 | AB47: =N47*AA47+AK47 -> 183.567 | AC47: 0 | AD47: =(N47-M47)*AC47 -> 0 | AE47: =17.5 -> 17.5 | AF47: =N47-M47-Q47-AB47-AD47-AE47 -> -7.067 | AG47: =AF47/N47 -> -0.0082174419 | AH47: =N47-AB47-AI47 -> 659.276 | AI47: =Y47*N47 -> 17.157 | AJ47: 0.0085 | AK47: =AJ47*N47 -> 7.31
A48: 46048 | B48: 7976 7977 7978 7979 7981 7983 | D48: GOIANIA | E48: GO | F48: MARABA | G48: PA | H48: UNIFORT | I48: FINALIZADO | J48: SIM | K48: ADAISON ROMAO | M48: 7657.62 | N48: 12900 | O48: 100000 | P48: 0.0003 | Q48: =O48*P48 -> 30 | R48: 0.03 | S48: =R48*N48 -> 387 | T48: 0.035 | U48: 1 | V48: =T48*N48 -> 451.5 | W48: 0.065 | X48: =N48*W48 -> 838.5 | Y48: =Z48*0.00133 -> 0.01995 | Z48: 15 | AA48: =R48+T48+W48+Y48 -> 0.14995 | AB48: =N48*AA48+AK48 -> 2044.005 | AC48: 0.1 | AD48: =(N48-M48)*AC48 -> 524.238 | AE48: =17.5 -> 17.5 | AF48: =N48-M48-Q48-AB48-AD48-AE48 -> 2626.637 | AG48: =AF48/N48 -> 0.20361527 | AH48: =N48-AB48-AI48 -> 10598.64 | AI48: =Y48*N48 -> 257.355 | AJ48: 0.0085 | AK48: =AJ48*N48 -> 109.65
A49: 46048 | B49: 7967 - 7968 - 7969 - 7974 | D49: GOIANIA | E49: GO | F49: VARZEA GRANDE | G49: MT | H49: UNIFORT | I49: FINALIZADO | J49: SIM | K49: ANTONIO BALDISSERA | M49: 4560 | N49: 7900 | O49: 50000 | P49: 0.0003 | Q49: =O49*P49 -> 15 | R49: 0.03 | S49: =R49*N49 -> 237 | T49: 0.035 | U49: 1 | V49: =T49*N49 -> 276.5 | W49: 0.065 | X49: =N49*W49 -> 513.5 | Y49: =Z49*0.00133 -> 0.01995 | Z49: 15 | AA49: =R49+T49+W49+Y49 -> 0.14995 | AB49: =N49*AA49+AK49 -> 1251.755 | AC49: 0.1 | AD49: =(N49-M49)*AC49 -> 334 | AE49: =17.5 -> 17.5 | AF49: =N49-M49-Q49-AB49-AD49-AE49 -> 1721.745 | AG49: =AF49/N49 -> 0.21794241 | AH49: =N49-AB49-AI49 -> 6490.64 | AI49: =Y49*N49 -> 157.605 | AJ49: 0.0085 | AK49: =AJ49*N49 -> 67.15
A50: 46048 | B50: 7953 | D50: GUARULHOS | E50: SP | F50: GUARULHOS | G50: SP | H50: CYA RUBBER | I50: FINALIZADO | J50: SIM | K50: JURANDY VIEIRA | M50: 610 | N50: 1050 | O50: 20000 | P50: 0.0003 | Q50: =O50*P50 -> 6 | R50: 0.12 | S50: =R50*N50 -> 126 | T50: 0 | U50: 1 | V50: =T50*N50 -> 0 | W50: 0.065 | X50: =N50*W50 -> 68.25 | Y50: =Z50*0.00133 -> 0.01995 | Z50: 15 | AA50: =R50+T50+W50+Y50 -> 0.20495 | AB50: =N50*AA50+AK50 -> 224.1225 | AC50: 0.07 | AD50: =(N50-M50)*AC50 -> 30.8 | AE50: =17.5 -> 17.5 | AF50: =N50-M50-Q50-AB50-AD50-AE50 -> 161.5775 | AG50: =AF50/N50 -> 0.15388333 | AH50: =N50-AB50-AI50 -> 804.93 | AI50: =Y50*N50 -> 20.9475 | AJ50: 0.0085 | AK50: =AJ50*N50 -> 8.925
A51: 46048 | B51: 28523 - 28522 - 28524 | D51: ITAJAI | E51: SC | F51: BETIM | G51: MG | H51: UNIFORT | I51: FINALIZADO | J51: SIM | K51: ADILSON VASQUES | M51: 9560 | N51: 12900 | O51: 100000 | P51: 0.0003 | Q51: =O51*P51 -> 30 | R51: 0.03 | S51: =R51*N51 -> 387 | T51: 0.035 | U51: 1 | V51: =T51*N51 -> 451.5 | W51: 0.065 | X51: =N51*W51 -> 838.5 | Y51: =Z51*0.00133 -> 0.01995 | Z51: 15 | AA51: =R51+T51+W51+Y51 -> 0.14995 | AB51: =N51*AA51+AK51 -> 2044.005 | AC51: 0 | AD51: 300 | AE51: =17.5 -> 17.5 | AF51: =N51-M51-Q51-AB51-AD51-AE51 -> 948.495 | AG51: =AF51/N51 -> 0.073526744 | AH51: =N51-AB51-AI51 -> 10598.64 | AI51: =Y51*N51 -> 257.355 | AJ51: 0.0085 | AK51: =AJ51*N51 -> 109.65
A52: 46048 | B52: 7982 | D52: GUARULHOS | E52: SP | F52: SALTO | G52: SP | H52: CYA RUBBER | I52: FINALIZADO | J52: SIM | K52: WILLIAM DE PAULA | M52: 1260 | N52: 2100 | O52: 50000 | P52: 0.0003 | Q52: =O52*P52 -> 15 | R52: 0.12 | S52: =R52*N52 -> 252 | T52: 0 | U52: 1 | V52: =T52*N52 -> 0 | W52: 0.065 | X52: =N52*W52 -> 136.5 | Y52: =Z52*0.00133 -> 0.01995 | Z52: 15 | AA52: =R52+T52+W52+Y52 -> 0.20495 | AB52: =N52*AA52+AK52 -> 448.245 | AC52: 0.07 | AD52: =(N52-M52)*AC52 -> 58.8 | AE52: =17.5 -> 17.5 | AF52: =N52-M52-Q52-AB52-AD52-AE52 -> 300.455 | AG52: =AF52/N52 -> 0.14307381 | AH52: =N52-AB52-AI52 -> 1609.86 | AI52: =Y52*N52 -> 41.895 | AJ52: 0.0085 | AK52: =AJ52*N52 -> 17.85
A53: 46050 | B53: 8175-8176-8177-8178-8179-8180 | D53: GOIANIA | E53: GO | F53: MARABA | G53: PA | H53: UNIFORT | I53: FINALIZADO | J53: SIM | K53: DOMINGOS GOMES | M53: 6360 | N53: 10500 | O53: 100000 | P53: 0.0003 | Q53: =O53*P53 -> 30 | R53: 0.03 | S53: =R53*N53 -> 315 | T53: 0.035 | U53: 1 | V53: =T53*N53 -> 367.5 | W53: 0.065 | X53: =N53*W53 -> 682.5 | Y53: =Z53*0.00133 -> 0.01995 | Z53: 15 | AA53: =R53+T53+W53+Y53 -> 0.14995 | AB53: =N53*AA53+AK53 -> 1663.725 | AC53: 0.1 | AD53: =(N53-M53)*AC53 -> 414 | AE53: =17.5 -> 17.5 | AF53: =N53-M53-Q53-AB53-AD53-AE53 -> 2014.775 | AG53: =AF53/N53 -> 0.19188333 | AH53: =N53-AB53-AI53 -> 8626.8 | AI53: =Y53*N53 -> 209.475 | AJ53: 0.0085 | AK53: =AJ53*N53 -> 89.25
A54: 46050 | B54: 8149-8150-8152-8163- | D54: GOIANIA | E54: GO | F54: VARZEA GRANDE | G54: MT | H54: UNIFORT | I54: FINALIZADO | J54: SIM | K54: THIAGO DA SILVA PINTO | M54: 4060 | N54: 6500 | O54: 50000 | P54: 0.0003 | Q54: =O54*P54 -> 15 | R54: 0.03 | S54: =R54*N54 -> 195 | T54: 0.035 | U54: 1 | V54: =T54*N54 -> 227.5 | W54: 0.065 | X54: =N54*W54 -> 422.5 | Y54: =Z54*0.00133 -> 0.01995 | Z54: 15 | AA54: =R54+T54+W54+Y54 -> 0.14995 | AB54: =N54*AA54+AK54 -> 1029.925 | AC54: 0.1 | AD54: =(N54-M54)*AC54 -> 244 | AE54: =17.5 -> 17.5 | AF54: =N54-M54-Q54-AB54-AD54-AE54 -> 1133.575 | AG54: =AF54/N54 -> 0.17439615 | AH54: =N54-AB54-AI54 -> 5340.4 | AI54: =Y54*N54 -> 129.675 | AJ54: 0.0085 | AK54: =AJ54*N54 -> 55.25
A55: 46050 | B55: 8144 | D55: ITAJAI | E55: SC | F55: SÃO LEOPOLDO | G55: RS | H55: CYA RUBBER | I55: FINALIZADO | J55: SIM | K55: RONALDO CERVELLIN | M55: 3210 | N55: 5200 | O55: 50000 | P55: 0.0003 | Q55: =O55*P55 -> 15 | R55: 0.12 | S55: =R55*N55 -> 624 | T55: 0 | U55: 1 | V55: =T55*N55 -> 0 | W55: 0.065 | X55: =N55*W55 -> 338 | Y55: =Z55*0.00133 -> 0.01995 | Z55: 15 | AA55: =R55+T55+W55+Y55 -> 0.20495 | AB55: =N55*AA55+AK55 -> 1109.94 | AC55: 0.07 | AD55: =(N55-M55)*AC55 -> 139.3 | AE55: =17.5 -> 17.5 | AF55: =N55-M55-Q55-AB55-AD55-AE55 -> 708.26 | AG55: =AF55/N55 -> 0.13620385 | AH55: =N55-AB55-AI55 -> 3986.32 | AI55: =Y55*N55 -> 103.74 | AJ55: 0.0085 | AK55: =AJ55*N55 -> 44.2
A56: 46050 | B56: 8123 | D56: GUARULHOS | E56: SP | F56: SAO PAULO | G56: SP | H56: CYA RUBBER | I56: FINALIZADO | J56: SIM | K56: SILVIONEY BECKER | M56: 760 | N56: 1490 | O56: 30000 | P56: 0.0003 | Q56: =O56*P56 -> 9 | R56: 0.12 | S56: =R56*N56 -> 178.8 | T56: 0 | U56: 1 | V56: =T56*N56 -> 0 | W56: 0.065 | X56: =N56*W56 -> 96.85 | Y56: =Z56*0.00133 -> 0.01995 | Z56: 15 | AA56: =R56+T56+W56+Y56 -> 0.20495 | AB56: =N56*AA56+AK56 -> 318.0405 | AC56: 0.07 | AD56: =(N56-M56)*AC56 -> 51.1 | AE56: =17.5 -> 17.5 | AF56: =N56-M56-Q56-AB56-AD56-AE56 -> 334.3595 | AG56: =AF56/N56 -> 0.22440235 | AH56: =N56-AB56-AI56 -> 1142.234 | AI56: =Y56*N56 -> 29.7255 | AJ56: 0.0085 | AK56: =AJ56*N56 -> 12.665
A57: 46050 | B57: 8135 | D57: GUARULHOS | E57: SP | F57: SÃO JOSÉ DOS CAMPOS | G57: SP | H57: CYA RUBBER | I57: FINALIZADO | J57: SIM | K57: AGNALDO CICERO | M57: 708.82 | N57: 1600 | O57: 50000 | P57: 0.0003 | Q57: =O57*P57 -> 15 | R57: 0.12 | S57: =R57*N57 -> 192 | T57: 0 | U57: 1 | V57: =T57*N57 -> 0 | W57: 0.065 | X57: =N57*W57 -> 104 | Y57: =Z57*0.00133 -> 0.01995 | Z57: 15 | AA57: =R57+T57+W57+Y57 -> 0.20495 | AB57: =N57*AA57+AK65 -> 341.52 | AC57: 0.13 | AD57: =(N57-M57)*AC57 -> 115.8534 | AE57: =17.5 -> 17.5 | AF57: =N57-M57-Q57-AB57-AD57-AE57 -> 401.3066 | AG57: =AF57/N57 -> 0.25081663 | AH57: =#REF!-#REF!-AI57 -> #REF! | AI57: =#REF!*#REF! -> #REF! | AJ57: 0.0085 | AK57: =AJ57*#REF! -> #REF!
A58: 46050 | B58: 8182 | D58: GUARULHOS | E58: SP | F58: ITAQUAQUECETUBA | G58: SP | H58: CYA RUBBER | I58: FINALIZADO | J58: SIM | K58: ALMIR FERREIRA | M58: 760 | N58: 1350 | O58: 50000 | P58: 0.0003 | Q58: =O58*P58 -> 15 | R58: 0.12 | S58: =R58*N58 -> 162 | T58: 0 | U58: 1 | V58: =T58*N58 -> 0 | W58: 0.065 | X58: =N58*W58 -> 87.75 | Y58: =Z58*0.00133 -> 0.01995 | Z58: 15 | AA58: =R58+T58+W58+Y58 -> 0.20495 | AB58: =N58*AA58+AK58 -> 467.9325 | AC58: 0.07 | AD58: =(N58-M58)*AC58 -> 41.3 | AE58: =17.5 -> 17.5 | AF58: =N58-M58-Q58-AB58-AD58-AE58 -> 48.2675 | AG58: =AF58/N58 -> 0.035753704 | AH58: =N65-AB65-AI58 -> 18663.65 | AI58: =Y65*N65 -> 448.875 | AJ58: 0.0085 | AK58: =AJ58*N65 -> 191.25
A59: 45686 | B59: 8235 - 8236 - 8237 - 8238 | D59: IMPERATRIZ | E59: MA | F59: TERESINA | G59: PI | H59: UNIFORT | I59: FINALIZADO | J59: SIM | K59: CLEBISON DOS SANTOS | M59: 3310 | N59: 5800 | O59: 50000 | P59: 0.0003 | Q59: =O59*P59 -> 15 | R59: 0.03 | S59: =R59*N59 -> 174 | T59: 0.035 | U59: 1 | V59: =T59*N59 -> 203 | W59: 0.065 | X59: =N59*W59 -> 377 | Y59: =Z59*0.00133 -> 0.01995 | Z59: 15 | AA59: =R59+T59+W59+Y59 -> 0.14995 | AB59: =N59*AA59+AK59 -> 919.01 | AC59: 0.1 | AD59: =(N59-M59)*AC59 -> 249 | AE59: =17.5 -> 17.5 | AF59: =N59-M59-Q59-AB59-AD59-AE59 -> 1289.49 | AG59: =AF59/N59 -> 0.22232586 | AH59: =N59-AB59-AI59 -> 4765.28 | AI59: =Y59*N59 -> 115.71 | AJ59: 0.0085 | AK59: =AJ59*N59 -> 49.3
A60: 45686 | B60: 8221-8222-8223-8224 | D60: VARZEA GRANDE | E60: MT | F60: VILHENA | G60: RO | H60: UNIFORT | I60: FINALIZADO | J60: SIM | K60: FABIANO RODRIGUES | M60: 2660 | N60: 4500 | O60: 50000 | P60: 0.0003 | Q60: =O60*P60 -> 15 | R60: 0.03 | S60: =R60*N60 -> 135 | T60: 0.035 | U60: 1 | V60: =T60*N60 -> 157.5 | W60: 0.065 | X60: =N60*W60 -> 292.5 | Y60: =Z60*0.00133 -> 0.01995 | Z60: 15 | AA60: =R60+T60+W60+Y60 -> 0.14995 | AB60: =N60*AA60+AK60 -> 713.025 | AC60: 0.1 | AD60: =(N60-M60)*AC60 -> 184 | AE60: =17.5 -> 17.5 | AF60: =N60-M60-Q60-AB60-AD60-AE60 -> 910.475 | AG60: =AF60/N60 -> 0.20232778 | AH60: =N60-AB60-AI60 -> 3697.2 | AI60: =Y60*N60 -> 89.775 | AJ60: 0.0085 | AK60: =AJ60*N60 -> 38.25
A61: 46052 | B61: 8299 | D61: GUARULHOS | E61: SP | F61: DIADEMA | G61: SP | H61: CYA RUBBER | I61: FINALIZADO | J61: SIM | K61: ALEXANDRE HENRIQUE | M61: 760 | N61: 1550 | O61: 50000 | P61: 0.0003 | Q61: =O61*P61 -> 15 | R61: 0.12 | S61: =R61*N61 -> 186 | T61: 0 | U61: 1 | V61: =T61*N61 -> 0 | W61: 0.065 | X61: =N61*W61 -> 100.75 | Y61: =Z61*0.00133 -> 0.01995 | Z61: 15 | AA61: =R61+T61+W61+Y61 -> 0.20495 | AB61: =N61*AA61+AK61 -> 330.8475 | AC61: 0.13 | AD61: =(N61-M61)*AC61 -> 102.7 | AE61: =17.5 -> 17.5 | AF61: =N61-M61-Q61-AB61-AD61-AE61 -> 323.9525 | AG61: =AF61/N61 -> 0.20900161 | AH61: =N61-AB61-AI61 -> 1188.23 | AI61: =Y61*N61 -> 30.9225 | AJ61: 0.0085 | AK61: =AJ61*N61 -> 13.175
A62: 46052 | B62: 8296 | D62: SAO LEOPOLDO | E62: RS | F62: PORTAO | G62: RS | H62: CYA RUBBER | I62: FINALIZADO | J62: SIM | K62: LEANDRO ALVES MATTOS | M62: 860 | N62: 1000 | O62: 30000 | P62: 0.0003 | Q62: =O62*P62 -> 9 | R62: 0 | S62: =R62*N62 -> 0 | T62: 0.035 | U62: 1 | V62: =T62*N62 -> 35 | W62: 0.065 | X62: =N62*W62 -> 65 | Y62: =Z62*0.00133 -> 0.01995 | Z62: 15 | AA62: =R62+T62+W62+Y62 -> 0.11995 | AB62: =N62*AA62+AK62 -> 128.45 | AC62: 0 | AD62: =(N62-M62)*AC62 -> 0 | AE62: =17.5 -> 17.5 | AF62: =N62-M62-Q62-AB62-AD62-AE62 -> -14.95 | AG62: =AF62/N62 -> -0.01495 | AH62: =N62-AB62-AI62 -> 851.6 | AI62: =Y62*N62 -> 19.95 | AJ62: 0.0085 | AK62: =AJ62*N62 -> 8.5
A63: 46052 | B63: 8281 | D63: GUARULHOS | E63: SP | F63: BARUERI | G63: SP | H63: CYA RUBBER | I63: FINALIZADO | J63: SIM | K63: UBALDINE ALVES | M63: 960 | N63: 1630 | O63: 150000 | P63: 0.0003 | Q63: =O63*P63 -> 45 | R63: 0.12 | S63: =R63*N63 -> 195.6 | T63: 0 | U63: 1 | V63: =T63*N63 -> 0 | W63: 0.065 | X63: =N63*W63 -> 105.95 | Y63: =Z63*0.00133 -> 0.01995 | Z63: 15 | AA63: =R63+T63+W63+Y63 -> 0.20495 | AB63: =N63*AA63+AK63 -> 347.9235 | AC63: 0.07 | AD63: =(N63-M63)*AC63 -> 46.9 | AE63: =17.5 -> 17.5 | AF63: =N63-M63-Q63-AB63-AD63-AE63 -> 212.6765 | AG63: =AF63/N63 -> 0.13047638 | AH63: =N63-AB63-AI63 -> 1249.558 | AI63: =Y63*N63 -> 32.5185 | AJ63: 0.0085 | AK63: =AJ63*N63 -> 13.855
A64: 46052 | B64: 8300 | D64: GUARULHOS | E64: SP | F64: ARAQUARI | G64: SC | H64: CYA RUBBER | I64: FINALIZADO | J64: SIM | K64: ALEXANDRE HENRIQUE | M64: 2460 | N64: 4300 | O64: 100000 | P64: 0.0003 | Q64: =O64*P64 -> 30 | R64: 0.12 | S64: =R64*N64 -> 516 | T64: 0 | U64: 1 | V64: =T64*N64 -> 0 | W64: 0.065 | X64: =N64*W64 -> 279.5 | Y64: =Z64*0.00133 -> 0.01995 | Z64: 15 | AA64: =R64+T64+W64+Y64 -> 0.20495 | AB64: =N64*AA64+AK64 -> 917.835 | AC64: 0.12 | AD64: =(N64-M64)*AC64 -> 220.8 | AE64: =17.5 -> 17.5 | AF64: =N64-M64-Q64-AB64-AD64-AE64 -> 653.865 | AG64: =AF64/N64 -> 0.15206163 | AH64: =N64-AB64-AI64 -> 3296.38 | AI64: =Y64*N64 -> 85.785 | AJ64: 0.0085 | AK64: =AJ64*N64 -> 36.55
A65: 46053 | B65: 8309 - 8310 - 8311 - 8312 - 8313 - 8314 | D65: BETIM | E65: MG | F65: VARZEA GRANDE | G65: MT | H65: UNIFORT | I65: FINALIZADO | J65: SIM | K65: ADILSON VASQUES | M65: 14560 | N65: 22500 | O65: 400000 | P65: 0.0003 | Q65: =O65*P65 -> 120 | R65: 0.03 | S65: =R65*N65 -> 675 | T65: 0.035 | U65: 1 | V65: =T65*N65 -> 787.5 | W65: 0.065 | X65: =N65*W65 -> 1462.5 | Y65: =Z65*0.00133 -> 0.01995 | Z65: 15 | AA65: =R65+T65+W65+Y65 -> 0.14995 | AB65: =N65*AA65+AK65 -> 3387.475 | AC65: 0.1 | AD65: =(N65-M65)*AC65 -> 794 | AE65: =17.5 -> 17.5 | AF65: =N65-M65-Q65-AB65-AD65-AE65 -> 3621.025 | AG65: =AF65/N65 -> 0.16093444 | AH65: =N57-AB57-AI65 -> 1226.56 | AI65: =Y57*N57 -> 31.92 | AJ65: 0.0085 | AK65: =AJ65*N57 -> 13.6
V66: =T66*N66 -> 0 | W66: 0.065 | X66: =N66*W66 -> 0 | Y66: =Z66*0.00133 -> 0 | Z66: 0 | AA66: =R66+T66+W66+Y66 -> 0.065 | AB66: =N66*AA66+AK66 -> 0 | AC66: 0 | AD66: =(N66-M66)*AC66 -> 0 | AE66: =17.5 -> 17.5 | AF66: =N66-M66-Q66-AB66-AD66-AE66 -> -17.5 | AG66: =AF66/N66 -> #DIV/0! | AH66: =N66-AB66-AI66 -> 0 | AI66: =Y66*N66 -> 0 | AJ66: 0.0085 | AK66: =AJ66*N66 -> 0
P67: 0.0003 | Q67: =O67*P67 -> 0 | S67: =R67*N67 -> 0 | V67: =T67*N67 -> 0 | W67: 0.065 | X67: =N67*W67 -> 0 | Y67: =Z67*0.00133 -> 0 | Z67: 0 | AA67: =R67+T67+W67+Y67 -> 0.065 | AB67: =N67*AA67+AK67 -> 0 | AC67: 0 | AD67: =(N67-M67)*AC67 -> 0 | AE67: =17.5 -> 17.5 | AF67: =N67-M67-Q67-AB67-AD67-AE67 -> -17.5 | AG67: =AF67/N67 -> #DIV/0! | AH67: =N67-AB67-AI67 -> 0 | AI67: =Y67*N67 -> 0 | AJ67: 0.0085 | AK67: =AJ67*N67 -> 0
P68: 0.0003 | Q68: =O68*P68 -> 0 | S68: =R68*N68 -> 0 | V68: =T68*N68 -> 0 | W68: 0.065 | X68: =N68*W68 -> 0 | Y68: =Z68*0.00133 -> 0 | Z68: 0 | AA68: =R68+T68+W68+Y68 -> 0.065 | AB68: =N68*AA68+AK68 -> 0 | AC68: 0 | AD68: =(N68-M68)*AC68 -> 0 | AE68: =17.5 -> 17.5 | AF68: =N68-M68-Q68-AB68-AD68-AE68 -> -17.5 | AG68: =AF68/N68 -> #DIV/0! | AH68: =N68-AB68-AI68 -> 0 | AI68: =Y68*N68 -> 0 | AJ68: 0.0085 | AK68: =AJ68*N68 -> 0
P69: 0.0003 | Q69: =O69*P69 -> 0 | S69: =R69*N69 -> 0 | V69: =T69*N69 -> 0 | W69: 0.065 | X69: =N69*W69 -> 0 | Y69: =Z69*0.00133 -> 0 | Z69: 0 | AA69: =R69+T69+W69+Y69 -> 0.065 | AB69: =N69*AA69+AK69 -> 0 | AC69: 0 | AD69: =(N69-M69)*AC69 -> 0 | AE69: =17.5 -> 17.5 | AF69: =N69-M69-Q69-AB69-AD69-AE69 -> -17.5 | AG69: =AF69/N69 -> #DIV/0! | AH69: =N69-AB69-AI69 -> 0 | AI69: =Y69*N69 -> 0 | AJ69: 0.0085 | AK69: =AJ69*N69 -> 0
P70: 0.0003 | Q70: =O70*P70 -> 0 | S70: =R70*N70 -> 0 | V70: =T70*N70 -> 0 | W70: 0.065 | X70: =N70*W70 -> 0 | Y70: =Z70*0.00133 -> 0 | Z70: 0 | AA70: =R70+T70+W70+Y70 -> 0.065 | AB70: =N70*AA70+AK70 -> 0 | AC70: 0 | AD70: =(N70-M70)*AC70 -> 0 | AE70: =17.5 -> 17.5 | AF70: =N70-M70-Q70-AB70-AD70-AE70 -> -17.5 | AG70: =AF70/N70 -> #DIV/0! | AH70: =N70-AB70-AI70 -> 0 | AI70: =Y70*N70 -> 0 | AJ70: 0.0085 | AK70: =AJ70*N70 -> 0
P71: 0.0003 | Q71: =O71*P71 -> 0 | S71: =R71*N71 -> 0 | V71: =T71*N71 -> 0 | W71: 0.065 | X71: =N71*W71 -> 0 | Y71: =Z71*0.00133 -> 0 | Z71: 0 | AA71: =R71+T71+W71+Y71 -> 0.065 | AB71: =N71*AA71+AK71 -> 0 | AC71: 0 | AD71: =(N71-M71)*AC71 -> 0 | AE71: =17.5 -> 17.5 | AF71: =N71-M71-Q71-AB71-AD71-AE71 -> -17.5 | AG71: =AF71/N71 -> #DIV/0! | AH71: =N71-AB71-AI71 -> 0 | AI71: =Y71*N71 -> 0 | AJ71: 0.0085 | AK71: =AJ71*N71 -> 0
P72: 0.0003 | Q72: =O72*P72 -> 0 | S72: =R72*N72 -> 0 | V72: =T72*N72 -> 0 | W72: 0.065 | X72: =N72*W72 -> 0 | Y72: =Z72*0.00133 -> 0 | Z72: 0 | AA72: =R72+T72+W72+Y72 -> 0.065 | AB72: =N72*AA72+AK72 -> 0 | AC72: 0 | AD72: =(N72-M72)*AC72 -> 0 | AE72: =17.5 -> 17.5 | AF72: =N72-M72-Q72-AB72-AD72-AE72 -> -17.5 | AG72: =AF72/N72 -> #DIV/0! | AH72: =N72-AB72-AI72 -> 0 | AI72: =Y72*N72 -> 0 | AJ72: 0.0085 | AK72: =AJ72*N72 -> 0
P73: 0.0003 | Q73: =O73*P73 -> 0 | S73: =R73*N73 -> 0 | V73: =T73*N73 -> 0 | W73: 0.065 | X73: =N73*W73 -> 0 | Y73: =Z73*0.00133 -> 0 | Z73: 0 | AA73: =R73+T73+W73+Y73 -> 0.065 | AB73: =N73*AA73+AK73 -> 0 | AC73: 0 | AD73: =(N73-M73)*AC73 -> 0 | AE73: =17.5 -> 17.5 | AF73: =N73-M73-Q73-AB73-AD73-AE73 -> -17.5 | AG73: =AF73/N73 -> #DIV/0! | AH73: =N73-AB73-AI73 -> 0 | AI73: =Y73*N73 -> 0 | AJ73: 0.0085 | AK73: =AJ73*N73 -> 0
P74: 0.0003 | Q74: =O74*P74 -> 0 | S74: =R74*N74 -> 0 | V74: =T74*N74 -> 0 | W74: 0.065 | X74: =N74*W74 -> 0 | Y74: =Z74*0.00133 -> 0 | Z74: 0 | AA74: =R74+T74+W74+Y74 -> 0.065 | AB74: =N74*AA74+AK74 -> 0 | AC74: 0 | AD74: =(N74-M74)*AC74 -> 0 | AE74: =17.5 -> 17.5 | AF74: =N74-M74-Q74-AB74-AD74-AE74 -> -17.5 | AG74: =AF74/N74 -> #DIV/0! | AH74: =N74-AB74-AI74 -> 0 | AI74: =Y74*N74 -> 0 | AJ74: 0.0085 | AK74: =AJ74*N74 -> 0
AF75: =SUM(AF3:AF74) -> 56610.103
D79: META | E79: REALIZADO | F79: COMISSÃO | G79: % REALIZADA | H79: CLIENTES | L79: =M6127
D80: 250000 | E80: =SUMIF(H:H,H80,N:N) -> 277200 | F80: =SUMIF(H:H,H80,AD:AD) -> 10531.238 | G80: =E80/D80 -> 1.1088 | H80: UNIFORT
D81: 20000 | E81: =SUMIF(H:H,H81,N:N) -> 2450 | F81: =SUMIF(H:H,H81,AD:AD) -> 154.7 | G81: =E81/D81 -> 0.1225 | H81: QUISVI
D82: 50000 | E82: =SUMIF(H:H,H82,N:N) -> 61640 | F82: =SUMIF(H:H,H82,AD:AD) -> 2501.2534 | G82: =E82/D82 -> 1.2328 | H82: CYA RUBBER
D83: 15000 | E83: =SUMIF(H:H,H83,N:N) -> 0 | F83: =SUMIF(H:H,H83,AD:AD) -> 0 | G83: =E83/D83 -> 0 | H83: AMERIBRAS
D84: 5000 | E84: =SUMIF(H:H,H84,N:N) -> 3200 | F84: =SUMIF(H:H,H84,AD:AD) -> 200 | G84: =E84/D84 -> 0.64 | H84: TERMOPLAST
D85: 8000 | E85: =SUMIF(H:H,H85,N:N) -> 11000 | F85: =SUMIF(H:H,H85,AD:AD) -> 0 | G85: =E85/D85 -> 1.375 | H85: ARTESHOW
D86: 5000 | E86: =SUMIF(H:H,H86,N:N) -> 0 | F86: =SUMIF(H:H,H86,AD:AD) -> 0 | G86: =E86/D86 -> 0 | H86: MAQPERF
D87: =SUM(D80:D86) -> 353000 | E87: =SUM(E80:E86) -> 355490 | F87: =SUM(F76:F86) -> 13387.191 | G87: =AVERAGE(G80,G86) -> 0.5544 | H87: TOTAL
F91: DIAS ÚTEIS | G91: 0
F92: META DIÁRIA | G92: 0
F93: META | G93: 325000
F94: 100% META | G94: =G95/G93 -> 1.0938154
F95: VALOR TOTAL: | G95: =E87 -> 355490
F97: FRETE MOTORISTA | G97: FATURAMENTO
F98: =SUM(M4:M193) -> 222006.44 | G98: =SUM(N4:N66) -> 355490
F99: PORCENTAGEM MÉDIA | G99: LUCRO EMPRESA
F100: =AF75/G98 -> 0.15924528 | G100: =G98*F100 -> 56610.103
G132: =F4:F1053 | H132: =TODAY() -> 46203
H133: 46053
R134: 0 | T134: =SUMIF(T4:T74,R134,U4:AK71) -> 33
R135: 0.035 | T135: =SUMIF(T4:T74,R135,U4:AK74) -> 29

Sheet FEVEREIRO - 2026
A1: GODI TRANSPORTES - UNINDO PROPÓSITOS
A3: DATA | B3: CTE | C3: MANIFESTO | D3: ORIGEM | E3: ESTADO | F3: DESTINO | G3: ESTADO | H3: CLIENTE | I3: PAGAMENTO | J3: CONFERENCIA | K3: MOTORISTA | L3: TELEFONE | M3: VALOR MOTORISTA | N3: VALOR EMPRESA | O3: NF | P3: SEGURO | Q3: SEGURO | R3: ICMS | S3: ICMS | T3: C.O | V3: CO | W3: IMPOSTO | X3: IMPOSTO | Y3: BOLETO | Z3: DIA PAG | AA3: TOTAL TAXAS | AB3: VALOR IMPOSTO | AC3: % | AD3: COMISSÕES | AE3: BOLETOS | AF3: LUCRO | AG3: RENTABIL | AH3: FRETE LIQ | AI3: MOVA | AJ3: ADQ TAB | AK3: VALOR
A4: 46055 | B4: 8338 | D4: GUARULHOS | E4: SP | F4: SALTO | G4: SP | H4: CYA RUBBER | I4: FINALIZADO | J4: SIM | K4: EMERSON PEREIRA | M4: 1260 | N4: 2100 | O4: 50000 | P4: 0.0003 | Q4: =O4*P4 -> 15 | R4: 0.12 | T4: 0 | U4: 1 | V4: =T4*N4 -> 0 | W4: 0.065 | X4: =N4*W4 -> 136.5 | Y4: =Z4*0.00133 -> 0.01995 | Z4: 15 | AA4: =R4+T4+W4+Y4 -> 0.20495 | AB4: =N4*AA4+AK4 -> 448.245 | AC4: 0.07 | AD4: =(N4-M4)*AC4 -> 58.8 | AE4: =17.5 -> 17.5 | AF4: =N4-M4-Q4-AB4-AD4-AE4 -> 300.455 | AG4: =AF4/N4 -> 0.14307381 | AH4: =N4-AB4-AI4 -> 1609.86 | AI4: =Y4*N4 -> 41.895 | AJ4: 0.0085 | AK4: =AJ4*N4 -> 17.85
A5: 46055 | B5: 8337 | D5: GUARULHOS | E5: SP | F5: GUARAREMA | G5: SP | H5: CYA RUBBER | I5: FINALIZADO | J5: SIM | K5: LEONIDAS CARNEIRO | M5: 960 | N5: 1790 | O5: 50000 | P5: 0.0003 | Q5: =O5*P5 -> 15 | R5: 0.12 | T5: 0 | U5: 1 | V5: =T5*N5 -> 0 | W5: 0.065 | X5: =N5*W5 -> 116.35 | Y5: =Z5*0.00133 -> 0.01995 | Z5: 15 | AA5: =R5+T5+W5+Y5 -> 0.20495 | AB5: =N5*AA5+AK5 -> 382.0755 | AC5: 0.13 | AD5: =(N5-M5)*AC5 -> 107.9 | AE5: =17.5 -> 17.5 | AF5: =N5-M5-Q5-AB5-AD5-AE5 -> 307.5245 | AG5: =AF5/N5 -> 0.1718014 | AH5: =N5-AB5-AI5 -> 1372.214 | AI5: =Y5*N5 -> 35.7105 | AJ5: 0.0085 | AK5: =AJ5*N5 -> 15.215
A6: 46055 | B6: 8359 | D6: GUARULHOS | E6: SP | F6: BRAGANÇA PAULISTA | G6: SP | H6: CYA RUBBER | I6: FINALIZADO | J6: SIM | K6: NATAN SANTOS | M6: 1140 | N6: 1850 | O6: 50000 | P6: 0.0003 | Q6: =O6*P6 -> 15 | R6: 0.12 | T6: 0 | U6: 1 | V6: =T6*N6 -> 0 | W6: 0.065 | X6: =N6*W6 -> 120.25 | Y6: =Z6*0.00133 -> 0.01995 | Z6: 15 | AA6: =R6+T6+W6+Y6 -> 0.20495 | AB6: =N6*AA6+AK6 -> 394.8825 | AC6: 0.07 | AD6: =(N6-M6)*AC6 -> 49.7 | AE6: =17.5 -> 17.5 | AF6: =N6-M6-Q6-AB6-AD6-AE6 -> 232.9175 | AG6: =AF6/N6 -> 0.12590135 | AH6: =N6-AB6-AI6 -> 1418.21 | AI6: =Y6*N6 -> 36.9075 | AJ6: 0.0085 | AK6: =AJ6*N6 -> 15.725
A7: 46055 | B7: 8335 - 8336 | D7: GUARULHOS | E7: SP | F7: ITAQUAQUECETUBA | G7: SP | H7: CYA RUBBER | I7: FINALIZADO | J7: SIM | K7: LEONIDAS CARNEIRO | M7: 1160 | N7: 2970 | O7: 50000 | P7: 0.0003 | Q7: =O7*P7 -> 15 | R7: 0.12 | T7: 0 | U7: 1 | V7: =T7*N7 -> 0 | W7: 0.065 | X7: =N7*W7 -> 193.05 | Y7: =Z7*0.00133 -> 0.01995 | Z7: 15 | AA7: =R7+T7+W7+Y7 -> 0.20495 | AB7: =N7*AA7+AK7 -> 633.9465 | AC7: 0.13 | AD7: =(N7-M7)*AC7 -> 235.3 | AE7: =17.5 -> 17.5 | AF7: =N7-M7-Q7-AB7-AD7-AE7 -> 908.2535 | AG7: =AF7/N7 -> 0.30580926 | AH7: =N7-AB7-AI7 -> 2276.802 | AI7: =Y7*N7 -> 59.2515 | AJ7: 0.0085 | AK7: =AJ7*N7 -> 25.245
A8: 46055 | B8: 8329 | D8: SÃO LEOPOLDO | E8: RS | F8: NOVA PETROPOLIS | G8: RS | H8: CYA RUBBER | I8: FINALIZADO | J8: SIM | K8: LEONARDO POHLMANN | M8: 1310 | N8: 1400 | O8: 50000 | P8: 0.0003 | Q8: =O8*P8 -> 15 | R8: 0 | T8: 0 | U8: 1 | V8: =T8*N8 -> 0 | W8: 0.065 | X8: =N8*W8 -> 91 | Y8: =Z8*0.00133 -> 0.01995 | Z8: 15 | AA8: =R8+T8+W8+Y8 -> 0.08495 | AB8: =N8*AA8+AK8 -> 130.83 | AC8: 0 | AD8: =(N8-M8)*AC8 -> 0 | AE8: =17.5 -> 17.5 | AF8: =N8-M8-Q8-AB8-AD8-AE8 -> -73.33 | AG8: =AF8/N8 -> -0.052378571 | AH8: =N8-AB8-AI8 -> 1241.24 | AI8: =Y8*N8 -> 27.93 | AJ8: 0.0085 | AK8: =AJ8*N8 -> 11.9
A9: 46055 | B9: 8339 - 8340 - 8341 - 8346 - 8350 - 8348 | D9: GOIANIA | E9: GO | F9: MARABA | G9: PA | H9: UNIFORT | I9: FINALIZADO | J9: SIM | K9: JOAO BELEM | M9: 7660 | N9: 13900 | O9: 100000 | P9: 0.0003 | Q9: =O9*P9 -> 30 | R9: 0.03 | T9: 0.035 | U9: 1 | V9: =T9*N9 -> 486.5 | W9: 0.065 | X9: =N9*W9 -> 903.5 | Y9: =Z9*0.00133 -> 0.01995 | Z9: 15 | AA9: =R9+T9+W9+Y9 -> 0.14995 | AB9: =N9*AA9+AK9 -> 2202.455 | AC9: 0.1 | AD9: =(N9-M9)*AC9 -> 624 | AE9: =17.5 -> 17.5 | AF9: =N9-M9-Q9-AB9-AD9-AE9 -> 3366.045 | AG9: =AF9/N9 -> 0.24216151 | AH9: =N9-AB9-AI9 -> 11420.24 | AI9: =Y9*N9 -> 277.305 | AJ9: 0.0085 | AK9: =AJ9*N9 -> 118.15
A10: 46056 | B10: 8411 | D10: SÃO LEOPOLDO | E10: RS | F10: ROCA SALES | G10: RS | H10: CYA RUBBER | I10: FINALIZADO | J10: SIM | K10: VILMAR ANDRE DOS SANTOS | M10: 1860 | N10: 2250 | O10: 50000 | P10: 0.0003 | Q10: =O10*P10 -> 15 | R10: 0 | T10: 0.035 | U10: 1 | V10: =T10*N10 -> 78.75 | W10: 0.065 | X10: =N10*W10 -> 146.25 | Y10: =Z10*0.00133 -> 0.01995 | Z10: 15 | AA10: =R10+T10+W10+Y10 -> 0.11995 | AB10: =N10*AA10+AK10 -> 289.0125 | AC10: 0 | AD10: =(N10-M10)*AC10 -> 0 | AE10: =17.5 -> 17.5 | AF10: =N10-M10-Q10-AB10-AD10-AE10 -> 68.4875 | AG10: =AF10/N10 -> 0.030438889 | AH10: =N10-AB10-AI10 -> 1916.1 | AI10: =Y10*N10 -> 44.8875 | AJ10: 0.0085 | AK10: =AJ10*N10 -> 19.125
A11: 46056 | B11: 8423 | D11: GUARULHOS | E11: SP | F11: SAO PAULO | G11: SP | H11: CYA RUBBER | I11: FINALIZADO | J11: SIM | K11: LEANDRO ALVES | M11: 560 | N11: 1100 | O11: 50000 | P11: 0.0003 | Q11: =O11*P11 -> 15 | R11: 0.12 | T11: 0 | U11: 1 | V11: =T11*N11 -> 0 | W11: 0.065 | X11: =N11*W11 -> 71.5 | Y11: =Z11*0.00133 -> 0.01995 | Z11: 15 | AA11: =R11+T11+W11+Y11 -> 0.20495 | AB11: =N11*AA11+AK11 -> 234.795 | AC11: 0.13 | AD11: =(N11-M11)*AC11 -> 70.2 | AE11: =17.5 -> 17.5 | AF11: =N11-M11-Q11-AB11-AD11-AE11 -> 202.505 | AG11: =AF11/N11 -> 0.18409545 | AH11: =N11-AB11-AI11 -> 843.26 | AI11: =Y11*N11 -> 21.945 | AJ11: 0.0085 | AK11: =AJ11*N11 -> 9.35
A12: 46057 | B12: 8466 | D12: GUARULHOS | E12: SP | F12: ITAQUAQUECETUBA | G12: SP | H12: CYA RUBBER | I12: FINALIZADO | J12: SIM | K12: EDIVALDO DA SILVA | M12: 460 | N12: 980 | O12: 20000 | P12: 0.0003 | Q12: =O12*P12 -> 6 | R12: 0.12 | T12: 0 | U12: 1 | V12: =T12*N12 -> 0 | W12: 0.065 | X12: =N12*W12 -> 63.7 | Y12: =Z12*0.00133 -> 0.01995 | Z12: 15 | AA12: =R12+T12+W12+Y12 -> 0.20495 | AB12: =N12*AA12+AK12 -> 209.181 | AC12: 0.13 | AD12: =(N12-M12)*AC12 -> 67.6 | AE12: =17.5 -> 17.5 | AF12: =N12-M12-Q12-AB12-AD12-AE12 -> 219.719 | AG12: =AF12/N12 -> 0.22420306 | AH12: =N12-AB12-AI12 -> 751.268 | AI12: =Y12*N12 -> 19.551 | AJ12: 0.0085 | AK12: =AJ12*N12 -> 8.33
A13: 46057 | B13: 8465 | D13: GUARULHOS | E13: SP | F13: SAO JOSE DOS CAMPOS | G13: SP | H13: CYA RUBBER | I13: FINALIZADO | J13: SIM | K13: EDIVALDO DA SILVA | M13: 880 | N13: 1680 | O13: 50000 | P13: 0.0003 | Q13: =O13*P13 -> 15 | R13: 0.12 | T13: 0 | U13: 1 | V13: =T13*N13 -> 0 | W13: 0.065 | X13: =N13*W13 -> 109.2 | Y13: =Z13*0.00133 -> 0.01995 | Z13: 15 | AA13: =R13+T13+W13+Y13 -> 0.20495 | AB13: =N13*AA13+AK13 -> 358.596 | AC13: 0.13 | AD13: =(N13-M13)*AC13 -> 104 | AE13: =17.5 -> 17.5 | AF13: =N13-M13-Q13-AB13-AD13-AE13 -> 304.904 | AG13: =AF13/N13 -> 0.18149048 | AH13: =N13-AB13-AI13 -> 1287.888 | AI13: =Y13*N13 -> 33.516 | AJ13: 0.0085 | AK13: =AJ13*N13 -> 14.28
A14: 46057 | B14: 8427 | D14: GUARULHOS | E14: SP | F14: DIADEMA | G14: SP | H14: CYA RUBBER | I14: FINALIZADO | J14: SIM | K14: FERNANDO DOS SANTOS | M14: 660 | N14: 1200 | O14: 50000 | P14: 0.0003 | Q14: =O14*P14 -> 15 | R14: 0.12 | T14: 0 | U14: 1 | V14: =T14*N14 -> 0 | W14: 0.065 | X14: =N14*W14 -> 78 | Y14: =Z14*0.00133 -> 0.01995 | Z14: 15 | AA14: =R14+T14+W14+Y14 -> 0.20495 | AB14: =N14*AA14+AK14 -> 256.14 | AC14: 0.13 | AD14: =(N14-M14)*AC14 -> 70.2 | AE14: =17.5 -> 17.5 | AF14: =N14-M14-Q14-AB14-AD14-AE14 -> 181.16 | AG14: =AF14/N14 -> 0.15096667 | AH14: =N14-AB14-AI14 -> 919.92 | AI14: =Y14*N14 -> 23.94 | AJ14: 0.0085 | AK14: =AJ14*N14 -> 10.2
A15: 46057 | B15: 8490 8491 | D15: IMPERATRIZ | E15: MA | F15: TERESINA | G15: PI | H15: UNIFORT | I15: FINALIZADO | J15: SIM | K15: AECIO VIEIRA | M15: 2860 | N15: 5800 | O15: 80000 | P15: 0.0003 | Q15: =O15*P15 -> 24 | R15: 0.03 | T15: 0.035 | U15: 1 | V15: =T15*N15 -> 203 | W15: 0.065 | X15: =N15*W15 -> 377 | Y15: =Z15*0.00133 -> 0.01995 | Z15: 15 | AA15: =R15+T15+W15+Y15 -> 0.14995 | AB15: =N15*AA15+AK15 -> 919.01 | AC15: 0.1 | AD15: =(N15-M15)*AC15 -> 294 | AE15: =17.5 -> 17.5 | AF15: =N15-M15-Q15-AB15-AD15-AE15 -> 1685.49 | AG15: =AF15/N15 -> 0.29060172 | AH15: =N15-AB15-AI15 -> 4765.28 | AI15: =Y15*N15 -> 115.71 | AJ15: 0.0085 | AK15: =AJ15*N15 -> 49.3
A16: 46057 | B16: 8479 - 8480 - 8481 - 8483 | D16: GOIANIA | E16: GO | F16: VARZEA GRANDE | G16: MT | H16: UNIFORT | I16: FINALIZADO | J16: SIM | K16: JOAO PEREIRA | M16: 3960 | N16: 6900 | O16: 80000 | P16: 0.0003 | Q16: =O16*P16 -> 24 | R16: 0.03 | T16: 0.035 | U16: 1 | V16: =T16*N16 -> 241.5 | W16: 0.065 | X16: =N16*W16 -> 448.5 | Y16: =Z16*0.00133 -> 0.01995 | Z16: 15 | AA16: =R16+T16+W16+Y16 -> 0.14995 | AB16: =N16*AA16+AK16 -> 1093.305 | AC16: 0.1 | AD16: =(N16-M16)*AC16 -> 294 | AE16: =17.5 -> 17.5 | AF16: =N16-M16-Q16-AB16-AD16-AE16 -> 1511.195 | AG16: =AF16/N16 -> 0.21901377 | AH16: =N16-AB16-AI16 -> 5669.04 | AI16: =Y16*N16 -> 137.655 | AJ16: 0.0085 | AK16: =AJ16*N16 -> 58.65
A17: 46058 | B17: 8504 8505 8506 8507 8508 8509 | D17: GOIANIA | E17: GO | F17: MARABA | G17: PA | H17: UNIFORT | I17: FINALIZADO | J17: SIM | K17: NEUDSON FERREIRA | M17: 6310 | N17: 10900 | O17: 100000 | P17: 0.0003 | Q17: =O17*P17 -> 30 | R17: 0.03 | T17: 0.035 | U17: 1 | V17: =T17*N17 -> 381.5 | W17: 0.065 | X17: =N17*W17 -> 708.5 | Y17: =Z17*0.00133 -> 0.01995 | Z17: 15 | AA17: =R17+T17+W17+Y17 -> 0.14995 | AB17: =N17*AA17+AK17 -> 1727.105 | AC17: 0.1 | AD17: =(N17-M17)*AC17 -> 459 | AE17: =17.5 -> 17.5 | AF17: =N17-M17-Q17-AB17-AD17-AE17 -> 2356.395 | AG17: =AF17/N17 -> 0.21618303 | AH17: =N17-AB17-AI17 -> 8955.44 | AI17: =Y17*N17 -> 217.455 | AJ17: 0.0085 | AK17: =AJ17*N17 -> 92.65
A18: 46058 | B18: 8519 | D18: GUARULHOS | E18: SP | F18: GUARULHOS | G18: SP | H18: CYA RUBBER | I18: FINALIZADO | J18: SIM | K18: LEANDRO ALVES | M18: 560 | N18: 1100 | O18: 20000 | P18: 0.0003 | Q18: =O18*P18 -> 6 | R18: 0.12 | T18: 0 | U18: 1 | V18: =T18*N18 -> 0 | W18: 0.065 | X18: =N18*W18 -> 71.5 | Y18: =Z18*0.00133 -> 0.01995 | Z18: 15 | AA18: =R18+T18+W18+Y18 -> 0.20495 | AB18: =N18*AA18+AK18 -> 234.795 | AC18: 0.13 | AD18: =(N18-M18)*AC18 -> 70.2 | AE18: =17.5 -> 17.5 | AF18: =N18-M18-Q18-AB18-AD18-AE18 -> 211.505 | AG18: =AF18/N18 -> 0.19227727 | AH18: =N18-AB18-AI18 -> 843.26 | AI18: =Y18*N18 -> 21.945 | AJ18: 0.0085 | AK18: =AJ18*N18 -> 9.35
A19: 46058 | B19: 8527 - 8528 | D19: VARZEA GRANDE | E19: MT | F19: VILHENA | G19: RO | H19: UNIFORT | I19: FINALIZADO | J19: SIM | K19: FABIANO RODRIGUES | M19: 3260 | N19: 6500 | O19: 50000 | P19: 0.0003 | Q19: =O19*P19 -> 15 | R19: 0.03 | T19: 0.035 | U19: 1 | V19: =T19*N19 -> 227.5 | W19: 0.065 | X19: =N19*W19 -> 422.5 | Y19: =Z19*0.00133 -> 0.01995 | Z19: 15 | AA19: =R19+T19+W19+Y19 -> 0.14995 | AB19: =N19*AA19+AK19 -> 1029.925 | AC19: 0.1 | AD19: =(N19-M19)*AC19 -> 324 | AE19: =17.5 -> 17.5 | AF19: =N19-M19-Q19-AB19-AD19-AE19 -> 1853.575 | AG19: =AF19/N19 -> 0.28516538 | AH19: =N19-AB19-AI19 -> 5340.4 | AI19: =Y19*N19 -> 129.675 | AJ19: 0.0085 | AK19: =AJ19*N19 -> 55.25
A20: 46059 | B20: 8583 - 8584 - 8585 - 8586 - 8587 | D20: BETIM | E20: MG | F20: GOIANIA | G20: GO | H20: UNIFORT | I20: FINALIZADO | J20: SIM | K20: LUIZ FELIPE DA SILVA | M20: 5060 | N20: 8200 | O20: 150000 | P20: 0.0003 | Q20: =O20*P20 -> 45 | R20: 0.03 | T20: 0.035 | U20: 1 | V20: =T20*N20 -> 287 | W20: 0.065 | X20: =N20*W20 -> 533 | Y20: =Z20*0.00133 -> 0.01995 | Z20: 15 | AA20: =R20+T20+W20+Y20 -> 0.14995 | AB20: =N20*AA20+AK20 -> 1299.29 | AC20: 0.1 | AD20: =(N20-M20)*AC20 -> 314 | AE20: =17.5 -> 17.5 | AF20: =N20-M20-Q20-AB20-AD20-AE20 -> 1464.21 | AG20: =AF20/N20 -> 0.1785622 | AH20: =N20-AB20-AI20 -> 6737.12 | AI20: =Y20*N20 -> 163.59 | AJ20: 0.0085 | AK20: =AJ20*N20 -> 69.7
A21: 46060 | B21: 8593 | D21: MARABA | E21: PA | F21: GOIANIA | G21: GO | H21: UNIFORT | I21: FINALIZADO | J21: SIM | K21: RAFAEL CORREA | M21: 7530 | N21: 11600 | O21: 100000 | P21: 0.0003 | Q21: =O21*P21 -> 30 | R21: 0.03 | T21: 0.035 | U21: 1 | V21: =T21*N21 -> 406 | W21: 0.065 | X21: =N21*W21 -> 754 | Y21: =Z21*0.00133 -> 0.01995 | Z21: 15 | AA21: =R21+T21+W21+Y21 -> 0.14995 | AB21: =N21*AA21+AK21 -> 1838.02 | AC21: 0.1 | AD21: =(N21-M21)*AC21 -> 407 | AE21: =17.5 -> 17.5 | AF21: =N21-M21-Q21-AB21-AD21-AE21 -> 1777.48 | AG21: =AF21/N21 -> 0.15323103 | AH21: =N21-AB21-AI21 -> 9530.56 | AI21: =Y21*N21 -> 231.42 | AJ21: 0.0085 | AK21: =AJ21*N21 -> 98.6
A22: 46061 | B22: 8597 - 8598 - 8599 - 8600 - 8601 - 8602 | D22: GOIANIA | E22: GO | F22: MARABA | G22: PA | H22: UNIFORT | I22: FINALIZADO | J22: SIM | K22: WILSON RODRIGUES | M22: 6710 | N22: 12900 | O22: 50000 | P22: 0.0003 | Q22: =O22*P22 -> 15 | R22: 0.03 | T22: 0.035 | U22: 1 | V22: =T22*N22 -> 451.5 | W22: 0.065 | X22: =N22*W22 -> 838.5 | Y22: =Z22*0.00133 -> 0.01995 | Z22: 15 | AA22: =R22+T22+W22+Y22 -> 0.14995 | AB22: =N22*AA22+AK22 -> 2044.005 | AC22: 0.1 | AD22: =(N22-M22)*AC22 -> 619 | AE22: =17.5 -> 17.5 | AF22: =N22-M22-Q22-AB22-AD22-AE22 -> 3494.495 | AG22: =AF22/N22 -> 0.27089109 | AH22: =N22-AB22-AI22 -> 10598.64 | AI22: =Y22*N22 -> 257.355 | AJ22: 0.0085 | AK22: =AJ22*N22 -> 109.65
A23: 46062 | B23: 8625 8626 8627 8628 | D23: GOIANIA | E23: GO | F23: VARZEA GRANDE | G23: MT | H23: UNIFORT | I23: FINALIZADO | J23: SIM | K23: JOSE VICENTE DA SILVA | M23: =5025.83+60 -> 5085.83 | N23: 8500 | O23: 50000 | P23: 0.0003 | Q23: =O23*P23 -> 15 | R23: 0.03 | T23: 0.035 | U23: 1 | V23: =T23*N23 -> 297.5 | W23: 0.065 | X23: =N23*W23 -> 552.5 | Y23: =Z23*0.00133 -> 0.01995 | Z23: 15 | AA23: =R23+T23+W23+Y23 -> 0.14995 | AB23: =N23*AA23+AK23 -> 1346.825 | AC23: 0.1 | AD23: =(N23-M23)*AC23 -> 341.417 | AE23: =17.5 -> 17.5 | AF23: =N23-M23-Q23-AB23-AD23-AE23 -> 1693.428 | AG23: =AF23/N23 -> 0.19922682 | AH23: =N23-AB23-AI23 -> 6983.6 | AI23: =Y23*N23 -> 169.575 | AJ23: 0.0085 | AK23: =AJ23*N23 -> 72.25
A24: 46062 | B24: 8617 8618 | D24: GUARULHOS | E24: SP | F24: SAO PAULO | G24: SP | H24: CYA RUBBER | I24: FINALIZADO | J24: SIM | K24: EDI LAZARO GONCALVES | M24: 960 | N24: 1630 | O24: 100000 | P24: 0.0003 | Q24: =O24*P24 -> 30 | R24: 0.12 | T24: 0 | U24: 1 | V24: =T24*N24 -> 0 | W24: 0.065 | X24: =N24*W24 -> 105.95 | Y24: =Z24*0.00133 -> 0.01995 | Z24: 15 | AA24: =R24+T24+W24+Y24 -> 0.20495 | AB24: =N24*AA24+AK24 -> 347.9235 | AC24: 0.07 | AD24: =(N24-M24)*AC24 -> 46.9 | AE24: =17.5 -> 17.5 | AF24: =N24-M24-Q24-AB24-AD24-AE24 -> 227.6765 | AG24: =AF24/N24 -> 0.13967883 | AH24: =N24-AB24-AI24 -> 1249.558 | AI24: =Y24*N24 -> 32.5185 | AJ24: 0.0085 | AK24: =AJ24*N24 -> 13.855
A25: 46062 | B25: 8644 | D25: ROCA SALES | E25: RS | F25: SÃO LEOPOLDO | G25: RS | H25: QUISVI | I25: FINALIZADO | J25: SIM | K25: CELSO LERMEN | M25: 1260 | N25: 2100 | O25: 80000 | P25: 0.0003 | Q25: =O25*P25 -> 24 | R25: 0 | T25: 0.035 | U25: 1 | V25: =T25*N25 -> 73.5 | W25: 0.065 | X25: =N25*W25 -> 136.5 | Y25: =Z25*0.00133 -> 0.01995 | Z25: 15 | AA25: =R25+T25+W25+Y25 -> 0.11995 | AB25: =N25*AA25+AK25 -> 269.745 | AC25: 0.13 | AD25: =(N25-M25)*AC25 -> 109.2 | AE25: =17.5 -> 17.5 | AF25: =N25-M25-Q25-AB25-AD25-AE25 -> 419.555 | AG25: =AF25/N25 -> 0.1997881 | AH25: =N25-AB25-AI25 -> 1788.36 | AI25: =Y25*N25 -> 41.895 | AJ25: 0.0085 | AK25: =AJ25*N25 -> 17.85
A26: 46063 | B26: 8652 | D26: GUARULHOS | E26: SP | F26: SALTO | G26: SP | H26: CYA RUBBER | I26: FINALIZADO | J26: SIM | K26: AGNALDO | M26: 1060 | N26: 2100 | O26: 50000 | P26: 0.0003 | Q26: =O26*P26 -> 15 | R26: 0.12 | T26: 0 | U26: 1 | V26: =T26*N26 -> 0 | W26: 0.065 | X26: =N26*W26 -> 136.5 | Y26: =Z26*0.00133 -> 0.01995 | Z26: 15 | AA26: =R26+T26+W26+Y26 -> 0.20495 | AB26: =N26*AA26+AK26 -> 448.245 | AC26: 0.13 | AD26: =(N26-M26)*AC26 -> 135.2 | AE26: =17.5 -> 17.5 | AF26: =N26-M26-Q26-AB26-AD26-AE26 -> 424.055 | AG26: =AF26/N26 -> 0.20193095 | AH26: =N26-AB26-AI26 -> 1609.86 | AI26: =Y26*N26 -> 41.895 | AJ26: 0.0085 | AK26: =AJ26*N26 -> 17.85
A27: 46063 | B27: 8658 | D27: GUARULHOS | E27: SP | F27: DIADEMA | G27: SP | H27: CYA RUBBER | I27: FINALIZADO | J27: SIM | K27: EMERSON NUNES | M27: 610 | N27: 1200 | O27: 50000 | P27: 0.0003 | Q27: =O27*P27 -> 15 | R27: 0.12 | T27: 0 | U27: 1 | V27: =T27*N27 -> 0 | W27: 0.065 | X27: =N27*W27 -> 78 | Y27: =Z27*0.00133 -> 0.01995 | Z27: 15 | AA27: =R27+T27+W27+Y27 -> 0.20495 | AB27: =N27*AA27+AK27 -> 256.14 | AC27: 0.13 | AD27: =(N27-M27)*AC27 -> 76.7 | AE27: =17.5 -> 17.5 | AF27: =N27-M27-Q27-AB27-AD27-AE27 -> 224.66 | AG27: =AF27/N27 -> 0.18721667 | AH27: =N27-AB27-AI27 -> 919.92 | AI27: =Y27*N27 -> 23.94 | AJ27: 0.0085 | AK27: =AJ27*N27 -> 10.2
A28: 46064 | B28: 8698 | D28: SAO LEOPOLDO | E28: RS | F28: BOM PRINCIPIO | G28: RS | H28: CYA RUBBER | I28: FINALIZADO | J28: SIM | K28: SERGIO CERVELLIN | M28: 960 | N28: 1550 | O28: 100000 | P28: 0.0003 | Q28: =O28*P28 -> 30 | R28: 0 | T28: 0.035 | U28: 1 | V28: =T28*N28 -> 54.25 | W28: 0.065 | X28: =N28*W28 -> 100.75 | Y28: =Z28*0.00133 -> 0.01995 | Z28: 15 | AA28: =R28+T28+W28+Y28 -> 0.11995 | AB28: =N28*AA28+AK28 -> 199.0975 | AC28: 0.13 | AD28: =(N28-M28)*AC28 -> 76.7 | AE28: =17.5 -> 17.5 | AF28: =N28-M28-Q28-AB28-AD28-AE28 -> 266.7025 | AG28: =AF28/N28 -> 0.17206613 | AH28: =N28-AB28-AI28 -> 1319.98 | AI28: =Y28*N28 -> 30.9225 | AJ28: 0.0085 | AK28: =AJ28*N28 -> 13.175
A29: 46064 | B29: 8700 | D29: GUARULHOS | E29: SP | F29: GUARULHOS | G29: SP | H29: CYA RUBBER | I29: FINALIZADO | J29: SIM | K29: AGNALDO CICERO | M29: 460 | N29: 1050 | O29: 20000 | P29: 0.0003 | Q29: =O29*P29 -> 6 | R29: 0.12 | T29: 0 | U29: 1 | V29: =T29*N29 -> 0 | W29: 0.065 | X29: =N29*W29 -> 68.25 | Y29: =Z29*0.00133 -> 0.01995 | Z29: 15 | AA29: =R29+T29+W29+Y29 -> 0.20495 | AB29: =N29*AA29+AK29 -> 224.1225 | AC29: 0.13 | AD29: =(N29-M29)*AC29 -> 76.7 | AE29: =17.5 -> 17.5 | AF29: =N29-M29-Q29-AB29-AD29-AE29 -> 265.6775 | AG29: =AF29/N29 -> 0.25302619 | AH29: =N29-AB29-AI29 -> 804.93 | AI29: =Y29*N29 -> 20.9475 | AJ29: 0.0085 | AK29: =AJ29*N29 -> 8.925
A30: 46064 | B30: 8708 8709 | D30: VARZEA GRANDE | E30: MT | F30: VILHENA | G30: RO | H30: UNIFORT | I30: FINALIZADO | J30: SIM | K30: MIGUEL FERNANDO | M30: 3560 | N30: 5900 | O30: 30000 | P30: 0.0003 | Q30: =O30*P30 -> 9 | R30: 0.03 | T30: 0.035 | U30: 1 | V30: =T30*N30 -> 206.5 | W30: 0.065 | X30: =N30*W30 -> 383.5 | Y30: =Z30*0.00133 -> 0.01995 | Z30: 15 | AA30: =R30+T30+W30+Y30 -> 0.14995 | AB30: =N30*AA30+AK30 -> 934.855 | AC30: 0.1 | AD30: =(N30-M30)*AC30 -> 234 | AE30: =17.5 -> 17.5 | AF30: =N30-M30-Q30-AB30-AD30-AE30 -> 1144.645 | AG30: =AF30/N30 -> 0.19400763 | AH30: =N30-AB30-AI30 -> 4847.44 | AI30: =Y30*N30 -> 117.705 | AJ30: 0.0085 | AK30: =AJ30*N30 -> 50.15
A31: 46064 | B31: 8706 | D31: SÃO LEOPOLDO | E31: RS | F31: CAXIAS DO SUL | G31: RS | H31: CYA RUBBER | I31: FINALIZADO | J31: SIM | K31: SERGIO CERVELLIN | M31: 1150 | N31: 1750 | O31: 100000 | P31: 0.0003 | Q31: =O31*P31 -> 30 | R31: 0 | T31: 0.035 | U31: 1 | V31: =T31*N31 -> 61.25 | W31: 0.065 | X31: =N31*W31 -> 113.75 | Y31: =Z31*0.00133 -> 0.01995 | Z31: 15 | AA31: =R31+T31+W31+Y31 -> 0.11995 | AB31: =N31*AA31+AK31 -> 224.7875 | AC31: 0.1 | AD31: =(N31-M31)*AC31 -> 60 | AE31: =17.5 -> 17.5 | AF31: =N31-M31-Q31-AB31-AD31-AE31 -> 267.7125 | AG31: =AF31/N31 -> 0.15297857 | AH31: =N31-AB31-AI31 -> 1490.3 | AI31: =Y31*N31 -> 34.9125 | AJ31: 0.0085 | AK31: =AJ31*N31 -> 14.875
A32: 46065 | B32: 8773-8774-8776-8777-8778-8779 | D32: GOIANIA | E32: GO | F32: MARABA | G32: PA | H32: UNIFORT | I32: FINALIZADO | J32: SIM | K32: MAILSON RODRIGUES | M32: 6560 | N32: 10900 | O32: 50000 | P32: 0.0003 | Q32: =O32*P32 -> 15 | R32: 0.03 | T32: 0.035 | U32: 1 | V32: =T32*N32 -> 381.5 | W32: 0.065 | X32: =N32*W32 -> 708.5 | Y32: =Z32*0.00133 -> 0.01995 | Z32: 15 | AA32: =R32+T32+W32+Y32 -> 0.14995 | AB32: =N32*AA32+AK32 -> 1727.105 | AC32: 0.1 | AD32: =(N32-M32)*AC32 -> 434 | AE32: =17.5 -> 17.5 | AF32: =N32-M32-Q32-AB32-AD32-AE32 -> 2146.395 | AG32: =AF32/N32 -> 0.19691697 | AH32: =N32-AB32-AI32 -> 8955.44 | AI32: =Y32*N32 -> 217.455 | AJ32: 0.0085 | AK32: =AJ32*N32 -> 92.65
A33: 46065 | B33: 8780 8781 8782 8783 | D33: GOIANIA | E33: GO | F33: VARZEA GRANDE | G33: MT | H33: UNIFORT | I33: FINALIZADO | J33: SIM | K33: JOSE ANTONIO | M33: 4460 | N33: 7500 | O33: 100000 | P33: 0.0003 | Q33: =O33*P33 -> 30 | R33: 0.03 | T33: 0.035 | U33: 1 | V33: =T33*N33 -> 262.5 | W33: 0.065 | X33: =N33*W33 -> 487.5 | Y33: =Z33*0.00133 -> 0.01995 | Z33: 15 | AA33: =R33+T33+W33+Y33 -> 0.14995 | AB33: =N33*AA33+AK33 -> 1188.375 | AC33: 0.1 | AD33: =(N33-M33)*AC33 -> 304 | AE33: =17.5 -> 17.5 | AF33: =N33-M33-Q33-AB33-AD33-AE33 -> 1500.125 | AG33: =AF33/N33 -> 0.20001667 | AH33: =N33-AB33-AI33 -> 6162 | AI33: =Y33*N33 -> 149.625 | AJ33: 0.0085 | AK33: =AJ33*N33 -> 63.75
A34: 46065 | B34: 28775 | D34: DIADEMA | E34: SP | F34: PORTO FERREIRA | G34: SP | H34: TERMOCOLOR | I34: FINALIZADO | J34: SIM | K34: THIAGO MENDES | M34: 2160 | N34: 3490 | O34: 80000 | P34: 0.0003 | Q34: =O34*P34 -> 24 | R34: 0.12 | T34: 0 | U34: 1 | V34: =T34*N34 -> 0 | W34: 0.065 | X34: =N34*W34 -> 226.85 | Y34: =Z34*0.00133 -> 0.01995 | Z34: 15 | AA34: =R34+T34+W34+Y34 -> 0.20495 | AB34: =N34*AA34+AK34 -> 744.9405 | AC34: 0 | AD34: 200 | AE34: =17.5 -> 17.5 | AF34: =N34-M34-Q34-AB34-AD34-AE34 -> 343.5595 | AG34: =AF34/N34 -> 0.098441117 | AH34: =N34-AB34-AI34 -> 2675.434 | AI34: =Y34*N34 -> 69.6255 | AJ34: 0.0085 | AK34: =AJ34*N34 -> 29.665
A35: 46065 | B35: 8785 | D35: ROCA SALES | E35: RS | F35: SÃO LEOPOLDO | G35: RS | H35: QUISVI | I35: FINALIZADO | J35: SIM | K35: LAURI CRISTIAN | M35: 1260 | N35: 2250 | O35: 80000 | P35: 0.0003 | Q35: =O35*P35 -> 24 | R35: 0 | T35: 0.035 | U35: 1 | V35: =T35*N35 -> 78.75 | W35: 0.065 | X35: =N35*W35 -> 146.25 | Y35: =Z35*0.00133 -> 0.01995 | Z35: 15 | AA35: =R35+T35+W35+Y35 -> 0.11995 | AB35: =N35*AA35+AK35 -> 289.0125 | AC35: 0.13 | AD35: =(N35-M35)*AC35 -> 128.7 | AE35: =17.5 -> 17.5 | AF35: =N35-M35-Q35-AB35-AD35-AE35 -> 530.7875 | AG35: =AF35/N35 -> 0.23590556 | AH35: =N35-AB35-AI35 -> 1916.1 | AI35: =Y35*N35 -> 44.8875 | AJ35: 0.0085 | AK35: =AJ35*N35 -> 19.125
A36: 46065 | B36: 8760 | D36: GUARULHOS | E36: SP | F36: GUARULHOS | G36: SP | H36: CYA RUBBER | I36: FINALIZADO | J36: SIM | K36: EMERSON NUNES | M36: 560 | N36: 1150 | O36: 50000 | P36: 0.0003 | Q36: =O36*P36 -> 15 | R36: 0.12 | T36: 0 | U36: 1 | V36: =T36*N36 -> 0 | W36: 0.065 | X36: =N36*W36 -> 74.75 | Y36: =Z36*0.00133 -> 0.01995 | Z36: 15 | AA36: =R36+T36+W36+Y36 -> 0.20495 | AB36: =N36*AA36+AK36 -> 245.4675 | AC36: 0.13 | AD36: =(N36-M36)*AC36 -> 76.7 | AE36: =17.5 -> 17.5 | AF36: =N36-M36-Q36-AB36-AD36-AE36 -> 235.3325 | AG36: =AF36/N36 -> 0.20463696 | AH36: =N36-AB36-AI36 -> 881.59 | AI36: =Y36*N36 -> 22.9425 | AJ36: 0.0085 | AK36: =AJ36*N36 -> 9.775
A37: 46066 | B37: 8850 | D37: GUARULHOS | E37: SP | F37: BRAGANÇA PAULISTA | G37: SP | H37: QUISVI | I37: FINALIZADO | J37: SIM | K37: ALMIR FERREIRA | M37: 960 | N37: 1650 | O37: 50000 | P37: 0.0003 | Q37: =O37*P37 -> 15 | R37: 0.12 | T37: 0 | U37: 1 | V37: =T37*N37 -> 0 | W37: 0.065 | X37: =N37*W37 -> 107.25 | Y37: =Z37*0.00133 -> 0.01995 | Z37: 15 | AA37: =R37+T37+W37+Y37 -> 0.20495 | AB37: =N37*AA37+AK37 -> 352.1925 | AC37: 0.07 | AD37: =(N37-M37)*AC37 -> 48.3 | AE37: =17.5 -> 17.5 | AF37: =N37-M37-Q37-AB37-AD37-AE37 -> 257.0075 | AG37: =AF37/N37 -> 0.15576212 | AH37: =N37-AB37-AI37 -> 1264.89 | AI37: =Y37*N37 -> 32.9175 | AJ37: 0.0085 | AK37: =AJ37*N37 -> 14.025
A38: 46066 | B38: 8851 | D38: ROCA SALES | E38: RS | F38: NOVA PRATA | G38: RS | H38: CYA RUBBER | I38: FINALIZADO | J38: SIM | K38: DIOGENES JUNIOR | M38: 1060 | N38: 2300 | O38: 60000 | P38: 0.0003 | Q38: =O38*P38 -> 18 | R38: 0 | T38: 0.035 | U38: 1 | V38: =T38*N38 -> 80.5 | W38: 0.065 | X38: =N38*W38 -> 149.5 | Y38: =Z38*0.00133 -> 0.01995 | Z38: 15 | AA38: =R38+T38+W38+Y38 -> 0.11995 | AB38: =N38*AA38+AK38 -> 295.435 | AC38: 0.13 | AD38: =(N38-M38)*AC38 -> 161.2 | AE38: =17.5 -> 17.5 | AF38: =N38-M38-Q38-AB38-AD38-AE38 -> 747.865 | AG38: =AF38/N38 -> 0.3251587 | AH38: =N38-AB38-AI38 -> 1958.68 | AI38: =Y38*N38 -> 45.885 | AJ38: 0.0085 | AK38: =AJ38*N38 -> 19.55
A39: 46071 | B39: 8886 | D39: GUARULHOS | E39: SP | F39: SALTO | G39: SP | H39: CYA RUBBER | I39: FINALIZADO | J39: SIM | K39: AGNALDO CICERO | M39: 1060 | N39: 2100 | O39: 80000 | P39: 0.0003 | Q39: =O39*P39 -> 24 | R39: 0.12 | T39: 0 | U39: 1 | V39: =T39*N39 -> 0 | W39: 0.065 | X39: =N39*W39 -> 136.5 | Y39: =Z39*0.00133 -> 0.01995 | Z39: 15 | AA39: =R39+T39+W39+Y39 -> 0.20495 | AB39: =N39*AA39+AK39 -> 448.245 | AC39: 0.1 | AD39: =(N39-M39)*AC39 -> 104 | AE39: =17.5 -> 17.5 | AF39: =N39-M39-Q39-AB39-AD39-AE39 -> 446.255 | AG39: =AF39/N39 -> 0.21250238 | AH39: =N39-AB39-AI39 -> 1609.86 | AI39: =Y39*N39 -> 41.895 | AJ39: 0.0085 | AK39: =AJ39*N39 -> 17.85
A40: 46071 | B40: 8887 | D40: GUARULHOS | E40: SP | F40: GUARAREMA | G40: SP | H40: CYA RUBBER | I40: FINALIZADO | J40: SIM | K40: EGINELSON DE SOUZA | M40: =834.3+60 -> 894.3 | N40: 1350 | O40: 66780 | P40: 0.0003 | Q40: =O40*P40 -> 20.034 | R40: 0.12 | T40: 0 | U40: 1 | V40: =T40*N40 -> 0 | W40: 0.065 | X40: =N40*W40 -> 87.75 | Y40: =Z40*0.00133 -> 0.01995 | Z40: 15 | AA40: =R40+T40+W40+Y40 -> 0.20495 | AB40: =N40*AA40+AK40 -> 288.1575 | AC40: 0.06 | AD40: =(N40-M40)*AC40 -> 27.342 | AE40: =17.5 -> 17.5 | AF40: =N40-M40-Q40-AB40-AD40-AE40 -> 102.6665 | AG40: =AF40/N40 -> 0.076049259 | AH40: =N40-AB40-AI40 -> 1034.91 | AI40: =Y40*N40 -> 26.9325 | AJ40: 0.0085 | AK40: =AJ40*N40 -> 11.475
A41: 46071 | B41: 8893 - 8894 | D41: IMPERATRIZ | E41: MA | F41: TERESINA | G41: PI | H41: UNIFORT | I41: FINALIZADO | J41: SIM | K41: RAIMUNDO QUINTO | M41: 2460 | N41: 4500 | O41: 50000 | P41: 0.0003 | Q41: =O41*P41 -> 15 | R41: 0.03 | T41: 0.035 | U41: 1 | V41: =T41*N41 -> 157.5 | W41: 0.065 | X41: =N41*W41 -> 292.5 | Y41: =Z41*0.00133 -> 0.01995 | Z41: 15 | AA41: =R41+T41+W41+Y41 -> 0.14995 | AB41: =N41*AA41+AK41 -> 713.025 | AC41: 0.1 | AD41: =(N41-M41)*AC41 -> 204 | AE41: =17.5 -> 17.5 | AF41: =N41-M41-Q41-AB41-AD41-AE41 -> 1090.475 | AG41: =AF41/N41 -> 0.24232778 | AH41: =N41-AB41-AI41 -> 3697.2 | AI41: =Y41*N41 -> 89.775 | AJ41: 0.0085 | AK41: =AJ41*N41 -> 38.25
A42: 46071 | B42: 8896 - 8897 | D42: VARZEA GRANDE | E42: MT | F42: VILHENA | G42: RO | H42: UNIFORT | I42: FINALIZADO | J42: SIM | K42: FABIANO RODRIGUES | M42: 2660 | N42: 3850 | O42: 10000 | P42: 0.0003 | Q42: =O42*P42 -> 3 | R42: 0.03 | T42: 0.035 | U42: 1 | V42: =T42*N42 -> 134.75 | W42: 0.065 | X42: =N42*W42 -> 250.25 | Y42: =Z42*0.00133 -> 0.01995 | Z42: 15 | AA42: =R42+T42+W42+Y42 -> 0.14995 | AB42: =N42*AA42+AK42 -> 610.0325 | AC42: 0.07 | AD42: =(N42-M42)*AC42 -> 83.3 | AE42: =17.5 -> 17.5 | AF42: =N42-M42-Q42-AB42-AD42-AE42 -> 476.1675 | AG42: =AF42/N42 -> 0.12367987 | AH42: =N42-AB42-AI42 -> 3163.16 | AI42: =Y42*N42 -> 76.8075 | AJ42: 0.0085 | AK42: =AJ42*N42 -> 32.725
A43: 46071 | B43: 8898 | D43: ROCA SALES | E43: RS | F43: SAO LEOPOLDO | G43: RS | H43: QUISVI | I43: FINALIZADO | J43: SIM | K43: EMERSON FELIPE | M43: 1210 | N43: 2250 | O43: 80000 | P43: 0.0003 | Q43: =O43*P43 -> 24 | R43: 0 | T43: 0 | U43: 1 | V43: =T43*N43 -> 0 | W43: 0.065 | X43: =N43*W43 -> 146.25 | Y43: =Z43*0.00133 -> 0.01995 | Z43: 15 | AA43: =R43+T43+W43+Y43 -> 0.08495 | AB43: =N43*AA43+AK43 -> 210.2625 | AC43: 0.13 | AD43: =(N43-M43)*AC43 -> 135.2 | AE43: =17.5 -> 17.5 | AF43: =N43-M43-Q43-AB43-AD43-AE43 -> 653.0375 | AG43: =AF43/N43 -> 0.29023889 | AH43: =N43-AB43-AI43 -> 1994.85 | AI43: =Y43*N43 -> 44.8875 | AJ43: 0.0085 | AK43: =AJ43*N43 -> 19.125
A44: 46072 | B44: 8954 | D44: SAO LEOPOLDO | E44: RS | F44: ROCA SALES | G44: RS | H44: QUISVI | I44: FINALIZADO | J44: SIM | K44: EMERSON FELIPE | M44: =1199.86+60 -> 1259.86 | N44: 2100 | O44: 50000 | P44: 0.0003 | Q44: =O44*P44 -> 15 | R44: 0 | T44: 0 | U44: 1 | V44: =T44*N44 -> 0 | W44: 0.065 | X44: =N44*W44 -> 136.5 | Y44: =Z44*0.00133 -> 0.01995 | Z44: 15 | AA44: =R44+T44+W44+Y44 -> 0.08495 | AB44: =N44*AA44+AK44 -> 196.245 | AC44: 0.13 | AD44: =(N44-M44)*AC44 -> 109.2182 | AE44: =17.5 -> 17.5 | AF44: =N44-M44-Q44-AB44-AD44-AE44 -> 502.1768 | AG44: =AF44/N44 -> 0.23913181 | AH44: =N44-AB44-AI44 -> 1861.86 | AI44: =Y44*N44 -> 41.895 | AJ44: 0.0085 | AK44: =AJ44*N44 -> 17.85
A45: 46072 | B45: 8965 | D45: GUARULHOS | E45: SP | F45: DIADEMA | G45: SP | H45: CYA RUBBER | I45: FINALIZADO | J45: SIM | K45: EDI LAZARO | M45: =697.46+60 -> 757.46 | N45: 1450 | O45: 100000 | P45: 0.0003 | Q45: =O45*P45 -> 30 | R45: 0.12 | T45: 0 | U45: 1 | V45: =T45*N45 -> 0 | W45: 0.065 | X45: =N45*W45 -> 94.25 | Y45: =Z45*0.00133 -> 0.01995 | Z45: 15 | AA45: =R45+T45+W45+Y45 -> 0.20495 | AB45: =N45*AA45+AK45 -> 309.5025 | AC45: 0.13 | AD45: =(N45-M45)*AC45 -> 90.0302 | AE45: =17.5 -> 17.5 | AF45: =N45-M45-Q45-AB45-AD45-AE45 -> 245.5073 | AG45: =AF45/N45 -> 0.16931538 | AH45: =N45-AB45-AI45 -> 1111.57 | AI45: =Y45*N45 -> 28.9275 | AJ45: 0.0085 | AK45: =AJ45*N45 -> 12.325
A46: 46072 | B46: 8970 - 8971 - 8972 - 8973 | D46: GOIANIA | E46: GO | F46: VARZEA GRANDE | G46: MT | H46: UNIFORT | I46: FINALIZADO | J46: SIM | K46: EZEQUIEL A | M46: 4560 | N46: 8500 | O46: 80000 | P46: 0.0003 | Q46: =O46*P46 -> 24 | R46: 0.03 | T46: 0.035 | U46: 1 | V46: =T46*N46 -> 297.5 | W46: 0.065 | X46: =N46*W46 -> 552.5 | Y46: =Z46*0.00133 -> 0.01995 | Z46: 15 | AA46: =R46+T46+W46+Y46 -> 0.14995 | AB46: =N46*AA46+AK46 -> 1346.825 | AC46: 0.1 | AD46: =(N46-M46)*AC46 -> 394 | AE46: =17.5 -> 17.5 | AF46: =N46-M46-Q46-AB46-AD46-AE46 -> 2157.675 | AG46: =AF46/N46 -> 0.25384412 | AH46: =N46-AB46-AI46 -> 6983.6 | AI46: =Y46*N46 -> 169.575 | AJ46: 0.0085 | AK46: =AJ46*N46 -> 72.25
A47: 46072 | B47: 8975 - 8976 - 8977 - 8978 - 8979 - 8980 | D47: GOIANIA | E47: GO | F47: MARABA | G47: PA | H47: UNIFORT | I47: FINALIZADO | J47: SIM | K47: EUCLIDES | M47: 4560 | N47: 9500 | O47: 100000 | P47: 0.0003 | Q47: =O47*P47 -> 30 | R47: 0.03 | T47: 0.035 | U47: 1 | V47: =T47*N47 -> 332.5 | W47: 0.065 | X47: =N47*W47 -> 617.5 | Y47: =Z47*0.00133 -> 0.01995 | Z47: 15 | AA47: =R47+T47+W47+Y47 -> 0.14995 | AB47: =N47*AA47+AK47 -> 1505.275 | AC47: 0.1 | AD47: =(N47-M47)*AC47 -> 494 | AE47: =17.5 -> 17.5 | AF47: =N47-M47-Q47-AB47-AD47-AE47 -> 2893.225 | AG47: =AF47/N47 -> 0.30455 | AH47: =N47-AB47-AI47 -> 7805.2 | AI47: =Y47*N47 -> 189.525 | AJ47: 0.0085 | AK47: =AJ47*N47 -> 80.75
A48: 46073 | B48: 9000 | D48: ROCA SALES | E48: RS | F48: SÃO LEOPOLDO | G48: RS | H48: QUISVI | I48: FINALIZADO | J48: SIM | K48: GREGORI NICHEL | M48: =1235+60 -> 1295 | N48: 2250 | O48: 80000 | P48: 0.0003 | Q48: =O48*P48 -> 24 | R48: 0 | T48: 0 | U48: 1 | V48: =T48*N48 -> 0 | W48: 0.065 | X48: =N48*W48 -> 146.25 | Y48: =Z48*0.00133 -> 0.01995 | Z48: 15 | AA48: =R48+T48+W48+Y48 -> 0.08495 | AB48: =N48*AA48+AK48 -> 210.2625 | AC48: 0.13 | AD48: =(N48-M48)*AC48 -> 124.15 | AE48: =17.5 -> 17.5 | AF48: =N48-M48-Q48-AB48-AD48-AE48 -> 579.0875 | AG48: =AF48/N48 -> 0.25737222 | AH48: =N48-AB48-AI48 -> 1994.85 | AI48: =Y48*N48 -> 44.8875 | AJ48: 0.0085 | AK48: =AJ48*N48 -> 19.125
A49: 46073 | B49: 28861 | D49: ITAJAI | E49: SC | F49: BETIM | G49: MG | H49: UNIFORT | I49: FINALIZADO | J49: SIM | K49: ADILSON DOS PASSOS | M49: 7060 | N49: 9500 | O49: 100000 | P49: 0.0003 | Q49: =O49*P49 -> 30 | R49: 0.03 | T49: 0.035 | U49: 1 | V49: =T49*N49 -> 332.5 | W49: 0.065 | X49: =N49*W49 -> 617.5 | Y49: =Z49*0.00133 -> 0.01995 | Z49: 15 | AA49: =R49+T49+W49+Y49 -> 0.14995 | AB49: =N49*AA49+AK49 -> 1505.275 | AC49: 0 | AD49: 300 | AE49: =17.5 -> 17.5 | AF49: =N49-M49-Q49-AB49-AD49-AE49 -> 587.225 | AG49: =AF49/N49 -> 0.061813158 | AH49: =N49-AB49-AI49 -> 7805.2 | AI49: =Y49*N49 -> 189.525 | AJ49: 0.0085 | AK49: =AJ49*N49 -> 80.75
A50: 46073 | B50: 9040 - 9041 | D50: ITAJAI | E50: SC | F50: BETIM | G50: MG | H50: UNIFORT | I50: FINALIZADO | J50: SIM | K50: TAILOR JEAN DIAS | M50: 9060 | N50: 14200 | O50: 500000 | P50: 0.0003 | Q50: =O50*P50 -> 150 | R50: 0.03 | T50: 0.035 | U50: 1 | V50: =T50*N50 -> 497 | W50: 0.065 | X50: =N50*W50 -> 923 | Y50: =Z50*0.00133 -> 0.01995 | Z50: 15 | AA50: =R50+T50+W50+Y50 -> 0.14995 | AB50: =N50*AA50+AK50 -> 2249.99 | AC50: 0.1 | AD50: =(N50-M50)*AC50 -> 514 | AE50: =17.5 -> 17.5 | AF50: =N50-M50-Q50-AB50-AD50-AE50 -> 2208.51 | AG50: =AF50/N50 -> 0.15552887 | AH50: =N50-AB50-AI50 -> 11666.72 | AI50: =Y50*N50 -> 283.29 | AJ50: 0.0085 | AK50: =AJ50*N50 -> 120.7
A51: 46073 | B51: 9038 | D51: DIADEMA | E51: SP | F51: PORTO FERREIRA | G51: SP | H51: TERMOCOLOR | I51: FINALIZADO | J51: SIM | K51: KAINAN FERNANDO | M51: 2190 | N51: 3490 | O51: 50000 | P51: 0.0003 | Q51: =O51*P51 -> 15 | R51: 0.12 | T51: 0 | U51: 1 | V51: =T51*N51 -> 0 | W51: 0.065 | X51: =N51*W51 -> 226.85 | Y51: =Z51*0.00133 -> 0.01995 | Z51: 15 | AA51: =R51+T51+W51+Y51 -> 0.20495 | AB51: =N51*AA51+AK51 -> 744.9405 | AC51: 0.07 | AD51: =(N51-M51)*AC51 -> 91 | AE51: =17.5 -> 17.5 | AF51: =N51-M51-Q51-AB51-AD51-AE51 -> 431.5595 | AG51: =AF51/N51 -> 0.12365602 | AH51: =N51-AB51-AI51 -> 2675.434 | AI51: =Y51*N51 -> 69.6255 | AJ51: 0.0085 | AK51: =AJ51*N51 -> 29.665
A52: 46076 | B52: 9055 | D52: GUARULHOS | E52: SP | F52: SÃO PAULO | G52: SP | H52: CYA RUBBER | I52: FINALIZADO | J52: SIM | K52: EDI LAZARO | M52: 860 | N52: 1380 | O52: 50000 | P52: 0.0003 | Q52: =O52*P52 -> 15 | R52: 0.12 | T52: 0 | U52: 1 | V52: =T52*N52 -> 0 | W52: 0.065 | X52: =N52*W52 -> 89.7 | Y52: =Z52*0.00133 -> 0.01995 | Z52: 15 | AA52: =R52+T52+W52+Y52 -> 0.20495 | AB52: =N52*AA52+AK52 -> 294.561 | AC52: 0.06 | AD52: =(N52-M52)*AC52 -> 31.2 | AE52: =17.5 -> 17.5 | AF52: =N52-M52-Q52-AB52-AD52-AE52 -> 161.739 | AG52: =AF52/N52 -> 0.11720217 | AH52: =N52-AB52-AI52 -> 1057.908 | AI52: =Y52*N52 -> 27.531 | AJ52: 0.0085 | AK52: =AJ52*N52 -> 11.73
A53: 46076 | B53: 9078 9079 | D53: GUARULHOS | E53: SP | F53: SANTANA DE PARNAIBA | G53: SP | H53: CYA RUBBER | I53: FINALIZADO | J53: SIM | K53: AGNALDO CICERO | M53: 710 | N53: 1200 | O53: 50000 | P53: 0.0003 | Q53: =O53*P53 -> 15 | R53: 0.12 | T53: 0 | U53: 1 | V53: =T53*N53 -> 0 | W53: 0.065 | X53: =N53*W53 -> 78 | Y53: =Z53*0.00133 -> 0.01995 | Z53: 15 | AA53: =R53+T53+W53+Y53 -> 0.20495 | AB53: =N53*AA53+AK53 -> 256.14 | AC53: 0.07 | AD53: =(N53-M53)*AC53 -> 34.3 | AE53: =17.5 -> 17.5 | AF53: =N53-M53-Q53-AB53-AD53-AE53 -> 167.06 | AG53: =AF53/N53 -> 0.13921667 | AH53: =N53-AB53-AI53 -> 919.92 | AI53: =Y53*N53 -> 23.94 | AJ53: 0.0085 | AK53: =AJ53*N53 -> 10.2
A54: 46076 | B54: 9077 | D54: CAMPO GRANDE | E54: PE | F54: DIADEMA | G54: SP | H54: TERMOCOLOR | I54: FINALIZADO | J54: SIM | K54: JOAO BATISTA | M54: 860 | N54: 1000 | O54: 10000 | P54: 0.0003 | Q54: =O54*P54 -> 3 | R54: 0.12 | T54: 0 | U54: 1 | V54: =T54*N54 -> 0 | W54: 0.065 | X54: =N54*W54 -> 65 | Y54: =Z54*0.00133 -> 0.01995 | Z54: 15 | AA54: =R54+T54+W54+Y54 -> 0.20495 | AB54: =N54*AA54+AK54 -> 213.45 | AC54: 0 | AD54: 0 | AE54: =17.5 -> 17.5 | AF54: =N54-M54-Q54-AB54-AD54-AE54 -> -93.95 | AG54: =AF54/N54 -> -0.09395 | AH54: =N54-AB54-AI54 -> 766.6 | AI54: =Y54*N54 -> 19.95 | AJ54: 0.0085 | AK54: =AJ54*N54 -> 8.5
A55: 46077 | B55: 9118 | D55: TRIUNFO | E55: RS | F55: SÃO LEOPOLDO | G55: RS | H55: CYA RUBBER | I55: FINALIZADO | J55: SIM | K55: JAIRO BATISTA | M55: 1060 | N55: 1100 | O55: 20000 | P55: 0.0003 | Q55: =O55*P55 -> 6 | R55: 0 | T55: 0.035 | U55: 1 | V55: =T55*N55 -> 38.5 | W55: 0.065 | X55: =N55*W55 -> 71.5 | Y55: =Z55*0.00133 -> 0.01995 | Z55: 15 | AA55: =R55+T55+W55+Y55 -> 0.11995 | AB55: =N55*AA55+AK55 -> 141.295 | AC55: 0 | AD55: =(N55-M55)*AC55 -> 0 | AE55: =17.5 -> 17.5 | AF55: =N55-M55-Q55-AB55-AD55-AE55 -> -124.795 | AG55: =AF55/N55 -> -0.11345 | AH55: =N55-AB55-AI55 -> 936.76 | AI55: =Y55*N55 -> 21.945 | AJ55: 0.0085 | AK55: =AJ55*N55 -> 9.35
A56: 46077 | B56: 9150 | D56: SÃO LEOPOLDO | E56: RS | F56: GUARULHOS | G56: SP | H56: CYA RUBBER | I56: FINALIZADO | J56: SIM | K56: ROGER WILLIAM | M56: 5260 | N56: 2900 | O56: 100000 | P56: 0.0003 | Q56: =O56*P56 -> 30 | R56: 0.12 | S56: =R56*N56 -> 348 | T56: 0 | U56: 1 | V56: =T56*N56 -> 0 | W56: 0.065 | X56: =N56*W56 -> 188.5 | Y56: =Z56*0.00133 -> 0.01995 | Z56: 15 | AA56: =R56+T56+W56+Y56 -> 0.20495 | AB56: =N56*AA56+AK56 -> 619.005 | AC56: 0 | AD56: =(N56-M56)*AC56 -> 0 | AE56: =17.5 -> 17.5 | AF56: =N56-M56-Q56-AB56-AD56-AE56 -> -3026.505 | AG56: =AF56/N56 -> -1.0436224 | AH56: =N56-AB56-AI56 -> 2223.14 | AI56: =Y56*N56 -> 57.855 | AJ56: 0.0085 | AK56: =AJ56*N56 -> 24.65
A57: 46077 | B57: 9110 | D57: ROCA SALES | E57: RS | F57: SÃO LEOPOLDO | G57: RS | H57: QUISVI | I57: FINALIZADO | J57: SIM | K57: SILVIONEY BECKER | M57: 969.85 | N57: 2100 | O57: 50000 | P57: 0.0003 | Q57: =O57*P57 -> 15 | R57: 0 | S57: =R57*N57 -> 0 | T57: 0.035 | U57: 1 | V57: =T57*N57 -> 73.5 | W57: 0.065 | X57: =N57*W57 -> 136.5 | Y57: =Z57*0.00133 -> 0.01995 | Z57: 15 | AA57: =R57+T57+W57+Y57 -> 0.11995 | AB57: =N57*AA57+AK58 -> 269.745 | AC57: 0.13 | AD57: =(N57-M57)*AC57 -> 146.9195 | AE57: =17.5 -> 17.5 | AF57: =N57-M57-Q57-AB57-AD57-AE57 -> 680.9855 | AG57: =AF57/N57 -> 0.32427881 | AH57: =#REF!-#REF!-AI57 -> #REF! | AI57: =#REF!*#REF! -> #REF! | AJ57: 0.0085 | AK57: =AJ57*#REF! -> #REF!
A58: 46077 | B58: 9133 | D58: GUARULHOS | E58: SP | F58: SALTO | G58: SP | H58: CYA RUBBER | I58: FINALIZADO | J58: SIM | K58: PEDRO RAFAEL | M58: 1260 | N58: 2100 | O58: 50000 | P58: 0.0003 | Q58: =O58*P58 -> 15 | R58: 0.12 | S58: =R58*N58 -> 252 | T58: 0 | U58: 1 | V58: =T58*N58 -> 0 | W58: 0.065 | X58: =N58*W58 -> 136.5 | Y58: =Z58*0.00133 -> 0.01995 | Z58: 15 | AA58: =R58+T58+W58+Y58 -> 0.20495 | AB58: =N58*AA58+AK59 -> 448.245 | AC58: 0.07 | AD58: =(N58-M58)*AC58 -> 58.8 | AE58: =17.5 -> 17.5 | AF58: =N58-M58-Q58-AB58-AD58-AE58 -> 300.455 | AG58: =AF58/N58 -> 0.14307381 | AH58: =N57-AB57-AI58 -> 1788.36 | AI58: =Y57*N57 -> 41.895 | AJ58: 0.0085 | AK58: =AJ58*N57 -> 17.85
A59: 46077 | B59: 9131 | D59: SÃO LEOPOLDO | E59: RS | F59: CAXIAS DO SUL | G59: RS | H59: CYA RUBBER | I59: FINALIZADO | J59: SIM | K59: RODRIGO CERVELIN | M59: 1150 | N59: 1750 | O59: 50000 | P59: 0.0003 | Q59: =O59*P59 -> 15 | R59: 0 | S59: =R59*N59 -> 0 | T59: 0 | U59: 1 | V59: =T59*N59 -> 0 | W59: 0.065 | X59: =N59*W59 -> 113.75 | Y59: =Z59*0.00133 -> 0.01995 | Z59: 15 | AA59: =R59+T59+W59+Y59 -> 0.08495 | AB59: =N59*AA59+AK59 -> 166.5125 | AC59: 0.13 | AD59: =(N59-M59)*AC59 -> 78 | AE59: =17.5 -> 17.5 | AF59: =N59-M59-Q59-AB59-AD59-AE59 -> 322.9875 | AG59: =AF59/N59 -> 0.18456429 | AH59: =N58-AB58-AI59 -> 1609.86 | AI59: =Y58*N58 -> 41.895 | AJ59: 0.0085 | AK59: =AJ59*N58 -> 17.85
A60: 46077 | B60: 9145 - 9147 - 9148 - 9149 | D60: GOIANIA | E60: GO | F60: VARZEA GRANDE | G60: MT | H60: UNIFORT | I60: FINALIZADO | J60: SIM | K60: FREDSON RENATO | M60: 4560 | N60: 7900 | O60: 80000 | P60: 0.0003 | Q60: =O60*P60 -> 24 | R60: 0.03 | T60: 0.035 | U60: 1 | V60: =T60*N60 -> 276.5 | W60: 0.065 | X60: =N60*W60 -> 513.5 | Y60: =Z60*0.00133 -> 0.01995 | Z60: 15 | AA60: =R60+T60+W60+Y60 -> 0.14995 | AB60: =N60*AA60+AK60 -> 1251.755 | AC60: 0.1 | AD60: =(N60-M60)*AC60 -> 334 | AE60: =17.5 -> 17.5 | AF60: =N60-M60-Q60-AB60-AD60-AE60 -> 1712.745 | AG60: =AF60/N60 -> 0.21680316 | AH60: =N60-AB60-AI60 -> 6490.64 | AI60: =Y60*N60 -> 157.605 | AJ60: 0.0085 | AK60: =AJ60*N60 -> 67.15
A61: 46078 | B61: 9188 - 9185 - 9186 - 9184 - 9187 | D61: GOIANIA | E61: GO | F61: MARABA | G61: PA | H61: UNIFORT | I61: FINALIZADO | J61: SIM | K61: LUZIMAR FERREIRA | M61: 6960 | N61: 11900 | O61: 100000 | P61: 0.0003 | Q61: =O61*P61 -> 30 | R61: 0.03 | T61: 0.035 | U61: 1 | V61: =T61*N61 -> 416.5 | W61: 0.065 | X61: =N61*W61 -> 773.5 | Y61: =Z61*0.00133 -> 0.01995 | Z61: 15 | AA61: =R61+T61+W61+Y61 -> 0.14995 | AB61: =N61*AA61+AK61 -> 1885.555 | AC61: 0.1 | AD61: =(N61-M61)*AC61 -> 494 | AE61: =17.5 -> 17.5 | AF61: =N61-M61-Q61-AB61-AD61-AE61 -> 2512.945 | AG61: =AF61/N61 -> 0.21117185 | AH61: =N61-AB61-AI61 -> 9777.04 | AI61: =Y61*N61 -> 237.405 | AJ61: 0.0085 | AK61: =AJ61*N61 -> 101.15
A62: 46078 | B62: 9168 | D62: ARAÇATUBA | E62: SP | F62: DIADEMA | G62: SP | H62: TERMOCOLOR | I62: FINALIZADO | J62: SIM | K62: BRUNO LUZ LOPES | M62: =3358.14+60 -> 3418.14 | N62: 6200 | O62: 150000 | P62: 0.0003 | Q62: =O62*P62 -> 45 | R62: 0.12 | S62: =R62*N62 -> 744 | T62: 0 | U62: 1 | V62: =T62*N62 -> 0 | W62: 0.065 | X62: =N62*W62 -> 403 | Y62: =Z62*0.00133 -> 0.01995 | Z62: 15 | AA62: =R62+T62+W62+Y62 -> 0.20495 | AB62: =N62*AA62+AK62 -> 1323.39 | AC62: 0.13 | AD62: =(N62-M62)*AC62 -> 361.6418 | AE62: =17.5 -> 17.5 | AF62: =N62-M62-Q62-AB62-AD62-AE62 -> 1034.3282 | AG62: =AF62/N62 -> 0.16682713 | AH62: =N62-AB62-AI62 -> 4752.92 | AI62: =Y62*N62 -> 123.69 | AJ62: 0.0085 | AK62: =AJ62*N62 -> 52.7
A63: 46079 | B63: 9237 | D63: GUARULHOS | E63: SP | F63: GUARAREMA | G63: SP | H63: CYA RUBBER | I63: FINALIZADO | J63: SIM | K63: EGINELSON DE SOUZA | M63: 910 | N63: 1750 | O63: 80000 | P63: 0.0003 | Q63: =O63*P63 -> 24 | R63: 0.12 | S63: =R63*N63 -> 210 | T63: 0 | U63: 1 | V63: =T63*N63 -> 0 | W63: 0.065 | X63: =N63*W63 -> 113.75 | Y63: =Z63*0.00133 -> 0.01995 | Z63: 15 | AA63: =R63+T63+W63+Y63 -> 0.20495 | AB63: =N63*AA63+AK63 -> 373.5375 | AC63: 0.13 | AD63: =(N63-M63)*AC63 -> 109.2 | AE63: =17.5 -> 17.5 | AF63: =N63-M63-Q63-AB63-AD63-AE63 -> 315.7625 | AG63: =AF63/N63 -> 0.18043571 | AH63: =N63-AB63-AI63 -> 1341.55 | AI63: =Y63*N63 -> 34.9125 | AJ63: 0.0085 | AK63: =AJ63*N63 -> 14.875
A64: 46079 | B64: 9293 | D64: GUARULHOS | E64: SP | F64: SAO BERNARDO DO CAMPO | G64: SP | H64: CYA RUBBER | I64: FINALIZADO | J64: SIM | K64: ROGERIO PICCHI | M64: 560 | N64: 1050 | O64: 50000 | P64: 0.0003 | Q64: =O64*P64 -> 15 | R64: 0.12 | S64: =R64*N64 -> 126 | T64: 0 | U64: 1 | V64: =T64*N64 -> 0 | W64: 0.065 | X64: =N64*W64 -> 68.25 | Y64: =Z64*0.00133 -> 0.01995 | Z64: 15 | AA64: =R64+T64+W64+Y64 -> 0.20495 | AB64: =N64*AA64+AK64 -> 224.1225 | AC64: 0.13 | AD64: =(N64-M64)*AC64 -> 63.7 | AE64: =17.5 -> 17.5 | AF64: =N64-M64-Q64-AB64-AD64-AE64 -> 169.6775 | AG64: =AF64/N64 -> 0.16159762 | AH64: =N64-AB64-AI64 -> 804.93 | AI64: =Y64*N64 -> 20.9475 | AJ64: 0.0085 | AK64: =AJ64*N64 -> 8.925
A65: 46080 | B65: 9364 9365 9366 9368 9369 9374 | D65: BETIM | E65: MG | F65: GOIANIA | G65: GO | H65: UNIFORT | I65: ANDAMENTO | J65: SIM | K65: THIAGO DUARTE | M65: 8260 | N65: 13000 | O65: 500000 | P65: 0.0003 | Q65: =O65*P65 -> 150 | R65: 0.03 | S65: =R65*N65 -> 390 | T65: 0.035 | U65: 1 | V65: =T65*N65 -> 455 | W65: 0.065 | X65: =N65*W65 -> 845 | Y65: =Z65*0.00133 -> 0.01995 | Z65: 15 | AA65: =R65+T65+W65+Y65 -> 0.14995 | AB65: =N65*AA65+AK65 -> 2059.85 | AC65: 0.1 | AD65: =(N65-M65)*AC65 -> 474 | AE65: =17.5 -> 17.5 | AF65: =N65-M65-Q65-AB65-AD65-AE65 -> 2038.65 | AG65: =AF65/N65 -> 0.15681923 | AH65: =N65-AB65-AI65 -> 10680.8 | AI65: =Y65*N65 -> 259.35 | AJ65: 0.0085 | AK65: =AJ65*N65 -> 110.5
A66: 46080 | B66: 9339 | D66: PATO BRAGADO | E66: PR | F66: PATO DE MIANS | G66: MG | H66: SCHEMAQ | I66: ANDAMENTO | J66: SIM | K66: DIEGO MARTINS | M66: 2360 | N66: 2000 | O66: 50000 | P66: 0.0003 | Q66: =O66*P66 -> 15 | R66: 0.12 | S66: =R66*N66 -> 240 | T66: 0 | U66: 1 | V66: =T66*N66 -> 0 | W66: 0.065 | X66: =N66*W66 -> 130 | Y66: =Z66*0.00133 -> 0.01995 | Z66: 15 | AA66: =R66+T66+W66+Y66 -> 0.20495 | AB66: =N66*AA66+AK66 -> 426.9 | AC66: 0 | AD66: =(N66-M66)*AC66 -> 0 | AE66: =17.5 -> 17.5 | AF66: =N66-M66-Q66-AB66-AD66-AE66 -> -819.4 | AG66: =AF66/N66 -> -0.4097 | AH66: =N66-AB66-AI66 -> 1533.2 | AI66: =Y66*N66 -> 39.9 | AJ66: 0.0085 | AK66: =AJ66*N66 -> 17
A67: 46081 | D67: BETIM | E67: MG | F67: VITORIA DA CONQUISTA | G67: BA | H67: UNIFORT | I67: CONTRATADO | J67: SIM | K67: LUCAS PEREIRA | M67: 4560 | N67: 7900 | O67: 400000 | P67: 0.0003 | Q67: =O67*P67 -> 120 | R67: 0.03 | S67: =R67*N67 -> 237 | T67: 0.035 | U67: 1 | V67: =T67*N67 -> 276.5 | W67: 0.065 | X67: =N67*W67 -> 513.5 | Y67: =Z67*0.00133 -> 0.01995 | Z67: 15 | AA67: =R67+T67+W67+Y67 -> 0.14995 | AB67: =N67*AA67+AK67 -> 1251.755 | AC67: 0.1 | AD67: =(N67-M67)*AC67 -> 334 | AE67: =17.5 -> 17.5 | AF67: =N67-M67-Q67-AB67-AD67-AE67 -> 1616.745 | AG67: =AF67/N67 -> 0.20465127 | AH67: =N67-AB67-AI67 -> 6490.64 | AI67: =Y67*N67 -> 157.605 | AJ67: 0.0085 | AK67: =AJ67*N67 -> 67.15
A68: 46081 | D68: JOINVILLE | E68: SC | F68: MUNHUMIRIM | G68: MG | H68: SATAKE | I68: CONTRATADO | J68: SIM | K68: ALEX VENTURA | M68: 1060 | N68: 1900 | O68: 50000 | P68: 0.0003 | Q68: =O68*P68 -> 15 | R68: 0.12 | S68: =R68*N68 -> 228 | T68: 0 | U68: 1 | V68: =T68*N68 -> 0 | W68: 0.065 | X68: =N68*W68 -> 123.5 | Y68: =Z68*0.00133 -> 0.00931 | Z68: 7 | AA68: =R68+T68+W68+Y68 -> 0.19431 | AB68: =N68*AA68+AK68 -> 385.339 | AC68: 0.13 | AD68: =(N68-M68)*AC68 -> 109.2 | AE68: =17.5 -> 17.5 | AF68: =N68-M68-Q68-AB68-AD68-AE68 -> 312.961 | AG68: =AF68/N68 -> 0.16471632 | AH68: =N68-AB68-AI68 -> 1496.972 | AI68: =Y68*N68 -> 17.689 | AJ68: 0.0085 | AK68: =AJ68*N68 -> 16.15
P69: 0.0003 | Q69: =O69*P69 -> 0 | S69: =R69*N69 -> 0 | V69: =T69*N69 -> 0 | W69: 0.065 | X69: =N69*W69 -> 0 | Y69: =Z69*0.00133 -> 0 | Z69: 0 | AA69: =R69+T69+W69+Y69 -> 0.065 | AB69: =N69*AA69+AK69 -> 0 | AC69: 0 | AD69: =(N69-M69)*AC69 -> 0 | AE69: =17.5 -> 17.5 | AF69: =N69-M69-Q69-AB69-AD69-AE69 -> -17.5 | AG69: =AF69/N69 -> #DIV/0! | AH69: =N69-AB69-AI69 -> 0 | AI69: =Y69*N69 -> 0 | AJ69: 0.0085 | AK69: =AJ69*N69 -> 0
P70: 0.0003 | Q70: =O70*P70 -> 0 | S70: =R70*N70 -> 0 | V70: =T70*N70 -> 0 | W70: 0.065 | X70: =N70*W70 -> 0 | Y70: =Z70*0.00133 -> 0 | Z70: 0 | AA70: =R70+T70+W70+Y70 -> 0.065 | AB70: =N70*AA70+AK70 -> 0 | AC70: 0 | AD70: =(N70-M70)*AC70 -> 0 | AE70: =17.5 -> 17.5 | AF70: =N70-M70-Q70-AB70-AD70-AE70 -> -17.5 | AG70: =AF70/N70 -> #DIV/0! | AH70: =N70-AB70-AI70 -> 0 | AI70: =Y70*N70 -> 0 | AJ70: 0.0085 | AK70: =AJ70*N70 -> 0
P71: 0.0003 | Q71: =O71*P71 -> 0 | S71: =R71*N71 -> 0 | V71: =T71*N71 -> 0 | W71: 0.065 | X71: =N71*W71 -> 0 | Y71: =Z71*0.00133 -> 0 | Z71: 0 | AA71: =R71+T71+W71+Y71 -> 0.065 | AB71: =N71*AA71+AK71 -> 0 | AC71: 0 | AD71: =(N71-M71)*AC71 -> 0 | AE71: =17.5 -> 17.5 | AF71: =N71-M71-Q71-AB71-AD71-AE71 -> -17.5 | AG71: =AF71/N71 -> #DIV/0! | AH71: =N71-AB71-AI71 -> 0 | AI71: =Y71*N71 -> 0 | AJ71: 0.0085 | AK71: =AJ71*N71 -> 0
P72: 0.0003 | Q72: =O72*P72 -> 0 | S72: =R72*N72 -> 0 | V72: =T72*N72 -> 0 | W72: 0.065 | X72: =N72*W72 -> 0 | Y72: =Z72*0.00133 -> 0 | Z72: 0 | AA72: =R72+T72+W72+Y72 -> 0.065 | AB72: =N72*AA72+AK72 -> 0 | AC72: 0 | AD72: =(N72-M72)*AC72 -> 0 | AE72: =17.5 -> 17.5 | AF72: =N72-M72-Q72-AB72-AD72-AE72 -> -17.5 | AG72: =AF72/N72 -> #DIV/0! | AH72: =N72-AB72-AI72 -> 0 | AI72: =Y72*N72 -> 0 | AJ72: 0.0085 | AK72: =AJ72*N72 -> 0
P73: 0.0003 | Q73: =O73*P73 -> 0 | S73: =R73*N73 -> 0 | V73: =T73*N73 -> 0 | W73: 0.065 | X73: =N73*W73 -> 0 | Y73: =Z73*0.00133 -> 0 | Z73: 0 | AA73: =R73+T73+W73+Y73 -> 0.065 | AB73: =N73*AA73+AK73 -> 0 | AC73: 0 | AD73: =(N73-M73)*AC73 -> 0 | AE73: =17.5 -> 17.5 | AF73: =N73-M73-Q73-AB73-AD73-AE73 -> -17.5 | AG73: =AF73/N73 -> #DIV/0! | AH73: =N73-AB73-AI73 -> 0 | AI73: =Y73*N73 -> 0 | AJ73: 0.0085 | AK73: =AJ73*N73 -> 0
P74: 0.0003 | Q74: =O74*P74 -> 0 | S74: =R74*N74 -> 0 | V74: =T74*N74 -> 0 | W74: 0.065 | X74: =N74*W74 -> 0 | Y74: =Z74*0.00133 -> 0 | Z74: 0 | AA74: =R74+T74+W74+Y74 -> 0.065 | AB74: =N74*AA74+AK74 -> 0 | AC74: 0 | AD74: =(N74-M74)*AC74 -> 0 | AE74: =17.5 -> 17.5 | AF74: =N74-M74-Q74-AB74-AD74-AE74 -> -17.5 | AG74: =AF74/N74 -> #DIV/0! | AH74: =N74-AB74-AI74 -> 0 | AI74: =Y74*N74 -> 0 | AJ74: 0.0085 | AK74: =AJ74*N74 -> 0
AF75: =SUM(AF3:AF74) -> 50619.129
D79: META | E79: REALIZADO | F79: COMISSÃO | G79: % REALIZADA | H79: CLIENTES | J79: DIA | K79: ATIVIDADES | M79: SEMANA 1 | N79: SEMANA 2 | O79: SEMANA 3 | P79: SEMANA 2 | Q79: SEMANA 3 | R79: SEMANA 4
D80: 250000 | E80: =SUMIF(H4:H74,H80,N4:N74) -> 200250 | F80: =SUMIF(H:H,H80,AD:AD) -> 8273.717 | G80: =E80/D80 -> 0.801 | H80: UNIFORT | J80: SEGUNDA | K80: LIGAÇÃO | M80: 3 | N80: 13 | O80: 0 | R80: 11
D81: 10000 | E81: =SUMIF(H4:H74,H81,N4:N74) -> 14700 | F81: =SUMIF(H:H,H81,AD:AD) -> 801.6877 | G81: =E81/D81 -> 1.47 | H81: QUISVI | K81: CARREGAMENTO | M81: 6 | N81: 3 | O81: 0 | R81: 3
D82: 70000 | E82: =SUMIF(H4:H74,H82,N4:N74) -> 49280 | F82: =SUMIF(H:H,H82,AD:AD) -> 2140.5722 | G82: =E82/D82 -> 0.704 | H82: CYA RUBBER | K82: PROSPECÇÃO | M82: 0 | N82: 0 | O82: 0 | R82: 0
D83: 10000 | E83: =SUMIF(H4:H74,H83,N4:N74) -> 14180 | F83: =SUMIF(H:H,H83,AD:AD) -> 652.6418 | G83: =E83/D83 -> 1.418 | H83: TERMOCOLOR | J83: TERÇA | K83: LIGAÇÃO | M83: 4 | N83: 11 | O83: 0
D84: 10000 | E84: =SUMIF(H4:H74,H84,N4:N74) -> 2000 | F84: =SUMIF(H:H,H84,AD:AD) -> 0 | G84: =E84/D84 -> 0.2 | H84: SCHEMAQ | K84: CARREGAMENTO | M84: 2 | N84: 2 | O84: 0
D85: 10000 | E85: =SUMIF(H5:H75,H85,N5:N75) -> 1900 | F85: =SUMIF(H:H,H85,AD:AD) -> 109.2 | G85: =E85/D85 -> 0.19 | H85: SATAKE | K85: PROSPECÇÃO | M85: 0 | N85: 0 | O85: 25
D86: =SUM(D80:D84) -> 350000 | E86: =SUM(E80:E84) -> 280410 | F86: =SUM(F76:F84) -> 11868.619 | G86: =AVERAGE(G80,G84) -> 0.5005 | H86: TOTAL | J86: QUARTA | K86: LIGAÇÃO | M86: 1 | N86: 5 | O86: 3
K87: CARREGAMENTO | M87: 5 | N87: 4 | O87: 5
K88: PROSPECÇÃO | M88: 0 | N88: 5 | O88: 0
J89: QUINTA | K89: LIGAÇÃO | M89: 9 | N89: 7 | O89: 12
K90: CARREGAMENTO | M90: 3 | N90: 5 | O90: 4
F91: DIAS ÚTEIS | G91: 1 | K91: PROSPECÇÃO | M91: 0 | N91: 0 | O91: 0
D92: PARÂMETRO 100K | F92: META DIÁRIA | G92: =(G93-G95)/G91 -> 119590 | J92: SEXTA | K92: LIGAÇÃO | M92: 1 | N92: 1 | O92: 6
D93: =E136*F135/E135 -> 4232.5947 | F93: META | G93: 400000 | K93: CARREGAMENTO | M93: 3 | N93: 2 | O93: 3
F94: 100% META | G94: =G95/G93 -> 0.701025 | K94: PROSPECÇÃO | M94: 0 | N94: 0 | O94: 0
F95: VALOR TOTAL: | G95: =E86 -> 280410
F97: FRETE MOTORISTA | G97: FATURAMENTO
F98: =SUM(M4:M193) -> 170192.44 | G98: =SUM(N4:N74) -> 282310
F99: PORCENTAGEM MÉDIA | G99: LUCRO EMPRESA
F100: =AF75/G98 -> 0.17930335 | G100: =G98*F100 -> 50619.129
G132: =F4:F1053
I134: =TODAY() -> 46203 | K134: 0 | M134: =SUMIF(T4:T68,K134,U4:U69) -> 35
E135: =E86 -> 280410 | F135: =F86 -> 11868.619 | I135: 46081 | K135: 0.035 | M135: =SUMIF(T4:T69,K135,U4:U69) -> 30
E136: 100000

Sheet MARÇO - 2026
A1: GODI TRANSPORTES - UNINDO PROPÓSITOS
A3: DATA | B3: CTE | C3: MANIFESTO | D3: ORIGEM | E3: ESTADO | F3: DESTINO | G3: ESTADO | H3: CLIENTE | I3: PAGAMENTO | J3: CONFERENCIA | K3: MOTORISTA | L3: TELEFONE | M3: VALOR MOTORISTA | N3: VALOR EMPRESA | O3: NF | P3: SEGURO | Q3: SEGURO | R3: ICMS | S3: ICMS | T3: C.O | V3: CO | W3: IMPOSTO | X3: IMPOSTO | Y3: BOLETO | Z3: DIA PAG | AA3: TOTAL TAXAS | AB3: VALOR IMPOSTO | AC3: % | AD3: COMISSÕES | AE3: BOLETOS | AF3: LUCRO | AG3: RENTABIL | AH3: FRETE LIQ | AI3: MOVA | AJ3: ADQ TAB | AK3: VALOR
A4: 45717 | B4: 9390 - 9391 | D4: GOIANIA | E4: GO | F4: MARABA | G4: PA | H4: UNIFORT | I4: FINALIZADO | J4: SIM | K4: JOSE ARAUJO | M4: 7560 | N4: 12900 | O4: 100000 | P4: 0.0003 | Q4: =O4*P4 -> 30 | R4: 0.03 | S4: =R4*N4 -> 387 | T4: 0.035 | U4: 1 | V4: =T4*N4 -> 451.5 | W4: 0.065 | X4: =N4*W4 -> 838.5 | Y4: =Z4*0.00133 -> 0.01995 | Z4: 15 | AA4: =R4+T4+W4+Y4 -> 0.14995 | AB4: =N4*AA4+AK4 -> 2044.005 | AC4: 0.1 | AD4: =(N4-M4)*AC4 -> 534 | AE4: =17.5 -> 17.5 | AF4: =N4-M4-Q4-AB4-AD4-AE4 -> 2714.495 | AG4: =AF4/N4 -> 0.21042597 | AH4: =N4-AB4-AI4 -> 10598.64 | AI4: =Y4*N4 -> 257.355 | AJ4: 0.0085 | AK4: =AJ4*N4 -> 109.65
A5: 45717 | B5: 9395 - 9402 - 9399 - 9398 | D5: GOIANIA | E5: GO | F5: VARZEA GRANDE | G5: MT | H5: UNIFORT | I5: FINALIZADO | J5: SIM | K5: RODRIGO CESAR | M5: 5260 | N5: 8600 | O5: 100000 | P5: 0.0003 | Q5: =O5*P5 -> 30 | R5: 0.03 | S5: =R5*N5 -> 258 | T5: 0.035 | U5: 1 | V5: =T5*N5 -> 301 | W5: 0.065 | X5: =N5*W5 -> 559 | Y5: =Z5*0.00133 -> 0.01995 | Z5: 15 | AA5: =R5+T5+W5+Y5 -> 0.14995 | AB5: =N5*AA5+AK5 -> 1362.67 | AC5: 0.1 | AD5: =(N5-M5)*AC5 -> 334 | AE5: =17.5 -> 17.5 | AF5: =N5-M5-Q5-AB5-AD5-AE5 -> 1595.83 | AG5: =AF5/N5 -> 0.18556163 | AH5: =N5-AB5-AI5 -> 7065.76 | AI5: =Y5*N5 -> 171.57 | AJ5: 0.0085 | AK5: =AJ5*N5 -> 73.1
A6: 45718 | B6: 9405 - 9408 - 53470 - 9407 | D6: GOIANIA | E6: GO | F6: IMPERATRIZ | G6: MA | H6: UNIFORT | I6: FINALIZADO | J6: SIM | K6: YURE RODRIGUES | M6: 6460 | N6: 10200 | O6: 350000 | P6: 0.0003 | Q6: =O6*P6 -> 105 | R6: 0.03 | S6: =R6*N6 -> 306 | T6: 0.035 | U6: 1 | V6: =T6*N6 -> 357 | W6: 0.065 | X6: =N6*W6 -> 663 | Y6: =Z6*0.00133 -> 0.01995 | Z6: 15 | AA6: =R6+T6+W6+Y6 -> 0.14995 | AB6: =N6*AA6+AK6 -> 1616.19 | AC6: 0.1 | AD6: =(N6-M6)*AC6 -> 374 | AE6: =17.5 -> 17.5 | AF6: =N6-M6-Q6-AB6-AD6-AE6 -> 1627.31 | AG6: =AF6/N6 -> 0.1595402 | AH6: =N6-AB6-AI6 -> 8380.32 | AI6: =Y6*N6 -> 203.49 | AJ6: 0.0085 | AK6: =AJ6*N6 -> 86.7
A7: 45718 | B7: 9396 | D7: GUARULHOS | E7: SP | F7: SALTO | G7: SP | H7: CYA RUBBER | I7: FINALIZADO | J7: SIM | K7: AGNALDO CICERO | M7: 1060 | N7: 2100 | O7: 50000 | P7: 0.0003 | Q7: =O7*P7 -> 15 | R7: 0.12 | S7: =R7*N7 -> 252 | T7: 0 | U7: 1 | V7: =T7*N7 -> 0 | W7: 0.065 | X7: =N7*W7 -> 136.5 | Y7: =Z7*0.00133 -> 0.01995 | Z7: 15 | AA7: =R7+T7+W7+Y7 -> 0.20495 | AB7: =N7*AA7+AK7 -> 448.245 | AC7: 0.13 | AD7: =(N7-M7)*AC7 -> 135.2 | AE7: =17.5 -> 17.5 | AF7: =N7-M7-Q7-AB7-AD7-AE7 -> 424.055 | AG7: =AF7/N7 -> 0.20193095 | AH7: =N7-AB7-AI7 -> 1609.86 | AI7: =Y7*N7 -> 41.895 | AJ7: 0.0085 | AK7: =AJ7*N7 -> 17.85
A8: 45718 | B8: 9397 | D8: GUARULHOS | E8: SP | F8: BRAGANÇA PAULISTA | G8: SP | H8: CYA RUBBER | I8: FINALIZADO | J8: SIM | K8: NATAN SANTOS | M8: 1140 | N8: 1540 | O8: 50000 | P8: 0.0003 | Q8: =O8*P8 -> 15 | R8: 0.12 | S8: =R8*N8 -> 184.8 | T8: 0 | U8: 1 | V8: =T8*N8 -> 0 | W8: 0.065 | X8: =N8*W8 -> 100.1 | Y8: =Z8*0.00133 -> 0.01995 | Z8: 15 | AA8: =R8+T8+W8+Y8 -> 0.20495 | AB8: =N8*AA8+AK8 -> 328.713 | AC8: 0 | AD8: =(N8-M8)*AC8 -> 0 | AE8: =17.5 -> 17.5 | AF8: =N8-M8-Q8-AB8-AD8-AE8 -> 38.787 | AG8: =AF8/N8 -> 0.025186364 | AH8: =N8-AB8-AI8 -> 1180.564 | AI8: =Y8*N8 -> 30.723 | AJ8: 0.0085 | AK8: =AJ8*N8 -> 13.09
A9: 45718 | B9: 9400 | D9: SÃO LEOPOLDO | E9: RS | F9: NOVA PETROPOLIS | G9: RS | H9: CYA RUBBER | I9: FINALIZADO | J9: SIM | K9: EMERSON FELIPE | M9: 960 | N9: 1790 | O9: 80000 | P9: 0.0003 | Q9: =O9*P9 -> 24 | R9: 0 | S9: =R9*N9 -> 0 | T9: 0.035 | U9: 1 | V9: =T9*N9 -> 62.65 | W9: 0.065 | X9: =N9*W9 -> 116.35 | Y9: =Z9*0.00133 -> 0.01995 | Z9: 15 | AA9: =R9+T9+W9+Y9 -> 0.11995 | AB9: =N9*AA9+AK9 -> 229.9255 | AC9: 0.13 | AD9: =(N9-M9)*AC9 -> 107.9 | AE9: =17.5 -> 17.5 | AF9: =N9-M9-Q9-AB9-AD9-AE9 -> 450.6745 | AG9: =AF9/N9 -> 0.25177346 | AH9: =N9-AB9-AI9 -> 1524.364 | AI9: =Y9*N9 -> 35.7105 | AJ9: 0.0085 | AK9: =AJ9*N9 -> 15.215
A10: 45718 | B10: 9413 | D10: SÃO LEOPOLDO | E10: RS | F10: CAXIAS DO SUL | G10: RS | H10: CYA RUBBER | I10: FINALIZADO | J10: SIM | K10: EMERSON FELIPE | M10: 960 | N10: 1790 | O10: 80000 | P10: 0.0003 | Q10: =O10*P10 -> 24 | R10: 0 | S10: =R10*N10 -> 0 | T10: 0.035 | U10: 1 | V10: =T10*N10 -> 62.65 | W10: 0.065 | X10: =N10*W10 -> 116.35 | Y10: =Z10*0.00133 -> 0.01995 | Z10: 15 | AA10: =R10+T10+W10+Y10 -> 0.11995 | AB10: =N10*AA10+AK10 -> 229.9255 | AC10: 0.13 | AD10: =(N10-M10)*AC10 -> 107.9 | AE10: =17.5 -> 17.5 | AF10: =N10-M10-Q10-AB10-AD10-AE10 -> 450.6745 | AG10: =AF10/N10 -> 0.25177346 | AH10: =N10-AB10-AI10 -> 1524.364 | AI10: =Y10*N10 -> 35.7105 | AJ10: 0.0085 | AK10: =AJ10*N10 -> 15.215
A11: 45718 | B11: 9433 | D11: GUARULHOS | E11: SP | F11: SAO PAULO | G11: SP | H11: CYA RUBBER | I11: FINALIZADO | J11: SIM | K11: AGNALDO CICERO | M11: 710 | N11: 1380 | O11: 50000 | P11: 0.0003 | Q11: =O11*P11 -> 15 | R11: 0.12 | S11: =R11*N11 -> 165.6 | T11: 0 | U11: 1 | V11: =T11*N11 -> 0 | W11: 0.065 | X11: =N11*W11 -> 89.7 | Y11: =Z11*0.00133 -> 0.01995 | Z11: 15 | AA11: =R11+T11+W11+Y11 -> 0.20495 | AB11: =N11*AA11+AK11 -> 294.561 | AC11: 0.13 | AD11: =(N11-M11)*AC11 -> 87.1 | AE11: =17.5 -> 17.5 | AF11: =N11-M11-Q11-AB11-AD11-AE11 -> 255.839 | AG11: =AF11/N11 -> 0.18539058 | AH11: =N11-AB11-AI11 -> 1057.908 | AI11: =Y11*N11 -> 27.531 | AJ11: 0.0085 | AK11: =AJ11*N11 -> 11.73
A12: 45718 | B12: 9445 | D12: JOINVILLE | E12: SC | F12: SANTA CRUZ DO RIO PARDO | G12: SP | H12: SATAKE | I12: FINALIZADO | J12: SIM | K12: ALEX VARELA | M12: 910 | N12: 1700 | O12: 20000 | P12: 0.0003 | Q12: =O12*P12 -> 6 | R12: 0.12 | S12: =R12*N12 -> 204 | T12: 0 | U12: 1 | V12: =T12*N12 -> 0 | W12: 0.065 | X12: =N12*W12 -> 110.5 | Y12: =Z12*0.00133 -> 0.01995 | Z12: 15 | AA12: =R12+T12+W12+Y12 -> 0.20495 | AB12: =N12*AA12+AK12 -> 362.865 | AC12: 0.13 | AD12: =(N12-M12)*AC12 -> 102.7 | AE12: =17.5 -> 17.5 | AF12: =N12-M12-Q12-AB12-AD12-AE12 -> 300.935 | AG12: =AF12/N12 -> 0.17702059 | AH12: =N12-AB12-AI12 -> 1303.22 | AI12: =Y12*N12 -> 33.915 | AJ12: 0.0085 | AK12: =AJ12*N12 -> 14.45
A13: 45719 | B13: 9515 | D13: ITAJAI | E13: SC | F13: BETIM | G13: MG | H13: UNIFORT | I13: FINALIZADO | J13: SIM | K13: JOAO CARLOS | M13: 9060 | N13: 14100 | O13: 340000 | P13: 0.0003 | Q13: =O13*P13 -> 102 | R13: 0.03 | S13: =R13*N13 -> 423 | T13: 0.035 | U13: 1 | V13: =T13*N13 -> 493.5 | W13: 0.065 | X13: =N13*W13 -> 916.5 | Y13: =Z13*0.00133 -> 0.01995 | Z13: 15 | AA13: =R13+T13+W13+Y13 -> 0.14995 | AB13: =N13*AA13+AK13 -> 2234.145 | AC13: 0.09 | AD13: =(N13-M13)*AC13 -> 453.6 | AE13: =17.5 -> 17.5 | AF13: =N13-M13-Q13-AB13-AD13-AE13 -> 2232.755 | AG13: =AF13/N13 -> 0.15835142 | AH13: =N13-AB13-AI13 -> 11584.56 | AI13: =Y13*N13 -> 281.295 | AJ13: 0.0085 | AK13: =AJ13*N13 -> 119.85
A14: 45719 | B14: 9535 | D14: ITAJAI | E14: SC | F14: BETIM | G14: MG | H14: UNIFORT | I14: FINALIZADO | J14: SIM | K14: ARLENIO FERREIRA | M14: 9060 | N14: 14000 | O14: 400000 | P14: 0.0003 | Q14: =O14*P14 -> 120 | R14: 0.03 | S14: =R14*N14 -> 420 | T14: 0.035 | U14: 1 | V14: =T14*N14 -> 490 | W14: 0.065 | X14: =N14*W14 -> 910 | Y14: =Z14*0.00133 -> 0.01995 | Z14: 15 | AA14: =R14+T14+W14+Y14 -> 0.14995 | AB14: =N14*AA14+AK14 -> 2218.3 | AC14: 0.09 | AD14: =(N14-M14)*AC14 -> 444.6 | AE14: =17.5 -> 17.5 | AF14: =N14-M14-Q14-AB14-AD14-AE14 -> 2139.6 | AG14: =AF14/N14 -> 0.15282857 | AH14: =N14-AB14-AI14 -> 11502.4 | AI14: =Y14*N14 -> 279.3 | AJ14: 0.0085 | AK14: =AJ14*N14 -> 119
A15: 45719 | B15: 9529 | D15: GUAURLHOS | E15: SP | F15: GUARAREMA | G15: SP | H15: CYA RUBBER | I15: FINALIZADO | J15: SIM | K15: IVANILDO ANTUNES | M15: 1010 | N15: 1790 | O15: 100000 | P15: 0.0003 | Q15: =O15*P15 -> 30 | R15: 0.12 | S15: =R15*N15 -> 214.8 | T15: 0 | U15: 1 | V15: =T15*N15 -> 0 | W15: 0.065 | X15: =N15*W15 -> 116.35 | Y15: =Z15*0.00133 -> 0.01995 | Z15: 15 | AA15: =R15+T15+W15+Y15 -> 0.20495 | AB15: =N15*AA15+AK15 -> 382.0755 | AC15: 0.1 | AD15: =(N15-M15)*AC15 -> 78 | AE15: =17.5 -> 17.5 | AF15: =N15-M15-Q15-AB15-AD15-AE15 -> 272.4245 | AG15: =AF15/N15 -> 0.15219246 | AH15: =N15-AB15-AI15 -> 1372.214 | AI15: =Y15*N15 -> 35.7105 | AJ15: 0.0085 | AK15: =AJ15*N15 -> 15.215
A16: 45719 | B16: 9497-9498-9499-9500 | D16: GOIANIA | E16: GO | F16: VARZEA GRANDE | G16: MT | H16: UNIFORT | I16: FINALIZADO | J16: SIM | K16: ATHOS RODRIGUES | M16: 4460 | N16: 7500 | O16: 100000 | P16: 0.0003 | Q16: =O16*P16 -> 30 | R16: 0.03 | S16: =R16*N16 -> 225 | T16: 0.035 | U16: 1 | V16: =T16*N16 -> 262.5 | W16: 0.065 | X16: =N16*W16 -> 487.5 | Y16: =Z16*0.00133 -> 0.01995 | Z16: 15 | AA16: =R16+T16+W16+Y16 -> 0.14995 | AB16: =N16*AA16+AK16 -> 1188.375 | AC16: 0.1 | AD16: =(N16-M16)*AC16 -> 304 | AE16: =17.5 -> 17.5 | AF16: =N16-M16-Q16-AB16-AD16-AE16 -> 1500.125 | AG16: =AF16/N16 -> 0.20001667 | AH16: =N16-AB16-AI16 -> 6162 | AI16: =Y16*N16 -> 149.625 | AJ16: 0.0085 | AK16: =AJ16*N16 -> 63.75
A17: 45720 | B17: 9555 | D17: GUARULHOS | E17: SP | F17: DIADEMA | G17: SP | H17: CYA RUBBER | I17: FINALIZADO | J17: SIM | K17: EDINALDO DA SILVA | M17: 580 | N17: 1050 | O17: 20000 | P17: 0.0003 | Q17: =O17*P17 -> 6 | R17: 0.12 | S17: =R17*N17 -> 126 | T17: 0 | U17: 1 | V17: =T17*N17 -> 0 | W17: 0.065 | X17: =N17*W17 -> 68.25 | Y17: =Z17*0.00133 -> 0.01995 | Z17: 15 | AA17: =R17+T17+W17+Y17 -> 0.20495 | AB17: =N17*AA17+AK17 -> 224.1225 | AC17: 0.13 | AD17: =(N17-M17)*AC17 -> 61.1 | AE17: =17.5 -> 17.5 | AF17: =N17-M17-Q17-AB17-AD17-AE17 -> 161.2775 | AG17: =AF17/N17 -> 0.15359762 | AH17: =N17-AB17-AI17 -> 804.93 | AI17: =Y17*N17 -> 20.9475 | AJ17: 0.0085 | AK17: =AJ17*N17 -> 8.925
A18: 45721 | B18: 9618 | D18: GUARULHOS | E18: SP | F18: BRAGANÇA PAULISTA | G18: SP | H18: CYA RUBBER | I18: FINALIZADO | J18: SIM | K18: ALMIR FERREIRA | M18: 960 | N18: 1540 | O18: 50000 | P18: 0.0003 | Q18: =O18*P18 -> 15 | R18: 0.12 | S18: =R18*N18 -> 184.8 | T18: 0 | U18: 1 | V18: =T18*N18 -> 0 | W18: 0.065 | X18: =N18*W18 -> 100.1 | Y18: =Z18*0.00133 -> 0.01995 | Z18: 15 | AA18: =R18+T18+W18+Y18 -> 0.20495 | AB18: =N18*AA18+AK18 -> 328.713 | AC18: 0.06 | AD18: =(N18-M18)*AC18 -> 34.8 | AE18: =17.5 -> 17.5 | AF18: =N18-M18-Q18-AB18-AD18-AE18 -> 183.987 | AG18: =AF18/N18 -> 0.11947208 | AH18: =N18-AB18-AI18 -> 1180.564 | AI18: =Y18*N18 -> 30.723 | AJ18: 0.0085 | AK18: =AJ18*N18 -> 13.09
A19: 45722 | B19: 9702 - 9703 - 53473 - 9704 - 9707 - 9708 | D19: BETIM | E19: MG | F19: GOIANIA | G19: GO | H19: UNIFORT | I19: FINALIZADO | J19: SIM | K19: JOSE NILTO TAVARES | M19: 7760 | N19: 13000 | O19: 150000 | P19: 0.0003 | Q19: =O19*P19 -> 45 | R19: 0.03 | S19: =R19*N19 -> 390 | T19: 0.035 | U19: 1 | V19: =T19*N19 -> 455 | W19: 0.065 | X19: =N19*W19 -> 845 | Y19: =Z19*0.00133 -> 0.01995 | Z19: 15 | AA19: =R19+T19+W19+Y19 -> 0.14995 | AB19: =N19*AA19+AK19 -> 2059.85 | AC19: 0.1 | AD19: =(N19-M19)*AC19 -> 524 | AE19: =17.5 -> 17.5 | AF19: =N19-M19-Q19-AB19-AD19-AE19 -> 2593.65 | AG19: =AF19/N19 -> 0.19951154 | AH19: =N19-AB19-AI19 -> 10680.8 | AI19: =Y19*N19 -> 259.35 | AJ19: 0.0085 | AK19: =AJ19*N19 -> 110.5
A20: 46087 | B20: 9695 | D20: PATO BRAGADO | E20: PR | F20: SAO JOAO DEL REI | G20: MG | H20: SCHEMAQ | I20: FINALIZADO | J20: SIM | K20: MARCOS RINALDO | M20: 1660 | N20: 2500 | O20: 50000 | P20: 0.0003 | Q20: =O20*P20 -> 15 | R20: 0.12 | S20: =R20*N20 -> 300 | T20: 0 | U20: 1 | V20: =T20*N20 -> 0 | W20: 0.065 | X20: =N20*W20 -> 162.5 | Y20: =Z20*0.00133 -> 0.01995 | Z20: 15 | AA20: =R20+T20+W20+Y20 -> 0.20495 | AB20: =N20*AA20+AK20 -> 533.625 | AC20: 0.04 | AD20: =(N20-M20)*AC20 -> 33.6 | AE20: =17.5 -> 17.5 | AF20: =N20-M20-Q20-AB20-AD20-AE20 -> 240.275 | AG20: =AF20/N20 -> 0.09611 | AH20: =N20-AB20-AI20 -> 1916.5 | AI20: =Y20*N20 -> 49.875 | AJ20: 0.0085 | AK20: =AJ20*N20 -> 21.25
A21: 45723 | B21: 29028 | D21: SANTO ANDRE | E21: SP | F21: BELO HORIZONTE | G21: MG | H21: ACTOS | I21: FINALIZADO | J21: SIM | K21: MAGNUN BRUNO | M21: 6060 | N21: 7600 | O21: 300000 | P21: 0.0003 | Q21: =O21*P21 -> 90 | R21: 0.12 | S21: =R21*N21 -> 912 | T21: 0 | U21: 1 | V21: =T21*N21 -> 0 | W21: 0.065 | X21: =N21*W21 -> 494 | Y21: =Z21*0.00133 -> 0.03724 | Z21: 28 | AA21: =R21+T21+W21+Y21 -> 0.22224 | AB21: =N21*AA21+AK21 -> 1753.624 | AC21: 0 | AD21: 300 | AE21: =17.5 -> 17.5 | AF21: =N21-M21-Q21-AB21-AD21-AE21 -> -621.124 | AG21: =AF21/N21 -> -0.081726842 | AH21: =N21-AB21-AI21 -> 5563.352 | AI21: =Y21*N21 -> 283.024 | AJ21: 0.0085 | AK21: =AJ21*N21 -> 64.6
A22: 45724 | B22: 9723-9724-9725-9726-9727-9728 | D22: GOIANIA | E22: GO | F22: MARABA | G22: PA | H22: UNIFORT | I22: FINALIZADO | J22: SIM | K22: CARLOS LACERDA | M22: 7460 | N22: 13000 | O22: 150000 | P22: 0.0003 | Q22: =O22*P22 -> 45 | R22: 0.03 | S22: =R22*N22 -> 390 | T22: 0.035 | U22: 1 | V22: =T22*N22 -> 455 | W22: 0.065 | X22: =N22*W22 -> 845 | Y22: =Z22*0.00133 -> 0.01995 | Z22: 15 | AA22: =R22+T22+W22+Y22 -> 0.14995 | AB22: =N22*AA22+AK22 -> 2059.85 | AC22: 0.1 | AD22: =(N22-M22)*AC22 -> 554 | AE22: =17.5 -> 17.5 | AF22: =N22-M22-Q22-AB22-AD22-AE22 -> 2863.65 | AG22: =AF22/N22 -> 0.22028077 | AH22: =N22-AB22-AI22 -> 10680.8 | AI22: =Y22*N22 -> 259.35 | AJ22: 0.0085 | AK22: =AJ22*N22 -> 110.5
A23: 45724 | B23: 9729-9730-9731-9732 | D23: GOIANIA | E23: GO | F23: VARZEA GRANDE | G23: MT | H23: UNIFORT | I23: FINALIZADO | J23: SIM | K23: ANTONIO DE SOUZA | M23: 5060 | N23: 8500 | O23: 150000 | P23: 0.0003 | Q23: =O23*P23 -> 45 | R23: 0.03 | S23: =R23*N23 -> 255 | T23: 0.035 | U23: 1 | V23: =T23*N23 -> 297.5 | W23: 0.065 | X23: =N23*W23 -> 552.5 | Y23: =Z23*0.00133 -> 0.01995 | Z23: 15 | AA23: =R23+T23+W23+Y23 -> 0.14995 | AB23: =N23*AA23+AK23 -> 1346.825 | AC23: 0.1 | AD23: =(N23-M23)*AC23 -> 344 | AE23: =17.5 -> 17.5 | AF23: =N23-M23-Q23-AB23-AD23-AE23 -> 1686.675 | AG23: =AF23/N23 -> 0.19843235 | AH23: =N23-AB23-AI23 -> 6983.6 | AI23: =Y23*N23 -> 169.575 | AJ23: 0.0085 | AK23: =AJ23*N23 -> 72.25
A24: 46090 | B24: 9733 | D24: GUARULHOS | E24: SP | F24: DIADEMA | G24: SP | H24: CYA RUBBER | I24: FINALIZADO | J24: SIM | K24: EDINALDO DA SILVA VIEIRA | M24: 580 | N24: 1050 | O24: 35473 | P24: 0.0003 | Q24: =O24*P24 -> 10.6419 | R24: 0.12 | S24: =R24*N24 -> 126 | T24: 0 | U24: 1 | V24: =T24*N24 -> 0 | W24: 0.065 | X24: =N24*W24 -> 68.25 | Y24: =Z24*0.00133 -> 0.01995 | Z24: 15 | AA24: =R24+T24+W24+Y24 -> 0.20495 | AB24: =N24*AA24+AK24 -> 224.1225 | AC24: 0.12 | AD24: =(N24-M24)*AC24 -> 56.4 | AE24: =17.5 -> 17.5 | AF24: =N24-M24-Q24-AB24-AD24-AE24 -> 161.3356 | AG24: =AF24/N24 -> 0.15365295 | AH24: =N24-AB24-AI24 -> 804.93 | AI24: =Y24*N24 -> 20.9475 | AJ24: 0.0085 | AK24: =AJ24*N24 -> 8.925
A25: 46090 | B25: 9750 | D25: ITAJAI | E25: SC | F25: BETIM | G25: MG | H25: UNIFORT | I25: FINALIZADO | J25: SIM | K25: ADALBERTO BATISTA LARA | M25: 9060 | N25: 14000 | O25: 464887.94 | P25: 0.0003 | Q25: =O25*P25 -> 139.46638 | R25: 0.03 | S25: =R25*N25 -> 420 | T25: 0.035 | U25: 1 | V25: =T25*N25 -> 490 | W25: 0.065 | X25: =N25*W25 -> 910 | Y25: =Z25*0.00133 -> 0.01995 | Z25: 15 | AA25: =R25+T25+W25+Y25 -> 0.14995 | AB25: =N25*AA25+AK25 -> 2218.3 | AC25: 0.09 | AD25: =(N25-M25)*AC25 -> 444.6 | AE25: =17.5 -> 17.5 | AF25: =N25-M25-Q25-AB25-AD25-AE25 -> 2120.1336 | AG25: =AF25/N25 -> 0.15143812 | AH25: =N25-AB25-AI25 -> 11502.4 | AI25: =Y25*N25 -> 279.3 | AJ25: 0.0085 | AK25: =AJ25*N25 -> 119
A26: 46091 | B26: 9762 | D26: GUARULHOS | E26: SP | F26: SALTO | G26: SP | H26: CYA RUBBER | I26: FINALIZADO | J26: SIM | K26: AGNALDO CICERO DA SILVA | M26: 1060 | N26: 2100 | O26: 50000 | P26: 0.0003 | Q26: =O26*P26 -> 15 | R26: 0.12 | S26: =R26*N26 -> 252 | T26: 0 | U26: 1 | V26: =T26*N26 -> 0 | W26: 0.065 | X26: =N26*W26 -> 136.5 | Y26: =Z26*0.00133 -> 0.01995 | Z26: 15 | AA26: =R26+T26+W26+Y26 -> 0.20495 | AB26: =N26*AA26+AK26 -> 448.245 | AC26: 0.13 | AD26: =(N26-M26)*AC26 -> 135.2 | AE26: =17.5 -> 17.5 | AF26: =N26-M26-Q26-AB26-AD26-AE26 -> 424.055 | AG26: =AF26/N26 -> 0.20193095 | AH26: =N26-AB26-AI26 -> 1609.86 | AI26: =Y26*N26 -> 41.895 | AJ26: 0.0085 | AK26: =AJ26*N26 -> 17.85
A27: 46091 | B27: 9783 | D27: ROCA SALES | E27: RS | F27: NOVA PRATA | G27: RS | H27: QUISVI | I27: FINALIZADO | J27: SIM | K27: MIKAEL SEIMETZ | M27: 760 | N27: 1800 | O27: 30000 | P27: 0.0003 | Q27: =O27*P27 -> 9 | R27: 0 | S27: =R27*N27 -> 0 | T27: 0 | U27: 1 | V27: =T27*N27 -> 0 | W27: 0.065 | X27: =N27*W27 -> 117 | Y27: =Z27*0.00133 -> 0.01995 | Z27: 15 | AA27: =R27+T27+W27+Y27 -> 0.08495 | AB27: =N27*AA27+AK27 -> 168.21 | AC27: 0.13 | AD27: =(N27-M27)*AC27 -> 135.2 | AE27: =17.5 -> 17.5 | AF27: =N27-M27-Q27-AB27-AD27-AE27 -> 710.09 | AG27: =AF27/N27 -> 0.39449444 | AH27: =N27-AB27-AI27 -> 1595.88 | AI27: =Y27*N27 -> 35.91 | AJ27: 0.0085 | AK27: =AJ27*N27 -> 15.3
A28: 46091 | B28: 9904 - 9905 | D28: ITAJAI | E28: SC | F28: BETIM | G28: MG | H28: UNIFORT | I28: FINALIZADO | J28: SIM | K28: ERISTON EVANGELISTA | M28: 9060 | N28: 14000 | O28: 506000 | P28: 0.0003 | Q28: =O28*P28 -> 151.8 | R28: 0.03 | S28: =R28*N28 -> 420 | T28: 0.035 | U28: 1 | V28: =T28*N28 -> 490 | W28: 0.065 | X28: =N28*W28 -> 910 | Y28: =Z28*0.00133 -> 0.01995 | Z28: 15 | AA28: =R28+T28+W28+Y28 -> 0.14995 | AB28: =N28*AA28+AK28 -> 2218.3 | AC28: 0.09 | AD28: =(N28-M28)*AC28 -> 444.6 | AE28: =17.5 -> 17.5 | AF28: =N28-M28-Q28-AB28-AD28-AE28 -> 2107.8 | AG28: =AF28/N28 -> 0.15055714 | AH28: =N28-AB28-AI28 -> 11502.4 | AI28: =Y28*N28 -> 279.3 | AJ28: 0.0085 | AK28: =AJ28*N28 -> 119
A29: 46091 | B29: 9908 | D29: JEQUIE | E29: BA | F29: LAGARTO | G29: SE | H29: TOTALFLEX | I29: FINALIZADO | J29: SIM | K29: ALISON CESAR DE BRITO SILVA | M29: =4623.22+60 -> 4683.22 | N29: 5500 | O29: 300000 | P29: 0.0003 | Q29: =O29*P29 -> 90 | R29: 0.12 | S29: =R29*N29 -> 660 | T29: 0 | U29: 1 | V29: =T29*N29 -> 0 | W29: 0.065 | X29: =N29*W29 -> 357.5 | Y29: =Z29*0.00133 -> 0.00931 | Z29: 7 | AA29: =R29+T29+W29+Y29 -> 0.19431 | AB29: =N29*AA29+AK29 -> 1115.455 | AC29: 0 | AD29: =(N29-M29)*AC29 -> 0 | AE29: =17.5 -> 17.5 | AF29: =N29-M29-Q29-AB29-AD29-AE29 -> -406.175 | AG29: =AF29/N29 -> -0.07385 | AH29: =N29-AB29-AI29 -> 4333.34 | AI29: =Y29*N29 -> 51.205 | AJ29: 0.0085 | AK29: =AJ29*N29 -> 46.75
A30: 46090 | B30: 9734 | D30: GUARULHOS | E30: SP | F30: SAO PAULO | G30: SP | H30: CYA RUBBER | I30: FINALIZADO | J30: SIM | K30: GERALDO | M30: 660 | N30: 980 | O30: 30000 | P30: 0.0003 | Q30: =O30*P30 -> 9 | R30: 0.12 | S30: =R30*N30 -> 117.6 | T30: 0 | U30: 1 | V30: =T30*N30 -> 0 | W30: 0.065 | X30: =N30*W30 -> 63.7 | Y30: =Z30*0.00133 -> 0.01995 | Z30: 15 | AA30: =R30+T30+W30+Y30 -> 0.20495 | AB30: =N30*AA30+AK30 -> 209.181 | AC30: 0.03 | AD30: =(N30-M30)*AC30 -> 9.6 | AE30: =17.5 -> 17.5 | AF30: =N30-M30-Q30-AB30-AD30-AE30 -> 74.719 | AG30: =AF30/N30 -> 0.076243878 | AH30: =N30-AB30-AI30 -> 751.268 | AI30: =Y30*N30 -> 19.551 | AJ30: 0.0085 | AK30: =AJ30*N30 -> 8.33
A31: 46092 | B31: 9921 | D31: GUARULHOS | E31: SP | F31: SAO PAULO | G31: SP | H31: CYA RUBBER | I31: FINALIZADO | J31: SIM | K31: EDMILSON DE SOUZA JARDIM | M31: 810 | N31: 1380 | O31: 50000 | P31: 0.0003 | Q31: =O31*P31 -> 15 | R31: 0.12 | S31: =R31*N31 -> 165.6 | T31: 0 | U31: 1 | V31: =T31*N31 -> 0 | W31: 0.065 | X31: =N31*W31 -> 89.7 | Y31: =Z31*0.00133 -> 0.01995 | Z31: 15 | AA31: =R31+T31+W31+Y31 -> 0.20495 | AB31: =N31*AA31+AK31 -> 294.561 | AC31: 0.07 | AD31: =(N31-M31)*AC31 -> 39.9 | AE31: =17.5 -> 17.5 | AF31: =N31-M31-Q31-AB31-AD31-AE31 -> 203.039 | AG31: =AF31/N31 -> 0.14712971 | AH31: =N31-AB31-AI31 -> 1057.908 | AI31: =Y31*N31 -> 27.531 | AJ31: 0.0085 | AK31: =AJ31*N31 -> 11.73
A32: 46092 | B32: 9939 | D32: GUARULHOS | E32: SP | F32: GUARULHOS | G32: SP | H32: CYA RUBBER | I32: FINALIZADO | J32: SIM | K32: JOAO PEDRO BELARMINO | M32: 260 | N32: 400 | O32: 20000 | P32: 0.0003 | Q32: =O32*P32 -> 6 | R32: 0.12 | S32: =R32*N32 -> 48 | T32: 0 | U32: 1 | V32: =T32*N32 -> 0 | W32: 0.065 | X32: =N32*W32 -> 26 | Y32: =Z32*0.00133 -> 0.01995 | Z32: 15 | AA32: =R32+T32+W32+Y32 -> 0.20495 | AB32: =N32*AA32+AK32 -> 85.38 | AC32: 0.02 | AD32: =(N32-M32)*AC32 -> 2.8 | AE32: =17.5 -> 17.5 | AF32: =N32-M32-Q32-AB32-AD32-AE32 -> 28.32 | AG32: =AF32/N32 -> 0.0708 | AH32: =N32-AB32-AI32 -> 306.64 | AI32: =Y32*N32 -> 7.98 | AJ32: 0.0085 | AK32: =AJ32*N32 -> 3.4
A33: 46092 | B33: 9948 | D33: GUARULHOS | E33: SP | F33: GUARAREMA | G33: SP | H33: CYA RUBBER | I33: FINALIZADO | J33: SIM | K33: JOAO PEDRO BELARMINO | M33: 1010 | N33: 1790 | O33: 50000 | P33: 0.0003 | Q33: =O33*P33 -> 15 | R33: 0.12 | S33: =R33*N33 -> 214.8 | T33: 0 | U33: 1 | V33: =T33*N33 -> 0 | W33: 0.065 | X33: =N33*W33 -> 116.35 | Y33: =Z33*0.00133 -> 0.01995 | Z33: 15 | AA33: =R33+T33+W33+Y33 -> 0.20495 | AB33: =N33*AA33+AK33 -> 382.0755 | AC33: 0.12 | AD33: =(N33-M33)*AC33 -> 93.6 | AE33: =17.5 -> 17.5 | AF33: =N33-M33-Q33-AB33-AD33-AE33 -> 271.8245 | AG33: =AF33/N33 -> 0.15185726 | AH33: =N33-AB33-AI33 -> 1372.214 | AI33: =Y33*N33 -> 35.7105 | AJ33: 0.0085 | AK33: =AJ33*N33 -> 15.215
A34: 46093 | B34: 6 - 7 - 5 - 8 - 9 - 10 | D34: GOIANIA | E34: GO | F34: MARABA | G34: PA | H34: UNIFORT | I34: FINALIZADO | J34: SIM | K34: LEVY FERREIRA | M34: 7760 | N34: 12500 | O34: 150000 | P34: 0.0003 | Q34: =O34*P34 -> 45 | R34: 0.03 | S34: =R34*N34 -> 375 | T34: 0.035 | U34: 1 | V34: =T34*N34 -> 437.5 | W34: 0.065 | X34: =N34*W34 -> 812.5 | Y34: =Z34*0.00133 -> 0.01995 | Z34: 15 | AA34: =R34+T34+W34+Y34 -> 0.14995 | AB34: =N34*AA34+AK34 -> 1980.625 | AC34: 0.1 | AD34: =(N34-M34)*AC34 -> 474 | AE34: =17.5 -> 17.5 | AF34: =N34-M34-Q34-AB34-AD34-AE34 -> 2222.875 | AG34: =AF34/N34 -> 0.17783 | AH34: =N34-AB34-AI34 -> 10270 | AI34: =Y34*N34 -> 249.375 | AJ34: 0.0085 | AK34: =AJ34*N34 -> 106.25
A35: 46093 | B35: 9998 - 9999 - 10070 - 10071 | D35: GOIANIA | E35: GO | F35: VARZEA GRANDE | G35: MT | H35: UNIFORT | I35: FINALIZADO | J35: SIM | K35: ANTONIO DE SOUZA | M35: 5160 | N35: 8500 | O35: 150000 | P35: 0.0003 | Q35: =O35*P35 -> 45 | R35: 0.03 | S35: =R35*N35 -> 255 | T35: 0.035 | U35: 1 | V35: =T35*N35 -> 297.5 | W35: 0.065 | X35: =N35*W35 -> 552.5 | Y35: =Z35*0.00133 -> 0.01995 | Z35: 15 | AA35: =R35+T35+W35+Y35 -> 0.14995 | AB35: =N35*AA35+AK35 -> 1346.825 | AC35: 0.1 | AD35: =(N35-M35)*AC35 -> 334 | AE35: =17.5 -> 17.5 | AF35: =N35-M35-Q35-AB35-AD35-AE35 -> 1596.675 | AG35: =AF35/N35 -> 0.18784412 | AH35: =N35-AB35-AI35 -> 6983.6 | AI35: =Y35*N35 -> 169.575 | AJ35: 0.0085 | AK35: =AJ35*N35 -> 72.25
A36: 46093 | B36: 9981 | D36: ROCA SALES | E36: RS | F36: NOVA PRATA | G36: RS | H36: QUISVI | I36: FINALIZADO | J36: SIM | K36: MIKAEL SEIMETZ | M36: =845.9+60 -> 905.9 | N36: 1800 | O36: 30000 | P36: 0.0003 | Q36: =O36*P36 -> 9 | R36: 0 | S36: =R36*N36 -> 0 | T36: 0 | U36: 1 | V36: =T36*N36 -> 0 | W36: 0.065 | X36: =N36*W36 -> 117 | Y36: =Z36*0.00133 -> 0.01995 | Z36: 15 | AA36: =R36+T36+W36+Y36 -> 0.08495 | AB36: =N36*AA36+AK36 -> 168.21 | AC36: 0.13 | AD36: =(N36-M36)*AC36 -> 116.233 | AE36: =17.5 -> 17.5 | AF36: =N36-M36-Q36-AB36-AD36-AE36 -> 583.157 | AG36: =AF36/N36 -> 0.32397611 | AH36: =N36-AB36-AI36 -> 1595.88 | AI36: =Y36*N36 -> 35.91 | AJ36: 0.0085 | AK36: =AJ36*N36 -> 15.3
A37: 46094 | B37: 35 | D37: GUARULHOS | E37: SP | F37: SAO JOSE DOS CAMPOS | G37: SP | H37: CYA RUBBER | I37: FINALIZADO | J37: SIM | K37: AGNALDO CICERO DA SILVA | M37: 810 | N37: 1620 | O37: 50000 | P37: 0.0003 | Q37: =O37*P37 -> 15 | R37: 0.12 | S37: =R37*N37 -> 194.4 | T37: 0 | U37: 1 | V37: =T37*N37 -> 0 | W37: 0.065 | X37: =N37*W37 -> 105.3 | Y37: =Z37*0.00133 -> 0.01995 | Z37: 15 | AA37: =R37+T37+W37+Y37 -> 0.20495 | AB37: =N37*AA37+AK37 -> 345.789 | AC37: 0.13 | AD37: =(N37-M37)*AC37 -> 105.3 | AE37: =17.5 -> 17.5 | AF37: =N37-M37-Q37-AB37-AD37-AE37 -> 326.411 | AG37: =AF37/N37 -> 0.20148827 | AH37: =N37-AB37-AI37 -> 1241.892 | AI37: =Y37*N37 -> 32.319 | AJ37: 0.0085 | AK37: =AJ37*N37 -> 13.77
A38: 46094 | B38: 29133 | D38: GUARULHOS | E38: SP | F38: ARAQUARI | G38: SC | H38: CYA RUBBER | I38: FINALIZADO | J38: SIM | K38: MARCIO | M38: 2660 | N38: 4650 | O38: 100000 | P38: 0.0003 | Q38: =O38*P38 -> 30 | R38: 0.12 | S38: =R38*N38 -> 558 | T38: 0 | U38: 1 | V38: =T38*N38 -> 0 | W38: 0.065 | X38: =N38*W38 -> 302.25 | Y38: =Z38*0.00133 -> 0.01995 | Z38: 15 | AA38: =R38+T38+W38+Y38 -> 0.20495 | AB38: =N38*AA38+AK38 -> 992.5425 | AC38: 0.12 | AD38: =(N38-M38)*AC38 -> 238.8 | AE38: =17.5 -> 17.5 | AF38: =N38-M38-Q38-AB38-AD38-AE38 -> 711.1575 | AG38: =AF38/N38 -> 0.1529371 | AH38: =N38-AB38-AI38 -> 3564.69 | AI38: =Y38*N38 -> 92.7675 | AJ38: 0.0085 | AK38: =AJ38*N38 -> 39.525
A39: 46094 | B39: 61 | D39: SAO LEOPOLDO | E39: RS | F39: ROCA SALES | G39: RS | H39: CYA RUBBER | I39: FINALIZADO | J39: SIM | K39: LUIS FERNANDO | M39: =1199.886+60 -> 1259.886 | N39: 1950 | O39: 80000 | P39: 0.0003 | Q39: =O39*P39 -> 24 | R39: 0 | S39: =R39*N39 -> 0 | T39: 0.035 | U39: 1 | V39: =T39*N39 -> 68.25 | W39: 0.065 | X39: =N39*W39 -> 126.75 | Y39: =Z39*0.00133 -> 0.01995 | Z39: 15 | AA39: =R39+T39+W39+Y39 -> 0.11995 | AB39: =N39*AA39+AK39 -> 250.4775 | AC39: 0.13 | AD39: =(N39-M39)*AC39 -> 89.71482 | AE39: =17.5 -> 17.5 | AF39: =N39-M39-Q39-AB39-AD39-AE39 -> 308.42168 | AG39: =AF39/N39 -> 0.15816496 | AH39: =N39-AB39-AI39 -> 1660.62 | AI39: =Y39*N39 -> 38.9025 | AJ39: 0.0085 | AK39: =AJ39*N39 -> 16.575
A40: 46095 | B40: 87 | D40: ITAJAI | E40: SC | F40: BETIM | G40: MG | H40: UNIFORT | I40: FINALIZADO | J40: SIM | K40: GABRIEL ADAO | M40: 9310 | N40: 14400 | O40: 400000 | P40: 0.0003 | Q40: =O40*P40 -> 120 | R40: 0.03 | S40: =R40*N40 -> 432 | T40: 0.035 | U40: 1 | V40: =T40*N40 -> 504 | W40: 0.065 | X40: =N40*W40 -> 936 | Y40: =Z40*0.00133 -> 0.01995 | Z40: 15 | AA40: =R40+T40+W40+Y40 -> 0.14995 | AB40: =N40*AA40+AK40 -> 2281.68 | AC40: 0.1 | AD40: =(N40-M40)*AC40 -> 509 | AE40: =17.5 -> 17.5 | AF40: =N40-M40-Q40-AB40-AD40-AE40 -> 2161.82 | AG40: =AF40/N40 -> 0.15012639 | AH40: =N40-AB40-AI40 -> 11831.04 | AI40: =Y40*N40 -> 287.28 | AJ40: 0.0085 | AK40: =AJ40*N40 -> 122.4
A41: 46097 | B41: 92 | D41: GUARULHOS | E41: SP | F41: SALTO | G41: SP | H41: CYA RUBBER | I41: FINALIZADO | J41: SIM | K41: AGNALDO CICERO | M41: 1060 | N41: 2100 | O41: 50000 | P41: 0.0003 | Q41: =O41*P41 -> 15 | R41: 0.12 | S41: =R41*N41 -> 252 | T41: 0 | U41: 1 | V41: =T41*N41 -> 0 | W41: 0.065 | X41: =N41*W41 -> 136.5 | Y41: =Z41*0.00133 -> 0.01995 | Z41: 15 | AA41: =R41+T41+W41+Y41 -> 0.20495 | AB41: =N41*AA41+AK41 -> 448.245 | AC41: 0.13 | AD41: =(N41-M41)*AC41 -> 135.2 | AE41: =17.5 -> 17.5 | AF41: =N41-M41-Q41-AB41-AD41-AE41 -> 424.055 | AG41: =AF41/N41 -> 0.20193095 | AH41: =N41-AB41-AI41 -> 1609.86 | AI41: =Y41*N41 -> 41.895 | AJ41: 0.0085 | AK41: =AJ41*N41 -> 17.85
A42: 46097 | B42: 163 | D42: ITAJAI | E42: SC | F42: BETIM | G42: MG | H42: UNIFORT | I42: FINALIZADO | J42: SIM | K42: GENELSO DE OLIVEIRA | M42: 10060 | N42: 15600 | O42: 400000 | P42: 0.0003 | Q42: =O42*P42 -> 120 | R42: 0.03 | S42: =R42*N42 -> 468 | T42: 0.035 | U42: 1 | V42: =T42*N42 -> 546 | W42: 0.065 | X42: =N42*W42 -> 1014 | Y42: =Z42*0.00133 -> 0.01995 | Z42: 15 | AA42: =R42+T42+W42+Y42 -> 0.14995 | AB42: =N42*AA42+AK42 -> 2471.82 | AC42: 0.1 | AD42: =(N42-M42)*AC42 -> 554 | AE42: =17.5 -> 17.5 | AF42: =N42-M42-Q42-AB42-AD42-AE42 -> 2376.68 | AG42: =AF42/N42 -> 0.15235128 | AH42: =N42-AB42-AI42 -> 12816.96 | AI42: =Y42*N42 -> 311.22 | AJ42: 0.0085 | AK42: =AJ42*N42 -> 132.6
A43: 46097 | B43: 152 | D43: GUARULHOS | E43: SP | F43: JAGUARIUNA | G43: SP | H43: CYA RUBBER | I43: FINALIZADO | J43: SIM | K43: ADILSON | M43: 1760 | N43: 2400 | O43: 50000 | P43: 0.0003 | Q43: =O43*P43 -> 15 | R43: 0.12 | S43: =R43*N43 -> 288 | T43: 0 | U43: 1 | V43: =T43*N43 -> 0 | W43: 0.065 | X43: =N43*W43 -> 156 | Y43: =Z43*0.00133 -> 0.01995 | Z43: 15 | AA43: =R43+T43+W43+Y43 -> 0.20495 | AB43: =N43*AA43+AK43 -> 512.28 | AC43: 0 | AD43: 200 | AE43: =17.5 -> 17.5 | AF43: =N43-M43-Q43-AB43-AD43-AE43 -> -104.78 | AG43: =AF43/N43 -> -0.043658333 | AH43: =N43-AB43-AI43 -> 1839.84 | AI43: =Y43*N43 -> 47.88 | AJ43: 0.0085 | AK43: =AJ43*N43 -> 20.4
A44: 46097 | B44: 122 | D44: GUARULHOS | E44: SP | F44: DIADEMA | G44: SP | H44: CYA RUBBER | I44: FINALIZADO | J44: SIM | K44: LEONIDAS CARNEIRO | M44: 1010 | N44: 1630 | O44: 50000 | P44: 0.0003 | Q44: =O44*P44 -> 15 | R44: 0.12 | S44: =R44*N44 -> 195.6 | T44: 0 | U44: 1 | V44: =T44*N44 -> 0 | W44: 0.065 | X44: =N44*W44 -> 105.95 | Y44: =Z44*0.00133 -> 0.01995 | Z44: 15 | AA44: =R44+T44+W44+Y44 -> 0.20495 | AB44: =N44*AA44+AK44 -> 347.9235 | AC44: 0.13 | AD44: =(N44-M44)*AC44 -> 80.6 | AE44: =17.5 -> 17.5 | AF44: =N44-M44-Q44-AB44-AD44-AE44 -> 158.9765 | AG44: =AF44/N44 -> 0.097531595 | AH44: =N44-AB44-AI44 -> 1249.558 | AI44: =Y44*N44 -> 32.5185 | AJ44: 0.0085 | AK44: =AJ44*N44 -> 13.855
A45: 46098 | B45: 208 - 210 - 211 - 212 - 213 - 214 | D45: GOIANIA | E45: GO | F45: MARABA | G45: PA | H45: UNIFORT | I45: FINALIZADO | J45: SIM | K45: CLOVIS MACIEL | M45: 6460 | N45: 11600 | O45: 150000 | P45: 0.0003 | Q45: =O45*P45 -> 45 | R45: 0.03 | S45: =R45*N45 -> 348 | T45: 0.035 | U45: 1 | V45: =T45*N45 -> 406 | W45: 0.065 | X45: =N45*W45 -> 754 | Y45: =Z45*0.00133 -> 0.01995 | Z45: 15 | AA45: =R45+T45+W45+Y45 -> 0.14995 | AB45: =N45*AA45+AK45 -> 1838.02 | AC45: 0.1 | AD45: =(N45-M45)*AC45 -> 514 | AE45: =17.5 -> 17.5 | AF45: =N45-M45-Q45-AB45-AD45-AE45 -> 2725.48 | AG45: =AF45/N45 -> 0.23495517 | AH45: =N45-AB45-AI45 -> 9530.56 | AI45: =Y45*N45 -> 231.42 | AJ45: 0.0085 | AK45: =AJ45*N45 -> 98.6
A46: 46098 | B46: 216-217-218-219 | D46: GOIANIA | E46: GO | F46: VARZEA GRANDE | G46: MT | H46: UNIFORT | I46: FINALIZADO | J46: SIM | K46: ANTONIO DE SOUZA E SILVA | M46: 5260 | N46: 8500 | O46: 150000 | P46: 0.0003 | Q46: =O46*P46 -> 45 | R46: 0.03 | S46: =R46*N46 -> 255 | T46: 0.035 | U46: 1 | V46: =T46*N46 -> 297.5 | W46: 0.065 | X46: =N46*W46 -> 552.5 | Y46: =Z46*0.00133 -> 0.01995 | Z46: 15 | AA46: =R46+T46+W46+Y46 -> 0.14995 | AB46: =N46*AA46+AK46 -> 1346.825 | AC46: 0.1 | AD46: =(N46-M46)*AC46 -> 324 | AE46: =17.5 -> 17.5 | AF46: =N46-M46-Q46-AB46-AD46-AE46 -> 1506.675 | AG46: =AF46/N46 -> 0.17725588 | AH46: =N46-AB46-AI46 -> 6983.6 | AI46: =Y46*N46 -> 169.575 | AJ46: 0.0085 | AK46: =AJ46*N46 -> 72.25
A47: 46098 | B47: 29177 | D47: ITAJAI | E47: SC | F47: BETIM | G47: MG | H47: UNIFORT | I47: FINALIZADO | J47: SIM | K47: NEGUEBA | M47: 9560 | N47: 12900 | O47: 400000 | P47: 0.0003 | Q47: =O47*P47 -> 120 | R47: 0.03 | S47: =R47*N47 -> 387 | T47: 0.035 | U47: 1 | V47: =T47*N47 -> 451.5 | W47: 0.065 | X47: =N47*W47 -> 838.5 | Y47: =Z47*0.00133 -> 0.01995 | Z47: 15 | AA47: =R47+T47+W47+Y47 -> 0.14995 | AB47: =N47*AA47+AK47 -> 2044.005 | AC47: 0.1497 | AD47: =(N47-M47)*AC47 -> 499.998 | AE47: =17.5 -> 17.5 | AF47: =N47-M47-Q47-AB47-AD47-AE47 -> 658.497 | AG47: =AF47/N47 -> 0.051046279 | AH47: =N47-AB47-AI47 -> 10598.64 | AI47: =Y47*N47 -> 257.355 | AJ47: 0.0085 | AK47: =AJ47*N47 -> 109.65
A48: 46099 | B48: 255 | D48: GUARULHOS | E48: SP | F48: BARUERI | G48: SP | H48: CYA RUBBER | I48: FINALIZADO | J48: SIM | K48: NATAN SANTOS | M48: 1010 | N48: 1630 | O48: 50000 | P48: 0.0003 | Q48: =O48*P48 -> 15 | R48: 0.12 | S48: =R48*N48 -> 195.6 | T48: 0 | U48: 1 | V48: =T48*N48 -> 0 | W48: 0.065 | X48: =N48*W48 -> 105.95 | Y48: =Z48*0.00133 -> 0.01995 | Z48: 15 | AA48: =R48+T48+W48+Y48 -> 0.20495 | AB48: =N48*AA48+AK48 -> 347.9235 | AC48: 0.07 | AD48: =(N48-M48)*AC48 -> 43.4 | AE48: =17.5 -> 17.5 | AF48: =N48-M48-Q48-AB48-AD48-AE48 -> 196.1765 | AG48: =AF48/N48 -> 0.12035368 | AH48: =N48-AB48-AI48 -> 1249.558 | AI48: =Y48*N48 -> 32.5185 | AJ48: 0.0085 | AK48: =AJ48*N48 -> 13.855
A49: 46099 | B49: 291 | D49: SAO LEOPOLDO | E49: RS | F49: NOVA PETROPOLIS | G49: RS | H49: CYA RUBBER | I49: FINALIZADO | J49: SIM | K49: VALNEI DANIEL | M49: 960 | N49: 1750 | O49: 50000 | P49: 0.0003 | Q49: =O49*P49 -> 15 | R49: 0 | S49: =R49*N49 -> 0 | T49: 0.035 | U49: 1 | V49: =T49*N49 -> 61.25 | W49: 0.065 | X49: =N49*W49 -> 113.75 | Y49: =Z49*0.00133 -> 0.01995 | Z49: 15 | AA49: =R49+T49+W49+Y49 -> 0.11995 | AB49: =N49*AA49+AK49 -> 224.7875 | AC49: 0.13 | AD49: =(N49-M49)*AC49 -> 102.7 | AE49: =17.5 -> 17.5 | AF49: =N49-M49-Q49-AB49-AD49-AE49 -> 430.0125 | AG49: =AF49/N49 -> 0.24572143 | AH49: =N49-AB49-AI49 -> 1490.3 | AI49: =Y49*N49 -> 34.9125 | AJ49: 0.0085 | AK49: =AJ49*N49 -> 14.875
A50: 46100 | B50: 303 | D50: GUARULHOS | E50: SP | F50: PINHALZINHO | G50: SP | H50: CYA RUBBER | I50: FINALIZADO | J50: SIM | K50: SILVIONEY BECKER | M50: 1060 | N50: 1830 | O50: 50000 | P50: 0.0003 | Q50: =O50*P50 -> 15 | R50: 0.12 | S50: =R50*N50 -> 219.6 | T50: 0 | U50: 1 | V50: =T50*N50 -> 0 | W50: 0.065 | X50: =N50*W50 -> 118.95 | Y50: =Z50*0.00133 -> 0.01995 | Z50: 15 | AA50: =R50+T50+W50+Y50 -> 0.20495 | AB50: =N50*AA50+AK51 -> 390.6135 | AC50: 0.08 | AD50: =(N50-M50)*AC50 -> 61.6 | AE50: =17.5 -> 17.5 | AF50: =N50-M50-Q50-AB50-AD50-AE50 -> 285.2865 | AG50: =AF50/N50 -> 0.15589426 | AH50: =#REF!-#REF!-AI50 -> #REF! | AI50: =#REF!*#REF! -> #REF! | AJ50: 0.0085 | AK50: =AJ50*#REF! -> #REF!
A51: 46100 | B51: 311 | D51: GUARULHOS | E51: SP | F51: DIADEMA | G51: SP | H51: CYA RUBBER | I51: FINALIZADO | J51: SIM | K51: EDINALDO DA SILVA | M51: 710 | N51: 1200 | O51: 30000 | P51: 0.0003 | Q51: =O51*P51 -> 9 | R51: 0.12 | S51: =R51*N51 -> 144 | T51: 0 | U51: 1 | V51: =T51*N51 -> 0 | W51: 0.065 | X51: =N51*W51 -> 78 | Y51: =Z51*0.00133 -> 0.01995 | Z51: 15 | AA51: =R51+T51+W51+Y51 -> 0.20495 | AB51: =N51*AA51+AK53 -> 256.14 | AC51: 0.05 | AD51: =(N51-M51)*AC51 -> 24.5 | AE51: =17.5 -> 17.5 | AF51: =N51-M51-Q51-AB51-AD51-AE51 -> 182.86 | AG51: =AF51/N51 -> 0.15238333 | AH51: =N50-AB50-AI51 -> 1402.878 | AI51: =Y50*N50 -> 36.5085 | AJ51: 0.0085 | AK51: =AJ51*N50 -> 15.555
A52: 46100 | B52: 297 | D52: SAO LEOPOLDO | E52: RS | F52: CAXIAS DO SUL | G52: RS | H52: CYA RUBBER | I52: FINALIZADO | J52: SIM | K52: RONALDO CERVELLIN | M52: 1360 | N52: 1840 | O52: 50000 | P52: 0.0003 | Q52: =O52*P52 -> 15 | R52: 0 | S52: =R52*N52 -> 0 | T52: 0.035 | U52: 1 | V52: =T52*N52 -> 64.4 | W52: 0.065 | X52: =N52*W52 -> 119.6 | Y52: =Z52*0.00133 -> 0.01995 | Z52: 15 | AA52: =R52+T52+W52+Y52 -> 0.11995 | AB52: =N52*AA52+AK52 -> 236.348 | AC52: 0.05 | AD52: =(N52-M52)*AC52 -> 24 | AE52: =17.5 -> 17.5 | AF52: =N52-M52-Q52-AB52-AD52-AE52 -> 187.152 | AG52: =AF52/N52 -> 0.10171304 | AH52: =N52-AB52-AI52 -> 1566.944 | AI52: =Y52*N52 -> 36.708 | AJ52: 0.0085 | AK52: =AJ52*N52 -> 15.64
A53: 46101 | B53: 351 | D53: GUARULHOS | E53: SP | F53: GUARAREMA | G53: SP | H53: CYA RUBBER | I53: FINALIZADO | J53: SIM | K53: AGNALDO | M53: 810 | N53: 1890 | O53: 50000 | P53: 0.0003 | Q53: =O53*P53 -> 15 | R53: 0.12 | S53: =R53*N53 -> 226.8 | T53: 0 | U53: 1 | V53: =T53*N53 -> 0 | W53: 0.065 | X53: =N53*W53 -> 122.85 | Y53: =Z53*0.00133 -> 0.01995 | Z53: 15 | AA53: =R53+T53+W53+Y53 -> 0.20495 | AB53: =N53*AA53+AK53 -> 397.5555 | AC53: 0.13 | AD53: =(N53-M53)*AC53 -> 140.4 | AE53: =17.5 -> 17.5 | AF53: =N53-M53-Q53-AB53-AD53-AE53 -> 509.5445 | AG53: =AF53/N53 -> 0.26960026 | AH53: =N51-AB51-AI53 -> 919.92 | AI53: =Y51*N51 -> 23.94 | AJ53: 0.0085 | AK53: =AJ53*N51 -> 10.2
A54: 46101 | B54: 397-398-399-400-401-402-403 | D54: BETIM | E54: MG | F54: GOIANIA | G54: GO | H54: UNIFORT | I54: FINALIZADO | J54: SIM | K54: NEGUEBA | M54: 8560 | N54: 13300 | O54: 300000 | P54: 0.0003 | Q54: =O54*P54 -> 90 | R54: 0.03 | S54: =R54*N54 -> 399 | T54: 0.035 | U54: 1 | V54: =T54*N54 -> 465.5 | W54: 0.065 | X54: =N54*W54 -> 864.5 | Y54: =Z54*0.00133 -> 0.01995 | Z54: 15 | AA54: =R54+T54+W54+Y54 -> 0.14995 | AB54: =N54*AA54+AK54 -> 2107.385 | AC54: 0.1 | AD54: =(N54-M54)*AC54 -> 474 | AE54: =17.5 -> 17.5 | AF54: =N54-M54-Q54-AB54-AD54-AE54 -> 2051.115 | AG54: =AF54/N54 -> 0.15421917 | AH54: =N54-AB54-AI54 -> 10927.28 | AI54: =Y54*N54 -> 265.335 | AJ54: 0.0085 | AK54: =AJ54*N54 -> 113.05
A55: 46101 | B55: 382 | D55: GUARULHOS | E55: SP | F55: SALTO | G55: SP | H55: CYA RUBBER | I55: FINALIZADO | J55: SIM | K55: FERNANDO LELI | M55: =1164.75+60 -> 1224.75 | N55: 2180 | O55: 50000 | P55: 0.0003 | Q55: =O55*P55 -> 15 | R55: 0.12 | S55: =R55*N55 -> 261.6 | T55: 0 | U55: 1 | V55: =T55*N55 -> 0 | W55: 0.065 | X55: =N55*W55 -> 141.7 | Y55: =Z55*0.00133 -> 0.01995 | Z55: 15 | AA55: =R55+T55+W55+Y55 -> 0.20495 | AB55: =N55*AA55+AK55 -> 465.321 | AC55: 0.12 | AD55: =(N55-M55)*AC55 -> 114.63 | AE55: =17.5 -> 17.5 | AF55: =N55-M55-Q55-AB55-AD55-AE55 -> 342.799 | AG55: =AF55/N55 -> 0.15724725 | AH55: =N55-AB55-AI55 -> 1671.188 | AI55: =Y55*N55 -> 43.491 | AJ55: 0.0085 | AK55: =AJ55*N55 -> 18.53
A56: 46101 | B56: 383 | D56: ROCA SALES | E56: RS | F56: SAO LEOPOLDO | G56: RS | H56: QUISVI | I56: FINALIZADO | J56: SIM | K56: FLAVIO DA COSTA | M56: 1257.02 | N56: 2100 | O56: 50000 | P56: 0.0003 | Q56: =O56*P56 -> 15 | R56: 0 | S56: =R56*N56 -> 0 | T56: 0.035 | U56: 1 | V56: =T56*N56 -> 73.5 | W56: 0.065 | X56: =N56*W56 -> 136.5 | Y56: =Z56*0.00133 -> 0.01995 | Z56: 15 | AA56: =R56+T56+W56+Y56 -> 0.11995 | AB56: =N56*AA56+AK56 -> 269.745 | AC56: 0.13 | AD56: =(N56-M56)*AC56 -> 109.5874 | AE56: =17.5 -> 17.5 | AF56: =N56-M56-Q56-AB56-AD56-AE56 -> 431.1476 | AG56: =AF56/N56 -> 0.20530838 | AH56: =N56-AB56-AI56 -> 1788.36 | AI56: =Y56*N56 -> 41.895 | AJ56: 0.0085 | AK56: =AJ56*N56 -> 17.85
A57: 46101 | B57: 357 358 | D57: GUARULHOS | E57: SP | F57: DIADEMA | G57: SP | H57: CYA RUBBER | I57: FINALIZADO | J57: SIM | K57: EDMILSON DE SOUZA | M57: 1010 | N57: 1730 | O57: 50000 | P57: 0.0003 | Q57: =O57*P57 -> 15 | R57: 0.12 | S57: =R57*N57 -> 207.6 | T57: 0 | U57: 1 | V57: =T57*N57 -> 0 | W57: 0.065 | X57: =N57*W57 -> 112.45 | Y57: =Z57*0.00133 -> 0.01995 | Z57: 15 | AA57: =R57+T57+W57+Y57 -> 0.20495 | AB57: =N57*AA57+AK57 -> 369.2685 | AC57: 0.1 | AD57: =(N57-M57)*AC57 -> 72 | AE57: =17.5 -> 17.5 | AF57: =N57-M57-Q57-AB57-AD57-AE57 -> 246.2315 | AG57: =AF57/N57 -> 0.14233035 | AH57: =N57-AB57-AI57 -> 1326.218 | AI57: =Y57*N57 -> 34.5135 | AJ57: 0.0085 | AK57: =AJ57*N57 -> 14.705
A58: 46103 | B58: 422 423 424 425 426 427 | D58: GOIANIA | E58: GO | F58: MARABA | G58: PA | H58: UNIFORT | I58: FINALIZADO | J58: SIM | K58: CRISTIANO GILMAR | M58: 9260 | N58: 14300 | O58: 150000 | P58: 0.0003 | Q58: =O58*P58 -> 45 | R58: 0.03 | S58: =R58*N58 -> 429 | T58: 0.035 | U58: 1 | V58: =T58*N58 -> 500.5 | W58: 0.065 | X58: =N58*W58 -> 929.5 | Y58: =Z58*0.00133 -> 0.01995 | Z58: 15 | AA58: =R58+T58+W58+Y58 -> 0.14995 | AB58: =N58*AA58+AK58 -> 2265.835 | AC58: 0.1 | AD58: =(N58-M58)*AC58 -> 504 | AE58: =17.5 -> 17.5 | AF58: =N58-M58-Q58-AB58-AD58-AE58 -> 2207.665 | AG58: =AF58/N58 -> 0.15438217 | AH58: =N58-AB58-AI58 -> 11748.88 | AI58: =Y58*N58 -> 285.285 | AJ58: 0.0085 | AK58: =AJ58*N58 -> 121.55
A59: 46103 | B59: 418 420 421 419 | D59: GOIANIA | E59: GO | F59: VARZEA GRANDE | G59: MT | H59: UNIFORT | I59: FINALIZADO | J59: SIM | K59: ANTONIO DE SOUZA E SILVA | M59: 5260 | N59: 8500 | O59: 150000 | P59: 0.0003 | Q59: =O59*P59 -> 45 | R59: 0.03 | S59: =R59*N59 -> 255 | T59: 0.035 | U59: 1 | V59: =T59*N59 -> 297.5 | W59: 0.065 | X59: =N59*W59 -> 552.5 | Y59: =Z59*0.00133 -> 0.01995 | Z59: 15 | AA59: =R59+T59+W59+Y59 -> 0.14995 | AB59: =N59*AA59+AK59 -> 1346.825 | AC59: 0.1 | AD59: =(N59-M59)*AC59 -> 324 | AE59: =17.5 -> 17.5 | AF59: =N59-M59-Q59-AB59-AD59-AE59 -> 1506.675 | AG59: =AF59/N59 -> 0.17725588 | AH59: =N59-AB59-AI59 -> 6983.6 | AI59: =Y59*N59 -> 169.575 | AJ59: 0.0085 | AK59: =AJ59*N59 -> 72.25
A60: 46104 | B60: 451 | D60: SANTO ANDRE | E60: SP | F60: CURITIBA | G60: PR | H60: ACTOS | I60: FINALIZADO | J60: SIM | K60: SIDNEY PIRIN BILL | M60: 3860 | N60: 5200 | O60: 150000 | P60: 0.0003 | Q60: =O60*P60 -> 45 | R60: 0.12 | S60: =R60*N60 -> 624 | T60: 0 | U60: 1 | V60: =T60*N60 -> 0 | W60: 0.065 | X60: =N60*W60 -> 338 | Y60: =Z60*0.00133 -> 0.01995 | Z60: 15 | AA60: =R60+T60+W60+Y60 -> 0.20495 | AB60: =N60*AA60+AK60 -> 1109.94 | AC60: 0 | AD60: =(N60-M60)*AC60 -> 0 | AE60: =17.5 -> 17.5 | AF60: =N60-M60-Q60-AB60-AD60-AE60 -> 167.56 | AG60: =AF60/N60 -> 0.032223077 | AH60: =N60-AB60-AI60 -> 3986.32 | AI60: =Y60*N60 -> 103.74 | AJ60: 0.0085 | AK60: =AJ60*N60 -> 44.2
A61: 46104 | B61: 444 | D61: GOIANIA | E61: GO | F61: BRASILIA | G61: DF | H61: ACTOS | I61: FINALIZADO | J61: SIM | K61: CLENILSON JOSE DA SILVA | M61: 1960 | N61: 3300 | O61: 100000 | P61: 0.0003 | Q61: =O61*P61 -> 30 | R61: 0.12 | S61: =R61*N61 -> 396 | T61: 0 | U61: 1 | V61: =T61*N61 -> 0 | W61: 0.065 | X61: =N61*W61 -> 214.5 | Y61: =Z61*0.00133 -> 0.01995 | Z61: 15 | AA61: =R61+T61+W61+Y61 -> 0.20495 | AB61: =N61*AA61+AK61 -> 704.385 | AC61: 0.07 | AD61: =(N61-M61)*AC61 -> 93.8 | AE61: =17.5 -> 17.5 | AF61: =N61-M61-Q61-AB61-AD61-AE61 -> 494.315 | AG61: =AF61/N61 -> 0.14979242 | AH61: =N61-AB61-AI61 -> 2529.78 | AI61: =Y61*N61 -> 65.835 | AJ61: 0.0085 | AK61: =AJ61*N61 -> 28.05
A62: 46104 | B62: 432 | D62: GUARULHOS | E62: SP | F62: SAO PAULO | G62: SP | H62: CYA RUBBER | I62: FINALIZADO | J62: SIM | K62: EDMILSON DE SOUZ | M62: 860 | N62: 1380 | O62: 30000 | P62: 0.0003 | Q62: =O62*P62 -> 9 | R62: 0.12 | S62: =R62*N62 -> 165.6 | T62: 0 | U62: 1 | V62: =T62*N62 -> 0 | W62: 0.065 | X62: =N62*W62 -> 89.7 | Y62: =Z62*0.00133 -> 0.01995 | Z62: 15 | AA62: =R62+T62+W62+Y62 -> 0.20495 | AB62: =N62*AA62+AK62 -> 294.561 | AC62: 0.07 | AD62: =(N62-M62)*AC62 -> 36.4 | AE62: =17.5 -> 17.5 | AF62: =N62-M62-Q62-AB62-AD62-AE62 -> 162.539 | AG62: =AF62/N62 -> 0.11778188 | AH62: =N62-AB62-AI62 -> 1057.908 | AI62: =Y62*N62 -> 27.531 | AJ62: 0.0085 | AK62: =AJ62*N62 -> 11.73
A63: 46105 | B63: 485 | D63: ROCA SALES | E63: RS | F63: NOVA PRATA | G63: RS | H63: QUISVI | I63: FINALIZADO | J63: SIM | K63: DORIVAL ALMEIDA DE MORAES | M63: 1260 | N63: 2400 | O63: 80000 | P63: 0.0003 | Q63: =O63*P63 -> 24 | R63: 0 | S63: =R63*N63 -> 0 | T63: 0 | U63: 1 | V63: =T63*N63 -> 0 | W63: 0.065 | X63: =N63*W63 -> 156 | Y63: =Z63*0.00133 -> 0.01995 | Z63: 15 | AA63: =R63+T63+W63+Y63 -> 0.08495 | AB63: =N63*AA63+AK63 -> 224.28 | AC63: 0.13 | AD63: =(N63-M63)*AC63 -> 148.2 | AE63: =17.5 -> 17.5 | AF63: =N63-M63-Q63-AB63-AD63-AE63 -> 726.02 | AG63: =AF63/N63 -> 0.30250833 | AH63: =N63-AB63-AI63 -> 2127.84 | AI63: =Y63*N63 -> 47.88 | AJ63: 0.0085 | AK63: =AJ63*N63 -> 20.4
A64: 46105 | B64: 496 | D64: SAO LEOPOLDO | E64: RS | F64: CAXIAS DO SUL | G64: RS | H64: CYA RUBBER | I64: FINALIZADO | J64: SIM | K64: NILDO DE SOUSA COELHO | M64: 1560 | N64: 3100 | O64: 257009.39 | P64: 0.0003 | Q64: =O64*P64 -> 77.102817 | R64: 0 | S64: =R64*N64 -> 0 | T64: 0 | U64: 1 | V64: =T64*N64 -> 0 | W64: 0.065 | X64: =N64*W64 -> 201.5 | Y64: =Z64*0.00133 -> 0.01995 | Z64: 15 | AA64: =R64+T64+W64+Y64 -> 0.08495 | AB64: =N64*AA64+AK64 -> 289.695 | AC64: 0.13 | AD64: =(N64-M64)*AC64 -> 200.2 | AE64: =17.5 -> 17.5 | AF64: =N64-M64-Q64-AB64-AD64-AE64 -> 955.50218 | AG64: =AF64/N64 -> 0.30822651 | AH64: =N64-AB64-AI64 -> 2748.46 | AI64: =Y64*N64 -> 61.845 | AJ64: 0.0085 | AK64: =AJ64*N64 -> 26.35
A65: 46106 | B65: 523 | D65: GUARULHOS | E65: SP | F65: GUARULHOS | G65: SP | H65: CYA RUBBER | I65: FINALIZADO | J65: SIM | K65: FRANCISCO JOSE | M65: 460 | N65: 850 | O65: 30300 | P65: 0.0003 | Q65: =O65*P65 -> 9.09 | R65: 0.12 | S65: =R65*N65 -> 102 | T65: 0 | U65: 1 | V65: =T65*N65 -> 0 | W65: 0.065 | X65: =N65*W65 -> 55.25 | Y65: =Z65*0.00133 -> 0.01995 | Z65: 15 | AA65: =R65+T65+W65+Y65 -> 0.20495 | AB65: =N65*AA65+AK65 -> 181.4325 | AC65: 0.13 | AD65: =(N65-M65)*AC65 -> 50.7 | AE65: =17.5 -> 17.5 | AF65: =N65-M65-Q65-AB65-AD65-AE65 -> 131.2775 | AG65: =AF65/N65 -> 0.15444412 | AH65: =N65-AB65-AI65 -> 651.61 | AI65: =Y65*N65 -> 16.9575 | AJ65: 0.0085 | AK65: =AJ65*N65 -> 7.225
A66: 46106 | B66: 524 | D66: GUARULHOS | E66: SP | F66: DIADEMA | G66: SP | H66: CYA RUBBER | I66: FINALIZADO | J66: SIM | K66: EDI LAZARO GONCALVES DE PINA | M66: 860 | N66: 1630 | O66: 59940 | P66: 0.0003 | Q66: =O66*P66 -> 17.982 | R66: 0.12 | S66: =R66*N66 -> 195.6 | T66: 0 | U66: 1 | V66: =T66*N66 -> 0 | W66: 0.065 | X66: =N66*W66 -> 105.95 | Y66: =Z66*0.00133 -> 0.01995 | Z66: 15 | AA66: =R66+T66+W66+Y66 -> 0.20495 | AB66: =N66*AA66+AK66 -> 347.9235 | AC66: 0.13 | AD66: =(N66-M66)*AC66 -> 100.1 | AE66: =17.5 -> 17.5 | AF66: =N66-M66-Q66-AB66-AD66-AE66 -> 286.4945 | AG66: =AF66/N66 -> 0.1757635 | AH66: =N66-AB66-AI66 -> 1249.558 | AI66: =Y66*N66 -> 32.5185 | AJ66: 0.0085 | AK66: =AJ66*N66 -> 13.855
A67: 46106 | B67: 527 | D67: SAO LEOPOLDO | E67: RS | F67: NOVA PETROPOLIS | G67: RS | H67: CYA RUBBER | I67: FINALIZADO | J67: SIM | K67: RONALDO CERVELLIN | M67: 1060 | N67: 1750 | O67: 61628.2 | P67: 0.0003 | Q67: =O67*P67 -> 18.48846 | R67: 0 | S67: =R67*N67 -> 0 | T67: 0 | U67: 1 | V67: =T67*N67 -> 0 | W67: 0.065 | X67: =N67*W67 -> 113.75 | Y67: =Z67*0.00133 -> 0.01995 | Z67: 15 | AA67: =R67+T67+W67+Y67 -> 0.08495 | AB67: =N67*AA67+AK67 -> 163.5375 | AC67: 0.13 | AD67: =(N67-M67)*AC67 -> 89.7 | AE67: =17.5 -> 17.5 | AF67: =N67-M67-Q67-AB67-AD67-AE67 -> 400.77404 | AG67: =AF67/N67 -> 0.22901374 | AH67: =N67-AB67-AI67 -> 1551.55 | AI67: =Y67*N67 -> 34.9125 | AJ67: 0.0085 | AK67: =AJ67*N67 -> 14.875
A68: 46106 | B68: 568 | D68: GUARULHOS | E68: SP | F68: SALTO | G68: SP | H68: CYA RUBBER | I68: FINALIZADO | J68: SIM | K68: ALMIR FERREIRA DE MENDONCA | M68: 1260 | N68: 2200 | O68: 80000 | P68: 0.0003 | Q68: =O68*P68 -> 24 | R68: 0.12 | S68: =R68*N68 -> 264 | T68: 0 | U68: 1 | V68: =T68*N68 -> 0 | W68: 0.065 | X68: =N68*W68 -> 143 | Y68: =Z68*0.00133 -> 0.01995 | Z68: 15 | AA68: =R68+T68+W68+Y68 -> 0.20495 | AB68: =N68*AA68+AK68 -> 469.59 | AC68: 0.1 | AD68: =(N68-M68)*AC68 -> 94 | AE68: =17.5 -> 17.5 | AF68: =N68-M68-Q68-AB68-AD68-AE68 -> 334.91 | AG68: =AF68/N68 -> 0.15223182 | AH68: =N68-AB68-AI68 -> 1686.52 | AI68: =Y68*N68 -> 43.89 | AJ68: 0.0085 | AK68: =AJ68*N68 -> 18.7
A69: 46107 | B69: 625-626-626-627-628-629-630 | D69: GOIANIA | E69: GO | F69: MARABA | G69: PA | H69: UNIFORT | I69: ANDAMENTO | J69: SIM | K69: WELLINGTON DIVINO | M69: 9060 | N69: 13900 | O69: 150000 | P69: 0.0003 | Q69: =O69*P69 -> 45 | R69: 0.03 | S69: =R69*N69 -> 417 | T69: 0.035 | U69: 1 | V69: =T69*N69 -> 486.5 | W69: 0.065 | X69: =N69*W69 -> 903.5 | Y69: =Z69*0.00133 -> 0.01995 | Z69: 15 | AA69: =R69+T69+W69+Y69 -> 0.14995 | AB69: =N69*AA69+AK69 -> 2202.455 | AC69: 0.1 | AD69: =(N69-M69)*AC69 -> 484 | AE69: =17.5 -> 17.5 | AF69: =N69-M69-Q69-AB69-AD69-AE69 -> 2091.045 | AG69: =AF69/N69 -> 0.15043489 | AH69: =N69-AB69-AI69 -> 11420.24 | AI69: =Y69*N69 -> 277.305 | AJ69: 0.0085 | AK69: =AJ69*N69 -> 118.15
A70: 46107 | B70: 620 621 622 623 | D70: GOIANIA | E70: GO | F70: VARZEA GRANDE | G70: MT | H70: UNIFORT | I70: FINALIZADO | J70: SIM | K70: ANTONIO DE SOUZA E SILVA | M70: 5260 | N70: 8500 | O70: 150000 | P70: 0.0003 | Q70: =O70*P70 -> 45 | R70: 0.03 | S70: =R70*N70 -> 255 | T70: 0.035 | U70: 1 | V70: =T70*N70 -> 297.5 | W70: 0.065 | X70: =N70*W70 -> 552.5 | Y70: =Z70*0.00133 -> 0.01995 | Z70: 15 | AA70: =R70+T70+W70+Y70 -> 0.14995 | AB70: =N70*AA70+AK70 -> 1346.825 | AC70: 0.1 | AD70: =(N70-M70)*AC70 -> 324 | AE70: =17.5 -> 17.5 | AF70: =N70-M70-Q70-AB70-AD70-AE70 -> 1506.675 | AG70: =AF70/N70 -> 0.17725588 | AH70: =N70-AB70-AI70 -> 6983.6 | AI70: =Y70*N70 -> 169.575 | AJ70: 0.0085 | AK70: =AJ70*N70 -> 72.25
A71: 46107 | B71: 585 | D71: GUARULHOS | E71: SP | F71: SAO JOSE DOS CAMPOS | G71: SP | H71: CYA RUBBER | I71: FINALIZADO | J71: SIM | K71: GABRIEL REIS ALBANO | M71: 860 | N71: 1630 | O71: 50000 | P71: 0.0003 | Q71: =O71*P71 -> 15 | R71: 0.12 | S71: =R71*N71 -> 195.6 | T71: 0 | U71: 1 | V71: =T71*N71 -> 0 | W71: 0.065 | X71: =N71*W71 -> 105.95 | Y71: =Z71*0.00133 -> 0.01995 | Z71: 15 | AA71: =R71+T71+W71+Y71 -> 0.20495 | AB71: =N71*AA71+AK71 -> 347.9235 | AC71: 0.13 | AD71: =(N71-M71)*AC71 -> 100.1 | AE71: =17.5 -> 17.5 | AF71: =N71-M71-Q71-AB71-AD71-AE71 -> 289.4765 | AG71: =AF71/N71 -> 0.17759294 | AH71: =N71-AB71-AI71 -> 1249.558 | AI71: =Y71*N71 -> 32.5185 | AJ71: 0.0085 | AK71: =AJ71*N71 -> 13.855
A72: 46108 | B72: 654 | D72: ROCA SALES | E72: RS | F72: SAO LEOPOLDO | G72: RS | H72: QUISVI | I72: FINALIZADO | J72: SIM | K72: EMERSON FELIPE | M72: 1360 | N72: 2100 | O72: 50000 | P72: 0.0003 | Q72: =O72*P72 -> 15 | R72: 0 | S72: =R72*N72 -> 0 | T72: 0 | U72: 1 | V72: =T72*N72 -> 0 | W72: 0.065 | X72: =N72*W72 -> 136.5 | Y72: =Z72*0.00133 -> 0.01995 | Z72: 15 | AA72: =R72+T72+W72+Y72 -> 0.08495 | AB72: =N72*AA72+AK72 -> 196.245 | AC72: 0.13 | AD72: =(N72-M72)*AC72 -> 96.2 | AE72: =17.5 -> 17.5 | AF72: =N72-M72-Q72-AB72-AD72-AE72 -> 415.055 | AG72: =AF72/N72 -> 0.19764524 | AH72: =N72-AB72-AI72 -> 1861.86 | AI72: =Y72*N72 -> 41.895 | AJ72: 0.0085 | AK72: =AJ72*N72 -> 17.85
A73: 46108 | B73: 693 | D73: SÃO LEOPOLDO | E73: RS | F73: CAXIAS DO SUL | G73: RS | H73: CYA RUBBER | I73: FINALIZADO | J73: SIM | K73: EMERSON FELIPE | M73: 1110 | N73: 1840 | O73: 80000 | P73: 0.0003 | Q73: =O73*P73 -> 24 | R73: 0 | S73: =R73*N73 -> 0 | T73: 0 | U73: 1 | V73: =T73*N73 -> 0 | W73: 0.065 | X73: =N73*W73 -> 119.6 | Y73: =Z73*0.00133 -> 0.01995 | Z73: 15 | AA73: =R73+T73+W73+Y73 -> 0.08495 | AB73: =N73*AA73+AK73 -> 171.948 | AC73: 0.13 | AD73: =(N73-M73)*AC73 -> 94.9 | AE73: =17.5 -> 17.5 | AF73: =N73-M73-Q73-AB73-AD73-AE73 -> 421.652 | AG73: =AF73/N73 -> 0.2291587 | AH73: =N73-AB73-AI73 -> 1631.344 | AI73: =Y73*N73 -> 36.708 | AJ73: 0.0085 | AK73: =AJ73*N73 -> 15.64
A74: 46109 | B74: 697 - 698 - 699 - 700 - 701 - 702 | D74: GOIANIA | E74: GO | F74: MARABA | G74: PA | H74: UNIFORT | I74: FINALIZADO | J74: SIM | K74: RUBENS PEREIRA | M74: 7410 | N74: 11900 | O74: 150000 | P74: 0.0003 | Q74: =O74*P74 -> 45 | R74: 0.03 | S74: =R74*N74 -> 357 | T74: 0.035 | U74: 1 | V74: =T74*N74 -> 416.5 | W74: 0.065 | X74: =N74*W74 -> 773.5 | Y74: =Z74*0.00133 -> 0.01995 | Z74: 15 | AA74: =R74+T74+W74+Y74 -> 0.14995 | AB74: =N74*AA74+AK74 -> 1885.555 | AC74: 0.1 | AD74: =(N74-M74)*AC74 -> 449 | AE74: =17.5 -> 17.5 | AF74: =N74-M74-Q74-AB74-AD74-AE74 -> 2092.945 | AG74: =AF74/N74 -> 0.17587773 | AH74: =N74-AB74-AI74 -> 9777.04 | AI74: =Y74*N74 -> 237.405 | AJ74: 0.0085 | AK74: =AJ74*N74 -> 101.15
A75: 46109 | B75: 703 - 704 - 705 - 706 | D75: GOIANIA | E75: GO | F75: VARZEA GRANDE | G75: MT | H75: UNIFORT | I75: FINALIZADO | J75: SIM | K75: ALINE KEMPFER | M75: 5260 | N75: 8500 | O75: 150000 | P75: 0.0003 | Q75: =O75*P75 -> 45 | R75: 0.03 | S75: =R75*N75 -> 255 | T75: 0.035 | U75: 1 | V75: =T75*N75 -> 297.5 | W75: 0.065 | X75: =N75*W75 -> 552.5 | Y75: =Z75*0.00133 -> 0.01995 | Z75: 15 | AA75: =R75+T75+W75+Y75 -> 0.14995 | AB75: =N75*AA75+AK75 -> 1346.825 | AC75: 0.1 | AD75: =(N75-M75)*AC75 -> 324 | AE75: =17.5 -> 17.5 | AF75: =N75-M75-Q75-AB75-AD75-AE75 -> 1506.675 | AG75: =AF75/N75 -> 0.17725588 | AH75: =N75-AB75-AI75 -> 6983.6 | AI75: =Y75*N75 -> 169.575 | AJ75: 0.0085 | AK75: =AJ75*N75 -> 72.25
A76: 46109 | B76: 29304 | D76: SANTO ANDRE | E76: SP | F76: PORTO ALEGRE | G76: RS | H76: ACTOS | I76: FINALIZADO | J76: SIM | K76: ROBISON GONÇALVES | M76: 10060 | N76: 12400 | O76: 300000 | P76: 0.0003 | Q76: =O76*P76 -> 90 | R76: 0.12 | S76: =R76*N76 -> 1488 | T76: 0 | U76: 1 | V76: =T76*N76 -> 0 | W76: 0.065 | X76: =N76*W76 -> 806 | Y76: =Z76*0.00133 -> 0.01995 | Z76: 15 | AA76: =R76+T76+W76+Y76 -> 0.20495 | AB76: =N76*AA76+AK76 -> 2646.78 | AC76: 0 | AD76: 400 | AE76: =17.5 -> 17.5 | AF76: =N76-M76-Q76-AB76-AD76-AE76 -> -814.28 | AG76: =AF76/N76 -> -0.065667742 | AH76: =N76-AB76-AI76 -> 9505.84 | AI76: =Y76*N76 -> 247.38 | AJ76: 0.0085 | AK76: =AJ76*N76 -> 105.4
A77: 46110 | B77: 708 | D77: BARRA DO PIRAI | E77: RJ | F77: SAO LEOPOLDO | G77: RS | H77: CYA RUBBER | I77: FINALIZADO | J77: SIM | K77: VALDIR HENRIQUE | M77: 11260 | N77: 15900 | O77: 50000 | P77: 0.0003 | Q77: =O77*P77 -> 15 | R77: 0.12 | S77: =R77*N77 -> 1908 | T77: 0 | U77: 1 | V77: =T77*N77 -> 0 | W77: 0.065 | X77: =N77*W77 -> 1033.5 | Y77: =Z77*0.00133 -> 0.01995 | Z77: 15 | AA77: =R77+T77+W77+Y77 -> 0.20495 | AB77: =N77*AA77+AK77 -> 3393.855 | AC77: 0.02 | AD77: =(N77-M77)*AC77 -> 92.8 | AE77: =17.5 -> 17.5 | AF77: =N77-M77-Q77-AB77-AD77-AE77 -> 1120.845 | AG77: =AF77/N77 -> 0.070493396 | AH77: =N77-AB77-AI77 -> 12188.94 | AI77: =Y77*N77 -> 317.205 | AJ77: 0.0085 | AK77: =AJ77*N77 -> 135.15
A78: 46111 | B78: 728 | D78: SANTO ANDRE | E78: SP | F78: RIBEIRAO PRETO | G78: SP | H78: ACTOS | I78: FINALIZADO | J78: SIM | K78: ANDREI DOS SANTOS | M78: 4760 | N78: 5400 | O78: 200000 | P78: 0.0003 | Q78: =O78*P78 -> 60 | R78: 0.12 | S78: =R78*N78 -> 648 | T78: 0 | U78: 1 | V78: =T78*N78 -> 0 | W78: 0.065 | X78: =N78*W78 -> 351 | Y78: =Z78*0.00133 -> 0.01995 | Z78: 15 | AA78: =R78+T78+W78+Y78 -> 0.20495 | AB78: =N78*AA78+AK78 -> 1152.63 | AC78: 0 | AD78: =(N78-M78)*AC78 -> 0 | AE78: =17.5 -> 17.5 | AF78: =N78-M78-Q78-AB78-AD78-AE78 -> -590.13 | AG78: =AF78/N78 -> -0.10928333 | AH78: =N78-AB78-AI78 -> 4139.64 | AI78: =Y78*N78 -> 107.73 | AJ78: 0.0085 | AK78: =AJ78*N78 -> 45.9
A79: 46111 | B79: 750 | D79: ITAJAI | E79: SC | F79: BETIM | G79: MG | H79: UNIFORT | I79: FINALIZADO | J79: SIM | K79: DANIEL BETINELL | M79: 9160 | N79: 10900 | O79: 50000 | P79: 0.0003 | Q79: =O79*P79 -> 15 | R79: 0.03 | S79: =R79*N79 -> 327 | T79: 0.035 | U79: 1 | V79: =T79*N79 -> 381.5 | W79: 0.065 | X79: =N79*W79 -> 708.5 | Y79: =Z79*0.00133 -> 0.01995 | Z79: 15 | AA79: =R79+T79+W79+Y79 -> 0.14995 | AB79: =N79*AA79+AK79 -> 1727.105 | AC79: 0 | AD79: =(N79-M79)*AC79 -> 0 | AE79: =17.5 -> 17.5 | AF79: =N79-M79-Q79-AB79-AD79-AE79 -> -19.605 | AG79: =AF79/N79 -> -0.0017986239 | AH79: =N79-AB79-AI79 -> 8955.44 | AI79: =Y79*N79 -> 217.455 | AJ79: 0.0085 | AK79: =AJ79*N79 -> 92.65
A80: 46112 | B80: 762 | D80: GUARULHOS | E80: SP | F80: GUARULHOS | G80: SP | H80: CYA RUBBER | I80: FINALIZADO | J80: SIM | K80: GERALDO ALVES | M80: 460 | N80: 850 | O80: 20000 | P80: 0.0003 | Q80: =O80*P80 -> 6 | R80: 0.12 | S80: =R80*N80 -> 102 | T80: 0 | U80: 1 | V80: =T80*N80 -> 0 | W80: 0.065 | X80: =N80*W80 -> 55.25 | Y80: =Z80*0.00133 -> 0.01995 | Z80: 15 | AA80: =R80+T80+W80+Y80 -> 0.20495 | AB80: =N80*AA80+AK80 -> 181.4325 | AC80: 0.13 | AD80: =(N80-M80)*AC80 -> 50.7 | AE80: =17.5 -> 17.5 | AF80: =N80-M80-Q80-AB80-AD80-AE80 -> 134.3675 | AG80: =AF80/N80 -> 0.15807941 | AH80: =N80-AB80-AI80 -> 651.61 | AI80: =Y80*N80 -> 16.9575 | AJ80: 0.0085 | AK80: =AJ80*N80 -> 7.225
A81: 46112 | B81: 787 | D81: GUARULHOS | E81: SP | F81: PINHALZINHO | G81: SP | H81: CYA RUBBER | I81: FINALIZADO | J81: SIM | K81: JARBAS FAUSTINO | M81: 1260 | N81: 2000 | O81: 20000 | P81: 0.0003 | Q81: =O81*P81 -> 6 | R81: 0.12 | S81: =R81*N81 -> 240 | T81: 0 | U81: 1 | V81: =T81*N81 -> 0 | W81: 0.065 | X81: =N81*W81 -> 130 | Y81: =Z81*0.00133 -> 0.01995 | Z81: 15 | AA81: =R81+T81+W81+Y81 -> 0.20495 | AB81: =N81*AA81+AK81 -> 426.9 | AC81: 0.06 | AD81: =(N81-M81)*AC81 -> 44.4 | AE81: =17.5 -> 17.5 | AF81: =N81-M81-Q81-AB81-AD81-AE81 -> 245.2 | AG81: =AF81/N81 -> 0.1226 | AH81: =N81-AB81-AI81 -> 1533.2 | AI81: =Y81*N81 -> 39.9 | AJ81: 0.0085 | AK81: =AJ81*N81 -> 17
A82: 46112 | B82: 770 - 771 - 772 - 773 | D82: SANTO ANDRE | E82: SP | F82: BELO HORIZONTE | G82: MG | H82: ACTOS | I82: FINALIZADO | J82: SIM | K82: RAFAEL HENRIQUE | M82: 5760 | N82: 7600 | O82: 200000 | P82: 0.0003 | Q82: =O82*P82 -> 60 | R82: 0.12 | S82: =R82*N82 -> 912 | T82: 0 | U82: 1 | V82: =T82*N82 -> 0 | W82: 0.065 | X82: =N82*W82 -> 494 | Y82: =Z82*0.00133 -> 0.01995 | Z82: 15 | AA82: =R82+T82+W82+Y82 -> 0.20495 | AB82: =N82*AA82+AK82 -> 1622.22 | AC82: 0 | AD82: 0 | AE82: =17.5 -> 17.5 | AF82: =N82-M82-Q82-AB82-AD82-AE82 -> 140.28 | AG82: =AF82/N82 -> 0.018457895 | AH82: =N82-AB82-AI82 -> 5826.16 | AI82: =Y82*N82 -> 151.62 | AJ82: 0.0085 | AK82: =AJ82*N82 -> 64.6
A83: 46112 | B83: 760 | D83: GUARULHOS | E83: SP | F83: DIADEMA | G83: SP | H83: CYA RUBBER | I83: FINALIZADO | J83: SIM | K83: EDMILSON DE SOUZA | M83: 960 | N83: 1630 | O83: 50000 | P83: 0.0003 | Q83: =O83*P83 -> 15 | R83: 0.12 | S83: =R83*N83 -> 195.6 | T83: 0 | U83: 1 | V83: =T83*N83 -> 0 | W83: 0.065 | X83: =N83*W83 -> 105.95 | Y83: =Z83*0.00133 -> 0.01995 | Z83: 15 | AA83: =R83+T83+W83+Y83 -> 0.20495 | AB83: =N83*AA83+AK83 -> 347.9235 | AC83: 0.07 | AD83: =(N83-M83)*AC83 -> 46.9 | AE83: =17.5 -> 17.5 | AF83: =N83-M83-Q83-AB83-AD83-AE83 -> 242.6765 | AG83: =AF83/N83 -> 0.14888129 | AH83: =N83-AB83-AI83 -> 1249.558 | AI83: =Y83*N83 -> 32.5185 | AJ83: 0.0085 | AK83: =AJ83*N83 -> 13.855
A84: 46112 | B84: 799 | D84: GUARULHOS | E84: SP | F84: SALTO | G84: SP | H84: CYA RUBBER | I84: FINALIZADO | J84: SIM | K84: ELIANDRO JOSE | M84: 1010 | N84: 1690 | O84: 50000 | P84: 0.0003 | Q84: =O84*P84 -> 15 | R84: 0.12 | S84: =R84*N84 -> 202.8 | T84: 0 | U84: 1 | V84: =T84*N84 -> 0 | W84: 0.065 | X84: =N84*W84 -> 109.85 | Y84: =Z84*0.00133 -> 0.01995 | Z84: 15 | AA84: =R84+T84+W84+Y84 -> 0.20495 | AB84: =N84*AA84+AK84 -> 360.7305 | AC84: 0.07 | AD84: =(N84-M84)*AC84 -> 47.6 | AE84: =17.5 -> 17.5 | AF84: =N84-M84-Q84-AB84-AD84-AE84 -> 239.1695 | AG84: =AF84/N84 -> 0.14152041 | AH84: =N84-AB84-AI84 -> 1295.554 | AI84: =Y84*N84 -> 33.7155 | AJ84: 0.0085 | AK84: =AJ84*N84 -> 14.365
AF85: =SUM(AF3:AF84) -> 63721.242
D89: META | E89: REALIZADO | F89: COMISSÃO | G89: % REALIZADA | H89: CLIENTES | J89: DIA | K89: ATIVIDADES | M89: SEMANA 1 | N89: SEMANA 2 | O89: SEMANA 3 | P89: SEMANA 2 | Q89: SEMANA 3 | R89: SEMANA 4
D90: 250000 | E90: =SUMIF(H4:H84,H90,N4:N84) -> 303600 | F90: =SUMIF(H:H,H90,AD:AD) -> 10847.398 | G90: =E90/D90 -> 1.2144 | H90: UNIFORT | J90: SEGUNDA | K90: LIGAÇÃO | M90: 0 | N90: 0 | O90: 0 | R90: 4
D91: 15000 | E91: =SUMIF(H4:H84,H91,N4:N84) -> 10200 | F91: =SUMIF(H:H,H91,AD:AD) -> 605.4204 | G91: =E91/D91 -> 0.68 | H91: QUISVI | K91: CARREGAMENTO | M91: 6 | N91: 3 | O91: 4 | R91: 5
D92: 60000 | E92: =SUMIF(H4:H84,H92,N4:N84) -> 85530 | F92: =SUMIF(H:H,H92,AD:AD) -> 3430.8448 | G92: =E92/D92 -> 1.4255 | H92: CYA RUBBER | K92: PROSPECÇÃO | M92: 0 | N92: 0 | O92: 0 | R92: 0
D93: 15000 | E93: =SUMIF(H4:H84,H93,N4:N84) -> 41500 | F93: =SUMIF(H:H,H93,AD:AD) -> 793.8 | G93: =E93/D93 -> 2.7666667 | H93: ACTOS | J93: TERÇA | K93: LIGAÇÃO | M93: 3 | N93: 8 | O93: 5 | R93: 6
D94: 10000 | E94: =SUMIF(H4:H84,H94,N4:N84) -> 2500 | F94: =SUMIF(H:H,H94,AD:AD) -> 33.6 | G94: =E94/D94 -> 0.25 | H94: SCHEMAQ | K94: CARREGAMENTO | M94: 4 | N94: 4 | O94: 3 | R94: 2
D95: 10000 | E95: =SUMIF(H5:H85,H95,N5:N85) -> 1700 | F95: =SUMIF(H:H,H95,AD:AD) -> 102.7 | G95: =E95/D95 -> 0.17 | H95: SATAKE | K95: PROSPECÇÃO | M95: 0 | N95: 0 | O95: 0 | R95: 0
D96: 10000 | E96: =SUMIF(H6:H86,H96,N6:N86) -> 5500 | F96: =SUMIF(H:H,H96,AD:AD) -> 0 | G96: =E96/D96 -> 0.55 | H96: TOTALFLEX | J96: QUARTA | K96: LIGAÇÃO | M96: 11 | N96: 12 | O96: 5 | R96: 7
D97: =SUM(D90:D95) -> 360000 | E97: =SUM(E90:E96) -> 450530 | F97: =SUM(F86:F95) -> 15813.763 | G97: =AVERAGE(G90,G95) -> 0.6922 | H97: TOTAL | K97: CARREGAMENTO | M97: 1 | N97: 4 | O97: 2 | R97: 4
K98: PROSPECÇÃO | M98: 0 | N98: 0 | O98: 0 | R98: 0
J99: QUINTA | K99: LIGAÇÃO | M99: 5 | N99: 4 | O99: 3 | R99: 0
K100: CARREGAMENTO | M100: 1 | N100: 3 | O100: 3 | R100: 3
F101: DIAS ÚTEIS | G101: 2 | K101: PROSPECÇÃO | M101: 0 | N101: 0 | O101: 0 | R101: 0
D102: PARÂMETRO 100K | F102: META DIÁRIA | G102: =(G103-G105)/G101 -> -50265 | J102: SEXTA | K102: LIGAÇÃO | M102: 0 | N102: 2 | O102: 10 | R102: 9
D103: =E146*F145/E145 -> 3510.0356 | F103: META | G103: 350000 | K103: CARREGAMENTO | M103: 2 | N103: 4 | O103: 4 | R103: 2
F104: 100% META | G104: =G105/G103 -> 1.2872286 | K104: PROSPECÇÃO | M104: 5 | N104: 0 | O104: 0 | R104: 0
...

Sheet ABRIL - 2026
A1: GODI TRANSPORTES - UNINDO PROPÓSITOS
A3: DATA | B3: CTE | C3: MANIFESTO | D3: ORIGEM | E3: ESTADO | F3: DESTINO | G3: ESTADO | H3: CLIENTE | I3: PAGAMENTO | J3: CONFERENCIA | K3: MOTORISTA | L3: TELEFONE | M3: VALOR MOTORISTA | N3: VALOR EMPRESA | O3: NF | P3: SEGURO | Q3: SEGURO | R3: ICMS | S3: ICMS | T3: C.O | V3: CO | W3: IMPOSTO | X3: IMPOSTO | Y3: BOLETO | Z3: DIA PAG | AA3: TOTAL TAXAS | AB3: VALOR IMPOSTO | AC3: % | AD3: COMISSÕES | AE3: BOLETOS | AF3: LUCRO | AG3: RENTABIL | AH3: FRETE LIQ | AI3: MOVA | AJ3: ADQ TAB | AK3: VALOR
A4: 46113 | B4: 868 873 | D4: GUARULHOS | E4: SP | F4: SALTO | G4: SP | H4: CYA RUBBER | I4: FINALIZADO | J4: SIM | K4: RODRIGO LEITE | M4: 1160 | N4: 2500 | O4: 80000 | P4: 0.0003 | Q4: =O4*P4 -> 24 | R4: 0.12 | S4: =R4*N4 -> 300 | T4: 0 | U4: 1 | V4: =T4*N4 -> 0 | W4: 0.065 | X4: =N4*W4 -> 162.5 | Y4: =Z4*0.00133 -> 0.01995 | Z4: 15 | AA4: =R4+T4+W4+Y4 -> 0.20495 | AB4: =N4*AA4+AK4 -> 533.625 | AC4: 0.13 | AD4: =(N4-M4)*AC4 -> 174.2 | AE4: =17.5 -> 17.5 | AF4: =N4-M4-Q4-AB4-AD4-AE4 -> 590.675 | AG4: =AF4/N4 -> 0.23627 | AH4: =N4-AB4-AI4 -> 1916.5 | AI4: =Y4*N4 -> 49.875 | AJ4: 0.0085 | AK4: =AJ4*N4 -> 21.25
A5: 46113 | B5: 841 | D5: GUARULHOS | E5: SP | F5: SAO PAULO | G5: SP | H5: CYA RUBBER | I5: FINALIZADO | J5: SIM | K5: EDMILSON DE SOUZA | M5: 860 | N5: 1450 | O5: 30000 | P5: 0.0003 | Q5: =O5*P5 -> 9 | R5: 0.12 | S5: =R5*N5 -> 174 | T5: 0 | U5: 1 | V5: =T5*N5 -> 0 | W5: 0.065 | X5: =N5*W5 -> 94.25 | Y5: =Z5*0.00133 -> 0.01995 | Z5: 15 | AA5: =R5+T5+W5+Y5 -> 0.20495 | AB5: =N5*AA5+AK5 -> 309.5025 | AC5: 0.07 | AD5: =(N5-M5)*AC5 -> 41.3 | AE5: =17.5 -> 17.5 | AF5: =N5-M5-Q5-AB5-AD5-AE5 -> 212.6975 | AG5: =AF5/N5 -> 0.14668793 | AH5: =N5-AB5-AI5 -> 1111.57 | AI5: =Y5*N5 -> 28.9275 | AJ5: 0.0085 | AK5: =AJ5*N5 -> 12.325
A6: 46113 | B6: 857 | D6: GUARULHOS | E6: SP | F6: SAO PAULO | G6: SP | H6: CYA RUBBER | I6: FINALIZADO | J6: SIM | K6: VALDEMIR DA SILVA | M6: 660 | N6: 1130 | O6: 30000 | P6: 0.0003 | Q6: =O6*P6 -> 9 | R6: 0.12 | S6: =R6*N6 -> 135.6 | T6: 0 | U6: 1 | V6: =T6*N6 -> 0 | W6: 0.065 | X6: =N6*W6 -> 73.45 | Y6: =Z6*0.00133 -> 0.01995 | Z6: 15 | AA6: =R6+T6+W6+Y6 -> 0.20495 | AB6: =N6*AA6+AK6 -> 241.1985 | AC6: 0.07 | AD6: =(N6-M6)*AC6 -> 32.9 | AE6: =17.5 -> 17.5 | AF6: =N6-M6-Q6-AB6-AD6-AE6 -> 169.4015 | AG6: =AF6/N6 -> 0.14991283 | AH6: =N6-AB6-AI6 -> 866.258 | AI6: =Y6*N6 -> 22.5435 | AJ6: 0.0085 | AK6: =AJ6*N6 -> 9.605
A7: 46113 | B7: 855 | D7: ROCA SALES | E7: RS | F7: SAO LEOPOLDO | G7: RS | H7: QUISVI | I7: FINALIZADO | J7: SIM | K7: CARLOS ALEXANDRE | M7: 1255 | N7: 2250 | O7: 60000 | P7: 0.0003 | Q7: =O7*P7 -> 18 | R7: 0 | S7: =R7*N7 -> 0 | T7: 0 | U7: 1 | V7: =T7*N7 -> 0 | W7: 0.065 | X7: =N7*W7 -> 146.25 | Y7: =Z7*0.00133 -> 0.01995 | Z7: 15 | AA7: =R7+T7+W7+Y7 -> 0.08495 | AB7: =N7*AA7+AK7 -> 210.2625 | AC7: 0.13 | AD7: =(N7-M7)*AC7 -> 129.35 | AE7: =17.5 -> 17.5 | AF7: =N7-M7-Q7-AB7-AD7-AE7 -> 619.8875 | AG7: =AF7/N7 -> 0.27550556 | AH7: =N7-AB7-AI7 -> 1994.85 | AI7: =Y7*N7 -> 44.8875 | AJ7: 0.0085 | AK7: =AJ7*N7 -> 19.125
A8: 46113 | B8: 869 | D8: JOINVILLE | E8: SC | F8: ITU | G8: SP | H8: SATAKE | I8: FINALIZADO | J8: SIM | K8: ROBERTO KRUGER | M8: 1060 | N8: 1900 | O8: 50000 | P8: 0.0003 | Q8: =O8*P8 -> 15 | R8: 0.12 | S8: =R8*N8 -> 228 | T8: 0 | U8: 1 | V8: =T8*N8 -> 0 | W8: 0.065 | X8: =N8*W8 -> 123.5 | Y8: =Z8*0.00133 -> 0.01995 | Z8: 15 | AA8: =R8+T8+W8+Y8 -> 0.20495 | AB8: =N8*AA8+AK8 -> 405.555 | AC8: 0.13 | AD8: =(N8-M8)*AC8 -> 109.2 | AE8: =17.5 -> 17.5 | AF8: =N8-M8-Q8-AB8-AD8-AE8 -> 292.745 | AG8: =AF8/N8 -> 0.15407632 | AH8: =N8-AB8-AI8 -> 1456.54 | AI8: =Y8*N8 -> 37.905 | AJ8: 0.0085 | AK8: =AJ8*N8 -> 16.15
A9: 46114 | B9: 927 - 928 - 929 - 930 - 931 - 932 - | D9: GOIANIA | E9: GO | F9: MARABA | G9: PA | H9: UNIFORT | I9: FINALIZADO | J9: SIM | K9: FREDSON | M9: 7060 | N9: 11500 | O9: 100000 | P9: 0.0003 | Q9: =O9*P9 -> 30 | R9: 0.03 | S9: =R9*N9 -> 345 | T9: 0.035 | U9: 1 | V9: =T9*N9 -> 402.5 | W9: 0.065 | X9: =N9*W9 -> 747.5 | Y9: =Z9*0.00133 -> 0.01995 | Z9: 15 | AA9: =R9+T9+W9+Y9 -> 0.14995 | AB9: =N9*AA9+AK9 -> 1822.175 | AC9: 0.1 | AD9: =(N9-M9)*AC9 -> 444 | AE9: =17.5 -> 17.5 | AF9: =N9-M9-Q9-AB9-AD9-AE9 -> 2126.325 | AG9: =AF9/N9 -> 0.18489783 | AH9: =N9-AB9-AI9 -> 9448.4 | AI9: =Y9*N9 -> 229.425 | AJ9: 0.0085 | AK9: =AJ9*N9 -> 97.75
A10: 46114 | B10: 897 | D10: GUARULHOS | E10: SP | F10: DIADEMA | G10: SP | H10: CYA RUBBER | I10: FINALIZADO | J10: SIM | K10: EDIVALDO DA SILVA | M10: 810 | N10: 1490 | O10: 30000 | P10: 0.0003 | Q10: =O10*P10 -> 9 | R10: 0.12 | S10: =R10*N10 -> 178.8 | T10: 0 | U10: 1 | V10: =T10*N10 -> 0 | W10: 0.065 | X10: =N10*W10 -> 96.85 | Y10: =Z10*0.00133 -> 0.01995 | Z10: 15 | AA10: =R10+T10+W10+Y10 -> 0.20495 | AB10: =N10*AA10+AK10 -> 318.0405 | AC10: 0.13 | AD10: =(N10-M10)*AC10 -> 88.4 | AE10: =17.5 -> 17.5 | AF10: =N10-M10-Q10-AB10-AD10-AE10 -> 247.0595 | AG10: =AF10/N10 -> 0.16581175 | AH10: =N10-AB10-AI10 -> 1142.234 | AI10: =Y10*N10 -> 29.7255 | AJ10: 0.0085 | AK10: =AJ10*N10 -> 12.665
A11: 46114 | B11: 906-907-908-909 | D11: GOIANIA | E11: GO | F11: VARZEA GRANDE | G11: MT | H11: UNIFORT | I11: FINALIZADO | J11: SIM | K11: ANTONIO DE SOUZA | M11: 5060 | N11: 8500 | O11: 100000 | P11: 0.0003 | Q11: =O11*P11 -> 30 | R11: 0.03 | S11: =R11*N11 -> 255 | T11: 0.035 | U11: 1 | V11: =T11*N11 -> 297.5 | W11: 0.065 | X11: =N11*W11 -> 552.5 | Y11: =Z11*0.00133 -> 0.01995 | Z11: 15 | AA11: =R11+T11+W11+Y11 -> 0.14995 | AB11: =N11*AA11+AK11 -> 1346.825 | AC11: 0.1 | AD11: =(N11-M11)*AC11 -> 344 | AE11: =17.5 -> 17.5 | AF11: =N11-M11-Q11-AB11-AD11-AE11 -> 1701.675 | AG11: =AF11/N11 -> 0.20019706 | AH11: =N11-AB11-AI11 -> 6983.6 | AI11: =Y11*N11 -> 169.575 | AJ11: 0.0085 | AK11: =AJ11*N11 -> 72.25
A12: 46115 | B12: 949 | D12: SANTO ANDRE | E12: SP | F12: JABOATAO DOS GUARARAPES | G12: PE | H12: ACTOS | I12: FINALIZADO | J12: SIM | K12: JOAO MARCOS | M12: 21060 | N12: 26100 | O12: 270000 | P12: 0.0003 | Q12: =O12*P12 -> 81 | R12: 0.056 | S12: =R12*N12 -> 1461.6 | T12: 0.035 | U12: 1 | V12: =T12*N12 -> 913.5 | W12: 0.065 | X12: =N12*W12 -> 1696.5 | Y12: =Z12*0.00133 -> 0.01995 | Z12: 15 | AA12: =R12+T12+W12+Y12 -> 0.17595 | AB12: =N12*AA12+AK12 -> 4814.145 | AC12: 0 | AD12: =(N12-M12)*AC12 -> 0 | AE12: =17.5 -> 17.5 | AF12: =N12-M12-Q12-AB12-AD12-AE12 -> 127.355 | AG12: =AF12/N12 -> 0.0048795019 | AH12: =N12-AB12-AI12 -> 20765.16 | AI12: =Y12*N12 -> 520.695 | AJ12: 0.0085 | AK12: =AJ12*N12 -> 221.85
A13: 46118 | B13: 968 | D13: GUARULHOS | E13: SP | F13: GUARULHOS | G13: SP | H13: CYA RUBBER | I13: FINALIZADO | J13: SIM | K13: EGINELSON DE SOUZA | M13: 660 | N13: 1150 | O13: 50000 | P13: 0.0003 | Q13: =O13*P13 -> 15 | R13: 0.12 | S13: =R13*N13 -> 138 | T13: 0 | U13: 1 | V13: =T13*N13 -> 0 | W13: 0.065 | X13: =N13*W13 -> 74.75 | Y13: =Z13*0.00133 -> 0.01995 | Z13: 15 | AA13: =R13+T13+W13+Y13 -> 0.20495 | AB13: =N13*AA13+AK13 -> 245.4675 | AC13: 0.08 | AD13: =(N13-M13)*AC13 -> 39.2 | AE13: =17.5 -> 17.5 | AF13: =N13-M13-Q13-AB13-AD13-AE13 -> 172.8325 | AG13: =AF13/N13 -> 0.15028913 | AH13: =N13-AB13-AI13 -> 881.59 | AI13: =Y13*N13 -> 22.9425 | AJ13: 0.0085 | AK13: =AJ13*N13 -> 9.775
A14: 46118 | B14: 958 - 959 | D14: SANTO ANDRE | E14: SP | F14: BRASILIA | G14: DF | H14: ACTOS | I14: FINALIZADO | J14: SIM | K14: ILOIR EDSON | M14: 10320 | N14: 12900 | O14: 100000 | P14: 0.0003 | Q14: =O14*P14 -> 30 | R14: 0.056 | S14: =R14*N14 -> 722.4 | T14: 0.035 | U14: 1 | V14: =T14*N14 -> 451.5 | W14: 0.065 | X14: =N14*W14 -> 838.5 | Y14: =Z14*0.00133 -> 0.01995 | Z14: 15 | AA14: =R14+T14+W14+Y14 -> 0.17595 | AB14: =N14*AA14+AK14 -> 2379.405 | AC14: 0 | AD14: =(N14-M14)*AC14 -> 0 | AE14: =17.5 -> 17.5 | AF14: =N14-M14-Q14-AB14-AD14-AE14 -> 153.095 | AG14: =AF14/N14 -> 0.011867829 | AH14: =N14-AB14-AI14 -> 10263.24 | AI14: =Y14*N14 -> 257.355 | AJ14: 0.0085 | AK14: =AJ14*N14 -> 109.65
A15: 46119 | B15: 1041 | D15: ITAJAI | E15: SC | F15: SAO LEOPOLDO | G15: RS | H15: CYA RUBBER | I15: FINALIZADO | J15: SIM | K15: LAISE DA SILVA | M15: 4510 | N15: 7000 | O15: 100000 | P15: 0.0003 | Q15: =O15*P15 -> 30 | R15: 0.12 | S15: =R15*N15 -> 840 | T15: 0 | U15: 1 | V15: =T15*N15 -> 0 | W15: 0.065 | X15: =N15*W15 -> 455 | Y15: =Z15*0.00133 -> 0.01995 | Z15: 15 | AA15: =R15+T15+W15+Y15 -> 0.20495 | AB15: =N15*AA15+AK15 -> 1494.15 | AC15: 0.06 | AD15: =(N15-M15)*AC15 -> 149.4 | AE15: =17.5 -> 17.5 | AF15: =N15-M15-Q15-AB15-AD15-AE15 -> 798.95 | AG15: =AF15/N15 -> 0.11413571 | AH15: =N15-AB15-AI15 -> 5366.2 | AI15: =Y15*N15 -> 139.65 | AJ15: 0.0085 | AK15: =AJ15*N15 -> 59.5
A16: 46119 | B16: 994 | D16: ROCA SALES | E16: RS | F16: SAO LEOPOLDO | G16: RS | H16: QUISVI | I16: FINALIZADO | J16: SIM | K16: JESLEY ROMANI | M16: 500 | N16: 1200 | O16: 20000 | P16: 0.0003 | Q16: =O16*P16 -> 6 | R16: 0 | S16: =R16*N16 -> 0 | T16: 0 | U16: 1 | V16: =T16*N16 -> 0 | W16: 0.065 | X16: =N16*W16 -> 78 | Y16: =Z16*0.00133 -> 0.01995 | Z16: 15 | AA16: =R16+T16+W16+Y16 -> 0.08495 | AB16: =N16*AA16+AK16 -> 112.14 | AC16: 0.13 | AD16: =(N16-M16)*AC16 -> 91 | AE16: =17.5 -> 17.5 | AF16: =N16-M16-Q16-AB16-AD16-AE16 -> 473.36 | AG16: =AF16/N16 -> 0.39446667 | AH16: =N16-AB16-AI16 -> 1063.92 | AI16: =Y16*N16 -> 23.94 | AJ16: 0.0085 | AK16: =AJ16*N16 -> 10.2
A17: 46119 | B17: 995 | D17: SANTO ANDRE | E17: SP | F17: GOIANIA | G17: GO | H17: ACTOS | I17: FINALIZADO | J17: SIM | K17: EVANDRO VANDERLEI | M17: 9000 | N17: 11400 | O17: 286012.07 | P17: 0.0003 | Q17: =O17*P17 -> 85.803621 | R17: 0.056 | S17: =R17*N17 -> 638.4 | T17: 0.035 | U17: 1 | V17: =T17*N17 -> 399 | W17: 0.065 | X17: =N17*W17 -> 741 | Y17: =Z17*0.00133 -> 0.01995 | Z17: 15 | AA17: =R17+T17+W17+Y17 -> 0.17595 | AB17: =N17*AA17+AK17 -> 2102.73 | AC17: 0 | AD17: =(N17-M17)*AC17 -> 0 | AE17: =17.5 -> 17.5 | AF17: =N17-M17-Q17-AB17-AD17-AE17 -> 193.96638 | AG17: =AF17/N17 -> 0.017014595 | AH17: =N17-AB17-AI17 -> 9069.84 | AI17: =Y17*N17 -> 227.43 | AJ17: 0.0085 | AK17: =AJ17*N17 -> 96.9
A18: 46120 | B18: 1044 | D18: GUARULHOS | E18: SP | F18: SALTO | G18: SP | H18: CYA RUBBER | I18: FINALIZADO | J18: SIM | K18: ALMIR FERREIRA | M18: 1100 | N18: 2200 | O18: 100000 | P18: 0.0003 | Q18: =O18*P18 -> 30 | R18: 0.12 | S18: =R18*N18 -> 264 | T18: 0 | U18: 1 | V18: =T18*N18 -> 0 | W18: 0.065 | X18: =N18*W18 -> 143 | Y18: =Z18*0.00133 -> 0.01995 | Z18: 15 | AA18: =R18+T18+W18+Y18 -> 0.20495 | AB18: =N18*AA18+AK18 -> 469.59 | AC18: 0.13 | AD18: =(N18-M18)*AC18 -> 143 | AE18: =17.5 -> 17.5 | AF18: =N18-M18-Q18-AB18-AD18-AE18 -> 439.91 | AG18: =AF18/N18 -> 0.19995909 | AH18: =N18-AB18-AI18 -> 1686.52 | AI18: =Y18*N18 -> 43.89 | AJ18: 0.0085 | AK18: =AJ18*N18 -> 18.7
A19: 46120 | B19: 1051 | D19: ROCA SALES | E19: RS | F19: SAO LEOPOLDO | G19: RS | H19: QUISVI | I19: FINALIZADO | J19: SIM | K19: EMERSON FELIPE | M19: 1268.53 | N19: 2300 | O19: 6120 | P19: 0.0003 | Q19: =O19*P19 -> 1.836 | R19: 0 | S19: =R19*N19 -> 0 | T19: 0 | U19: 1 | V19: =T19*N19 -> 0 | W19: 0.065 | X19: =N19*W19 -> 149.5 | Y19: =Z19*0.00133 -> 0.01995 | Z19: 15 | AA19: =R19+T19+W19+Y19 -> 0.08495 | AB19: =N19*AA19+AK19 -> 214.935 | AC19: 0.13 | AD19: =(N19-M19)*AC19 -> 134.0911 | AE19: =17.5 -> 17.5 | AF19: =N19-M19-Q19-AB19-AD19-AE19 -> 663.1079 | AG19: =AF19/N19 -> 0.28830778 | AH19: =N19-AB19-AI19 -> 2039.18 | AI19: =Y19*N19 -> 45.885 | AJ19: 0.0085 | AK19: =AJ19*N19 -> 19.55
A20: 46120 | B20: 1063 - 1065 - 1066 - 1067 | D20: GOIANIA | E20: GO | F20: VARZEA GRANDE | G20: MT | H20: UNIFORT | I20: FINALIZADO | J20: SIM | K20: ANTONIO DE SOUZA | M20: 5200 | N20: 8500 | O20: 104000 | P20: 0.0003 | Q20: =O20*P20 -> 31.2 | R20: 0.03 | S20: =R20*N20 -> 255 | T20: 0.035 | U20: 1 | V20: =T20*N20 -> 297.5 | W20: 0.065 | X20: =N20*W20 -> 552.5 | Y20: =Z20*0.00133 -> 0.01995 | Z20: 15 | AA20: =R20+T20+W20+Y20 -> 0.14995 | AB20: =N20*AA20+AK20 -> 1346.825 | AC20: 0.1 | AD20: =(N20-M20)*AC20 -> 330 | AE20: =17.5 -> 17.5 | AF20: =N20-M20-Q20-AB20-AD20-AE20 -> 1574.475 | AG20: =AF20/N20 -> 0.18523235 | AH20: =N20-AB20-AI20 -> 6983.6 | AI20: =Y20*N20 -> 169.575 | AJ20: 0.0085 | AK20: =AJ20*N20 -> 72.25
A21: 46120 | B21: 1068 - 1069 - 1071 - 1072 - 1073 - 1074 | D21: GOIANIA | E21: GO | F21: MARABA | G21: PA | H21: UNIFORT | I21: FINALIZADO | J21: SIM | K21: JOSE CARLOS GOMES | M21: 7000 | N21: 11500 | O21: 100000 | P21: 0.0003 | Q21: =O21*P21 -> 30 | R21: 0.03 | S21: =R21*N21 -> 345 | T21: 0.035 | U21: 1 | V21: =T21*N21 -> 402.5 | W21: 0.065 | X21: =N21*W21 -> 747.5 | Y21: =Z21*0.00133 -> 0.01995 | Z21: 15 | AA21: =R21+T21+W21+Y21 -> 0.14995 | AB21: =N21*AA21+AK21 -> 1822.175 | AC21: 0.1 | AD21: =(N21-M21)*AC21 -> 450 | AE21: =17.5 -> 17.5 | AF21: =N21-M21-Q21-AB21-AD21-AE21 -> 2180.325 | AG21: =AF21/N21 -> 0.18959348 | AH21: =N21-AB21-AI21 -> 9448.4 | AI21: =Y21*N21 -> 229.425 | AJ21: 0.0085 | AK21: =AJ21*N21 -> 97.75
A22: 46120 | B22: 1076 - 1077 - 1078 | D22: SANTO ANDRE | E22: SP | F22: BELO HORIZONTE | G22: MG | H22: ACTOS | I22: FINALIZADO | J22: SIM | K22: DIEGO AUGUSTO FALEIRO | M22: 6500 | N22: 7600 | O22: 295738.5 | P22: 0.0003 | Q22: =O22*P22 -> 88.72155 | R22: 0.12 | S22: =R22*N22 -> 912 | T22: 0 | U22: 1 | V22: =T22*N22 -> 0 | W22: 0.065 | X22: =N22*W22 -> 494 | Y22: =Z22*0.00133 -> 0.01995 | Z22: 15 | AA22: =R22+T22+W22+Y22 -> 0.20495 | AB22: =N22*AA22+AK22 -> 1622.22 | AC22: 0 | AD22: =(N22-M22)*AC22 -> 0 | AE22: =17.5 -> 17.5 | AF22: =N22-M22-Q22-AB22-AD22-AE22 -> -628.44155 | AG22: =AF22/N22 -> -0.082689678 | AH22: =N22-AB22-AI22 -> 5826.16 | AI22: =Y22*N22 -> 151.62 | AJ22: 0.0085 | AK22: =AJ22*N22 -> 64.6
A23: 46121 | B23: 1098 - 1099 | D23: SANTO ANDRE | E23: SP | F23: CURITIBA | G23: PR | H23: ACTOS | I23: FINALIZADO | J23: SIM | K23: JANIR BERNARDI | M23: 4010 | N23: 5200 | O23: 200000 | P23: 0.0003 | Q23: =O23*P23 -> 60 | R23: 0.12 | S23: =R23*N23 -> 624 | T23: 0 | U23: 1 | V23: =T23*N23 -> 0 | W23: 0.065 | X23: =N23*W23 -> 338 | Y23: =Z23*0.00133 -> 0.01995 | Z23: 15 | AA23: =R23+T23+W23+Y23 -> 0.20495 | AB23: =N23*AA23+AK23 -> 1109.94 | AC23: 0 | AD23: =(N23-M23)*AC23 -> 0 | AE23: =17.5 -> 17.5 | AF23: =N23-M23-Q23-AB23-AD23-AE23 -> 2.56 | AG23: =AF23/N23 -> 0.00049230769 | AH23: =N23-AB23-AI23 -> 3986.32 | AI23: =Y23*N23 -> 103.74 | AJ23: 0.0085 | AK23: =AJ23*N23 -> 44.2
A24: 46121 | B24: 1117 | D24: VIÇOSA | E24: MG | F24: BETIM | G24: MG | H24: TRYUMPHO | I24: FINALIZADO | J24: SIM | K24: JOSE PRUDENCIO DA SILVA | M24: 7560 | N24: 6900 | O24: 950000 | P24: 0.0003 | Q24: =O24*P24 -> 285 | R24: 0 | S24: =R24*N24 -> 0 | T24: 0 | U24: 1 | V24: =T24*N24 -> 0 | W24: 0.065 | X24: =N24*W24 -> 448.5 | Y24: =Z24*0.00133 -> 0.01995 | Z24: 15 | AA24: =R24+T24+W24+Y24 -> 0.08495 | AB24: =N24*AA24+AK24 -> 644.805 | AC24: 0 | AD24: =(N24-M24)*AC24 -> 0 | AE24: =17.5 -> 17.5 | AF24: =N24-M24-Q24-AB24-AD24-AE24 -> -1607.305 | AG24: =AF24/N24 -> -0.23294275 | AH24: =N24-AB24-AI24 -> 6117.54 | AI24: =Y24*N24 -> 137.655 | AJ24: 0.0085 | AK24: =AJ24*N24 -> 58.65
A25: 46122 | B25: 1154 | D25: SAO LEOPOLDO | E25: RS | F25: GUARULHOS | G25: SP | H25: CYA RUBBER | I25: FINALIZADO | J25: SIM | K25: RAFAEL WALOSKI | M25: 8400 | N25: 11000 | O25: 300000 | P25: 0.0003 | Q25: =O25*P25 -> 90 | R25: 0.12 | S25: =R25*N25 -> 1320 | T25: 0 | U25: 1 | V25: =T25*N25 -> 0 | W25: 0.065 | X25: =N25*W25 -> 715 | Y25: =Z25*0.00133 -> 0.01995 | Z25: 15 | AA25: =R25+T25+W25+Y25 -> 0.20495 | AB25: =N25*AA25+AK25 -> 2347.95 | AC25: 0 | AD25: =(N25-M25)*AC25 -> 0 | AE25: =17.5 -> 17.5 | AF25: =N25-M25-Q25-AB25-AD25-AE25 -> 144.55 | AG25: =AF25/N25 -> 0.013140909 | AH25: =N25-AB25-AI25 -> 8432.6 | AI25: =Y25*N25 -> 219.45 | AJ25: 0.0085 | AK25: =AJ25*N25 -> 93.5
A26: 46122 | B26: 1161 1162 1163 | D26: SANTO ANDRE | E26: SP | F26: FORTALEZA | G26: CE | H26: ACTOS | I26: FINALIZADO | J26: SIM | K26: FERNANDO LOCKS | M26: 25060 | N26: 28400 | O26: 350000 | P26: 0.0003 | Q26: =O26*P26 -> 105 | R26: 0.056 | S26: =R26*N26 -> 1590.4 | T26: 0.035 | U26: 1 | V26: =T26*N26 -> 994 | W26: 0.065 | X26: =N26*W26 -> 1846 | Y26: =Z26*0.00133 -> 0.01995 | Z26: 15 | AA26: =R26+T26+W26+Y26 -> 0.17595 | AB26: =N26*AA26+AK26 -> 5238.38 | AC26: 0 | AD26: =(N26-M26)*AC26 -> 0 | AE26: =17.5 -> 17.5 | AF26: =N26-M26-Q26-AB26-AD26-AE26 -> -2020.88 | AG26: =AF26/N26 -> -0.071157746 | AH26: =N26-AB26-AI26 -> 22595.04 | AI26: =Y26*N26 -> 566.58 | AJ26: 0.0085 | AK26: =AJ26*N26 -> 241.4
A27: 46122 | B27: 1155 | D27: VIANA | E27: ES | F27: CAJURU | G27: SP | H27: CYA RUBBER | I27: FINALIZADO | J27: SIM | K27: LUIZ FERNANDO ANTUNES | M27: 8360 | N27: 11400 | O27: 300000 | P27: 0.0003 | Q27: =O27*P27 -> 90 | R27: 0.12 | S27: =R27*N27 -> 1368 | T27: 0 | U27: 1 | V27: =T27*N27 -> 0 | W27: 0.065 | X27: =N27*W27 -> 741 | Y27: =Z27*0.00133 -> 0.01995 | Z27: 15 | AA27: =R27+T27+W27+Y27 -> 0.20495 | AB27: =N27*AA27+AK27 -> 2433.33 | AC27: 0 | AD27: =(N27-M27)*AC27 -> 0 | AE27: =17.5 -> 17.5 | AF27: =N27-M27-Q27-AB27-AD27-AE27 -> 499.17 | AG27: =AF27/N27 -> 0.043786842 | AH27: =N27-AB27-AI27 -> 8739.24 | AI27: =Y27*N27 -> 227.43 | AJ27: 0.0085 | AK27: =AJ27*N27 -> 96.9
A28: 46123 | B28: 1188 - 1189 - 1190 | D28: BETIM | E28: MG | F28: GOIANIA | G28: GO | H28: UNIFORT | I28: FINALIZADO | J28: SIM | K28: DIEGO AUGUSTO FALEIRO | M28: 9060 | N28: 14400 | O28: 500000 | P28: 0.0003 | Q28: =O28*P28 -> 150 | R28: 0.03 | S28: =R28*N28 -> 432 | T28: 0.035 | U28: 1 | V28: =T28*N28 -> 504 | W28: 0.065 | X28: =N28*W28 -> 936 | Y28: =Z28*0.00133 -> 0.01995 | Z28: 15 | AA28: =R28+T28+W28+Y28 -> 0.14995 | AB28: =N28*AA28+AK28 -> 2281.68 | AC28: 0.1 | AD28: =(N28-M28)*AC28 -> 534 | AE28: =17.5 -> 17.5 | AF28: =N28-M28-Q28-AB28-AD28-AE28 -> 2356.82 | AG28: =AF28/N28 -> 0.16366806 | AH28: =N28-AB28-AI28 -> 11831.04 | AI28: =Y28*N28 -> 287.28 | AJ28: 0.0085 | AK28: =AJ28*N28 -> 122.4
A29: 46123 | B29: 1192 | D29: BETIM | E29: MG | F29: VITORIA DA CONQUISTA | G29: BA | H29: UNIFORT | I29: FINALIZADO | J29: SIM | K29: ANDERSON DARE | M29: 9060 | N29: 11600 | O29: 500000 | P29: 0.0003 | Q29: =O29*P29 -> 150 | R29: 0.056 | S29: =R29*N29 -> 649.6 | T29: 0.035 | U29: 1 | V29: =T29*N29 -> 406 | W29: 0.065 | X29: =N29*W29 -> 754 | Y29: =Z29*0.00133 -> 0.01995 | Z29: 15 | AA29: =R29+T29+W29+Y29 -> 0.17595 | AB29: =N29*AA29+AK29 -> 2139.62 | AC29: 0 | AD29: =(N29-M29)*AC29 -> 0 | AE29: =17.5 -> 17.5 | AF29: =N29-M29-Q29-AB29-AD29-AE29 -> 232.88 | AG29: =AF29/N29 -> 0.020075862 | AH29: =N29-AB29-AI29 -> 9228.96 | AI29: =Y29*N29 -> 231.42 | AJ29: 0.0085 | AK29: =AJ29*N29 -> 98.6
A30: 46124 | B30: 1193 - 1194 | D30: GOIANIA | E30: GO | F30: VARZEA GRANDE | G30: MT | H30: UNIFORT | I30: FINALIZADO | J30: SIM | K30: ALINE KEMPFER | M30: 5460 | N30: 8600 | O30: 104000 | P30: 0.0003 | Q30: =O30*P30 -> 31.2 | R30: 0.03 | S30: =R30*N30 -> 258 | T30: 0.035 | U30: 1 | V30: =T30*N30 -> 301 | W30: 0.065 | X30: =N30*W30 -> 559 | Y30: =Z30*0.00133 -> 0.01995 | Z30: 15 | AA30: =R30+T30+W30+Y30 -> 0.14995 | AB30: =N30*AA30+AK30 -> 1362.67 | AC30: 0.1 | AD30: =(N30-M30)*AC30 -> 314 | AE30: =17.5 -> 17.5 | AF30: =N30-M30-Q30-AB30-AD30-AE30 -> 1414.63 | AG30: =AF30/N30 -> 0.16449186 | AH30: =N30-AB30-AI30 -> 7065.76 | AI30: =Y30*N30 -> 171.57 | AJ30: 0.0085 | AK30: =AJ30*N30 -> 73.1
A31: 46124 | B31: 1195 - 1196 | D31: GOIANIA | E31: GO | F31: MARABA | G31: PA | H31: UNIFORT | I31: FINALIZADO | J31: SIM | K31: ANTONIO FAUSTO | M31: 7560 | N31: 11900 | O31: 100000 | P31: 0.0003 | Q31: =O31*P31 -> 30 | R31: 0.03 | S31: =R31*N31 -> 357 | T31: 0.035 | U31: 1 | V31: =T31*N31 -> 416.5 | W31: 0.065 | X31: =N31*W31 -> 773.5 | Y31: =Z31*0.00133 -> 0.01995 | Z31: 15 | AA31: =R31+T31+W31+Y31 -> 0.14995 | AB31: =N31*AA31+AK31 -> 1885.555 | AC31: 0.1 | AD31: =(N31-M31)*AC31 -> 434 | AE31: =17.5 -> 17.5 | AF31: =N31-M31-Q31-AB31-AD31-AE31 -> 1972.945 | AG31: =AF31/N31 -> 0.1657937 | AH31: =N31-AB31-AI31 -> 9777.04 | AI31: =Y31*N31 -> 237.405 | AJ31: 0.0085 | AK31: =AJ31*N31 -> 101.15
A32: 46125 | B32: 1205 | D32: GUARULHOS | E32: SP | F32: SALTO | G32: SP | H32: CYA RUBBER | I32: FINALIZADO | J32: SIM | K32: AGNALDO | M32: 1230 | N32: 2200 | O32: 80000 | P32: 0.0003 | Q32: =O32*P32 -> 24 | R32: 0.12 | S32: =R32*N32 -> 264 | T32: 0 | U32: 1 | V32: =T32*N32 -> 0 | W32: 0.065 | X32: =N32*W32 -> 143 | Y32: =Z32*0.00133 -> 0.01995 | Z32: 15 | AA32: =R32+T32+W32+Y32 -> 0.20495 | AB32: =N32*AA32+AK32 -> 469.59 | AC32: 0.13 | AD32: =(N32-M32)*AC32 -> 126.1 | AE32: =17.5 -> 17.5 | AF32: =N32-M32-Q32-AB32-AD32-AE32 -> 332.81 | AG32: =AF32/N32 -> 0.15127727 | AH32: =N32-AB32-AI32 -> 1686.52 | AI32: =Y32*N32 -> 43.89 | AJ32: 0.0085 | AK32: =AJ32*N32 -> 18.7
A33: 46125 | B33: 1217 | D33: SANTO ANDRE | E33: SP | F33: GOIANIA | G33: GO | H33: ACTOS | I33: FINALIZADO | J33: SIM | K33: ROBISON GONÇALVES | M33: 9560 | N33: 11400 | O33: 170000 | P33: 0.0003 | Q33: =O33*P33 -> 51 | R33: 0.056 | S33: =R33*N33 -> 638.4 | T33: 0.035 | U33: 1 | V33: =T33*N33 -> 399 | W33: 0.065 | X33: =N33*W33 -> 741 | Y33: =Z33*0.00133 -> 0.01995 | Z33: 15 | AA33: =R33+T33+W33+Y33 -> 0.17595 | AB33: =N33*AA33+AK33 -> 2102.73 | AC33: 0 | AD33: 400 | AE33: =17.5 -> 17.5 | AF33: =N33-M33-Q33-AB33-AD33-AE33 -> -731.23 | AG33: =AF33/N33 -> -0.064142982 | AH33: =N33-AB33-AI33 -> 9069.84 | AI33: =Y33*N33 -> 227.43 | AJ33: 0.0085 | AK33: =AJ33*N33 -> 96.9
A34: 46126 | B34: 1245 | D34: ROCA SALES | E34: RS | F34: SAO LEOPOLDO | G34: RS | H34: QUISVI | I34: FINALIZADO | J34: SIM | K34: JESLEY ROMANI | M34: 610 | N34: 1300 | O34: 50000 | P34: 0.0003 | Q34: =O34*P34 -> 15 | R34: 0 | S34: =R34*N34 -> 0 | T34: 0 | U34: 1 | V34: =T34*N34 -> 0 | W34: 0.065 | X34: =N34*W34 -> 84.5 | Y34: =Z34*0.00133 -> 0.01995 | Z34: 15 | AA34: =R34+T34+W34+Y34 -> 0.08495 | AB34: =N34*AA34+AK34 -> 121.485 | AC34: 0.13 | AD34: =(N34-M34)*AC34 -> 89.7 | AE34: =17.5 -> 17.5 | AF34: =N34-M34-Q34-AB34-AD34-AE34 -> 446.315 | AG34: =AF34/N34 -> 0.34331923 | AH34: =N34-AB34-AI34 -> 1152.58 | AI34: =Y34*N34 -> 25.935 | AJ34: 0.0085 | AK34: =AJ34*N34 -> 11.05
A35: 46127 | B35: 1308 | D35: SANTO ANDRE | E35: SP | F35: BRASILIA | G35: DF | H35: ACTOS | I35: FINALIZADO | J35: SIM | K35: JOEL JOSE | M35: 9760 | N35: 12400 | O35: 200000 | P35: 0.0003 | Q35: =O35*P35 -> 60 | R35: 0.056 | S35: =R35*N35 -> 694.4 | T35: 0.035 | U35: 1 | V35: =T35*N35 -> 434 | W35: 0.065 | X35: =N35*W35 -> 806 | Y35: =Z35*0.00133 -> 0.01995 | Z35: 15 | AA35: =R35+T35+W35+Y35 -> 0.17595 | AB35: =N35*AA35+AK35 -> 2287.18 | AC35: 0 | AD35: =(N35-M35)*AC35 -> 0 | AE35: =17.5 -> 17.5 | AF35: =N35-M35-Q35-AB35-AD35-AE35 -> 275.32 | AG35: =AF35/N35 -> 0.022203226 | AH35: =N35-AB35-AI35 -> 9865.44 | AI35: =Y35*N35 -> 247.38 | AJ35: 0.0085 | AK35: =AJ35*N35 -> 105.4
A36: 46128 | B36: 1368 | D36: GUARULHOS | E36: SP | F36: FRANCA | G36: SP | H36: CYA RUBBER | I36: FINALIZADO | J36: SIM | K36: SILVIO FRANCISCO | M36: 4740 | N36: 7650 | O36: 400000 | P36: 0.0003 | Q36: =O36*P36 -> 120 | R36: 0.12 | S36: =R36*N36 -> 918 | T36: 0 | U36: 1 | V36: =T36*N36 -> 0 | W36: 0.065 | X36: =N36*W36 -> 497.25 | Y36: =Z36*0.00133 -> 0.01995 | Z36: 15 | AA36: =R36+T36+W36+Y36 -> 0.20495 | AB36: =N36*AA36+AK36 -> 1632.8925 | AC36: 0.07 | AD36: =(N36-M36)*AC36 -> 203.7 | AE36: =17.5 -> 17.5 | AF36: =N36-M36-Q36-AB36-AD36-AE36 -> 935.9075 | AG36: =AF36/N36 -> 0.12234085 | AH36: =N36-AB36-AI36 -> 5864.49 | AI36: =Y36*N36 -> 152.6175 | AJ36: 0.0085 | AK36: =AJ36*N36 -> 65.025
A37: 46128 | B37: 1327 - 1328 | D37: GUARULHOS | E37: SP | F37: MAUA | G37: SP | H37: CYA RUBBER | I37: FINALIZADO | J37: SIM | K37: GUILHERME GUIMARAES | M37: 760 | N37: 1500 | O37: 50000 | P37: 0.0003 | Q37: =O37*P37 -> 15 | R37: 0.12 | S37: =R37*N37 -> 180 | T37: 0 | U37: 1 | V37: =T37*N37 -> 0 | W37: 0.065 | X37: =N37*W37 -> 97.5 | Y37: =Z37*0.00133 -> 0.01995 | Z37: 15 | AA37: =R37+T37+W37+Y37 -> 0.20495 | AB37: =N37*AA37+AK37 -> 320.175 | AC37: 0.13 | AD37: =(N37-M37)*AC37 -> 96.2 | AE37: =17.5 -> 17.5 | AF37: =N37-M37-Q37-AB37-AD37-AE37 -> 291.125 | AG37: =AF37/N37 -> 0.19408333 | AH37: =N37-AB37-AI37 -> 1149.9 | AI37: =Y37*N37 -> 29.925 | AJ37: 0.0085 | AK37: =AJ37*N37 -> 12.75
A38: 46128 | B38: 1347 1348 | D38: ROCA SALES | E38: RS | F38: CAMPO BOM | G38: RS | H38: QUISVI | I38: FINALIZADO | J38: SIM | K38: LUIS FILIPE PEREIRA | M38: 660 | N38: 1400 | O38: 50000 | P38: 0.0003 | Q38: =O38*P38 -> 15 | R38: 0 | S38: =R38*N38 -> 0 | T38: 0 | U38: 1 | V38: =T38*N38 -> 0 | W38: 0.065 | X38: =N38*W38 -> 91 | Y38: =Z38*0.00133 -> 0.01995 | Z38: 15 | AA38: =R38+T38+W38+Y38 -> 0.08495 | AB38: =N38*AA38+AK38 -> 130.83 | AC38: 0.13 | AD38: =(N38-M38)*AC38 -> 96.2 | AE38: =17.5 -> 17.5 | AF38: =N38-M38-Q38-AB38-AD38-AE38 -> 480.47 | AG38: =AF38/N38 -> 0.34319286 | AH38: =N38-AB38-AI38 -> 1241.24 | AI38: =Y38*N38 -> 27.93 | AJ38: 0.0085 | AK38: =AJ38*N38 -> 11.9
A39: 46129 | B39: 1393 | D39: GUARULHOS | E39: SP | F39: DIADEMA | G39: SP | H39: CYA RUBBER | I39: FINALIZADO | J39: SIM | K39: EDMILSON DE SOUZA | M39: 960 | N39: 1630 | O39: 50000 | P39: 0.0003 | Q39: =O39*P39 -> 15 | R39: 0.12 | S39: =R39*N39 -> 195.6 | T39: 0 | U39: 1 | V39: =T39*N39 -> 0 | W39: 0.065 | X39: =N39*W39 -> 105.95 | Y39: =Z39*0.00133 -> 0.01995 | Z39: 15 | AA39: =R39+T39+W39+Y39 -> 0.20495 | AB39: =N39*AA39+AK39 -> 347.9235 | AC39: 0.07 | AD39: =(N39-M39)*AC39 -> 46.9 | AE39: =17.5 -> 17.5 | AF39: =N39-M39-Q39-AB39-AD39-AE39 -> 242.6765 | AG39: =AF39/N39 -> 0.14888129 | AH39: =N39-AB39-AI39 -> 1249.558 | AI39: =Y39*N39 -> 32.5185 | AJ39: 0.0085 | AK39: =AJ39*N39 -> 13.855
A40: 46129 | B40: 1413 - 1414 - 1416 - 1417 | D40: GOIANIA | E40: GO | F40: VARZEA GRANDE | G40: MT | H40: UNIFORT | I40: FINALIZADO | J40: SIM | K40: ANTONIO DE SOUZA | M40: 5360 | N40: 8600 | O40: 100000 | P40: 0.0003 | Q40: =O40*P40 -> 30 | R40: 0.03 | S40: =R40*N40 -> 258 | T40: 0.035 | U40: 1 | V40: =T40*N40 -> 301 | W40: 0.065 | X40: =N40*W40 -> 559 | Y40: =Z40*0.00133 -> 0.01995 | Z40: 15 | AA40: =R40+T40+W40+Y40 -> 0.14995 | AB40: =N40*AA40+AK40 -> 1362.67 | AC40: 0.1 | AD40: =(N40-M40)*AC40 -> 324 | AE40: =17.5 -> 17.5 | AF40: =N40-M40-Q40-AB40-AD40-AE40 -> 1505.83 | AG40: =AF40/N40 -> 0.17509651 | AH40: =N40-AB40-AI40 -> 7065.76 | AI40: =Y40*N40 -> 171.57 | AJ40: 0.0085 | AK40: =AJ40*N40 -> 73.1
A41: 46129 | B41: 1419 - 1420 - 1421 - 1423 - 1425 - 1426 | D41: GOIANIA | E41: GO | F41: MARABA | G41: PA | H41: UNIFORT | I41: FINALIZADO | J41: SIM | K41: UILDES ROCHA | M41: 7740 | N41: 12500 | O41: 100000 | P41: 0.0003 | Q41: =O41*P41 -> 30 | R41: 0.03 | S41: =R41*N41 -> 375 | T41: 0.035 | U41: 1 | V41: =T41*N41 -> 437.5 | W41: 0.065 | X41: =N41*W41 -> 812.5 | Y41: =Z41*0.00133 -> 0.01995 | Z41: 15 | AA41: =R41+T41+W41+Y41 -> 0.14995 | AB41: =N41*AA41+AK41 -> 1980.625 | AC41: 0.1 | AD41: =(N41-M41)*AC41 -> 476 | AE41: =17.5 -> 17.5 | AF41: =N41-M41-Q41-AB41-AD41-AE41 -> 2255.875 | AG41: =AF41/N41 -> 0.18047 | AH41: =N41-AB41-AI41 -> 10270 | AI41: =Y41*N41 -> 249.375 | AJ41: 0.0085 | AK41: =AJ41*N41 -> 106.25
A42: 46134 | B42: 1497 1498 | D42: GUARULHOS | E42: SP | F42: SALTO | G42: SP | H42: CYA RUBBER | I42: FINALIZADO | J42: SIM | K42: EGINELSON DE SOUZA | M42: 1360 | N42: 2600 | O42: 100000 | P42: 0.0003 | Q42: =O42*P42 -> 30 | R42: 0.12 | S42: =R42*N42 -> 312 | T42: 0 | U42: 1 | V42: =T42*N42 -> 0 | W42: 0.065 | X42: =N42*W42 -> 169 | Y42: =Z42*0.00133 -> 0.01995 | Z42: 15 | AA42: =R42+T42+W42+Y42 -> 0.20495 | AB42: =N42*AA42+AK42 -> 554.97 | AC42: 0.13 | AD42: =(N42-M42)*AC42 -> 161.2 | AE42: =17.5 -> 17.5 | AF42: =N42-M42-Q42-AB42-AD42-AE42 -> 476.33 | AG42: =AF42/N42 -> 0.18320385 | AH42: =N42-AB42-AI42 -> 1993.16 | AI42: =Y42*N42 -> 51.87 | AJ42: 0.0085 | AK42: =AJ42*N42 -> 22.1
A43: 46134 | B43: 1515 | D43: SAO LEOPOLDO | E43: RS | F43: ROCA SALES | G43: RS | H43: CYA RUBBER | I43: FINALIZADO | J43: SIM | K43: EMERSON FELIPE | M43: 1260 | N43: 1950 | O43: 50000 | P43: 0.0003 | Q43: =O43*P43 -> 15 | R43: 0 | S43: =R43*N43 -> 0 | T43: 0 | U43: 1 | V43: =T43*N43 -> 0 | W43: 0.065 | X43: =N43*W43 -> 126.75 | Y43: =Z43*0.00133 -> 0.01995 | Z43: 15 | AA43: =R43+T43+W43+Y43 -> 0.08495 | AB43: =N43*AA43+AK43 -> 182.2275 | AC43: 0.13 | AD43: =(N43-M43)*AC43 -> 89.7 | AE43: =17.5 -> 17.5 | AF43: =N43-M43-Q43-AB43-AD43-AE43 -> 385.5725 | AG43: =AF43/N43 -> 0.19772949 | AH43: =N43-AB43-AI43 -> 1728.87 | AI43: =Y43*N43 -> 38.9025 | AJ43: 0.0085 | AK43: =AJ43*N43 -> 16.575
